{"version": 0.6, "generator": "Overpass API 0.7.59.2 0994154d", "osm3s": {"timestamp_osm_base": "2023-03-12T19:49:22Z", "copyright": "The data included in this document is from www.openstreetmap.org. The data is made available under ODbL."}, "elements": [{"type": "node", "id": 12453073, "lat": 50.7231144, "lon": 9.6491527}, {"type": "node", "id": 12453076, "lat": 50.7069236, "lon": 9.6726205}, {"type": "node", "id": 12453150, "lat": 50.7133101, "lon": 9.6605216}, {"type": "node", "id": 12453152, "lat": 50.7033481, "lon": 9.6770261}, {"type": "node", "id": 21464514, "lat": 50.7134388, "lon": 9.6607111}, {"type": "node", "id": 21464515, "lat": 50.7173419, "lon": 9.6545285}, {"type": "node", "id": 21464516, "lat": 50.7231842, "lon": 9.6493693}, {"type": "node", "id": 32011438, "lat": 50.7053136, "lon": 9.6748463}, {"type": "node", "id": 32011439, "lat": 50.7099402, "lon": 9.6677244}, {"type": "node", "id": 32011440, "lat": 50.7103488, "lon": 9.6664174}, {"type": "node", "id": 32011441, "lat": 50.7150539, "lon": 9.6578717}, {"type": "node", "id": 32011442, "lat": 50.7160584, "lon": 9.6558335}, {"type": "node", "id": 32011444, "lat": 50.7208078, "lon": 9.6510686}, {"type": "node", "id": 81715387, "lat": 50.7150583, "lon": 9.6582063}, {"type": "node", "id": 81715394, "lat": 50.7152883, "lon": 9.6576817}, {"type": "node", "id": 81715404, "lat": 50.7157585, "lon": 9.6567613}, {"type": "node", "id": 260441234, "lat": 50.7148429, "lon": 9.6577388, "tags": {"TMC:cid_58:tabcd_1:Class": "Point", "TMC:cid_58:tabcd_1:Direction": "negative", "TMC:cid_58:tabcd_1:LCLversion": "9.00", "TMC:cid_58:tabcd_1:LocationCode": "12303", "TMC:cid_58:tabcd_1:NextLocationCode": "59699", "TMC:cid_58:tabcd_1:PrevLocationCode": "59700", "highway": "motorway_junction", "name": "Rastst\u00e4tte Gro\u00dfenmoor", "noref": "yes"}}, {"type": "node", "id": 260441235, "lat": 50.7140115, "lon": 9.6586741}, {"type": "node", "id": 260441239, "lat": 50.7113809, "lon": 9.6638601}, {"type": "node", "id": 534889138, "lat": 50.7189041, "lon": 9.6523471}, {"type": "node", "id": 534889159, "lat": 50.7190505, "lon": 9.6526212}, {"type": "node", "id": 534889189, "lat": 50.7084171, "lon": 9.6701201}, {"type": "node", "id": 656633641, "lat": 50.7113276, "lon": 9.6617091}, {"type": "node", "id": 690920955, "lat": 50.7116775, "lon": 9.6610452}, {"type": "node", "id": 690921001, "lat": 50.7108737, "lon": 9.6625857}, {"type": "node", "id": 690921003, "lat": 50.7106526, "lon": 9.6634826}, {"type": "node", "id": 690921005, "lat": 50.7110014, "lon": 9.6646994}, {"type": "node", "id": 690921007, "lat": 50.7114266, "lon": 9.6652285}, {"type": "node", "id": 690921010, "lat": 50.7125399, "lon": 9.6653963}, {"type": "node", "id": 690921012, "lat": 50.7127396, "lon": 9.6653235}, {"type": "node", "id": 690921162, "lat": 50.7148205, "lon": 9.6620067}, {"type": "node", "id": 690921179, "lat": 50.7153961, "lon": 9.660967}, {"type": "node", "id": 690921180, "lat": 50.7159699, "lon": 9.6596936}, {"type": "node", "id": 690921186, "lat": 50.713061, "lon": 9.6651388}, {"type": "node", "id": 690921188, "lat": 50.7135412, "lon": 9.66467}, {"type": "node", "id": 690921190, "lat": 50.7139054, "lon": 9.6639573}, {"type": "node", "id": 774561858, "lat": 50.7140954, "lon": 9.6585706}, {"type": "node", "id": 774561874, "lat": 50.7144681, "lon": 9.6583436}, {"type": "node", "id": 924556490, "lat": 50.7053622, "lon": 9.6527559}, {"type": "node", "id": 924556492, "lat": 50.705937, "lon": 9.6528719}, {"type": "node", "id": 924556494, "lat": 50.7070641, "lon": 9.6531698}, {"type": "node", "id": 924556495, "lat": 50.7076964, "lon": 9.65339}, {"type": "node", "id": 924556496, "lat": 50.7078152, "lon": 9.6534901}, {"type": "node", "id": 924556499, "lat": 50.7078984, "lon": 9.6536084}, {"type": "node", "id": 924556502, "lat": 50.7079651, "lon": 9.6538583}, {"type": "node", "id": 924556514, "lat": 50.7080483, "lon": 9.6543054}, {"type": "node", "id": 924556517, "lat": 50.7081191, "lon": 9.6545422}, {"type": "node", "id": 924556520, "lat": 50.7085814, "lon": 9.6556074}, {"type": "node", "id": 926293596, "lat": 50.709042, "lon": 9.6567243}, {"type": "node", "id": 926293598, "lat": 50.7090862, "lon": 9.6568418}, {"type": "node", "id": 926293611, "lat": 50.7092086, "lon": 9.6570351}, {"type": "node", "id": 926293615, "lat": 50.7094297, "lon": 9.6573143}, {"type": "node", "id": 926293620, "lat": 50.7096677, "lon": 9.6575721}, {"type": "node", "id": 926293622, "lat": 50.7099194, "lon": 9.6578621}, {"type": "node", "id": 926293624, "lat": 50.7100282, "lon": 9.6580017}, {"type": "node", "id": 926293626, "lat": 50.7101268, "lon": 9.6582488}, {"type": "node", "id": 926293628, "lat": 50.7102527, "lon": 9.6586301}, {"type": "node", "id": 926293630, "lat": 50.7103513, "lon": 9.6589577}, {"type": "node", "id": 926293647, "lat": 50.7104261, "lon": 9.6592369}, {"type": "node", "id": 926293650, "lat": 50.7104499, "lon": 9.6595645}, {"type": "node", "id": 926293653, "lat": 50.7104465, "lon": 9.6598545}, {"type": "node", "id": 926293656, "lat": 50.7104737, "lon": 9.66008}, {"type": "node", "id": 926293658, "lat": 50.710824, "lon": 9.660848}, {"type": "node", "id": 926293662, "lat": 50.7109872, "lon": 9.6611971}, {"type": "node", "id": 926293665, "lat": 50.7111538, "lon": 9.6614869}, {"type": "node", "id": 926293690, "lat": 50.7107016, "lon": 9.6630855}, {"type": "node", "id": 926293694, "lat": 50.7106604, "lon": 9.6637927}, {"type": "node", "id": 926293696, "lat": 50.7107046, "lon": 9.6640922}, {"type": "node", "id": 926293697, "lat": 50.7108131, "lon": 9.664405}, {"type": "node", "id": 926293766, "lat": 50.7116641, "lon": 9.6653931}, {"type": "node", "id": 926293770, "lat": 50.7143991, "lon": 9.6627887}, {"type": "node", "id": 926293797, "lat": 50.7142856, "lon": 9.6617996}, {"type": "node", "id": 1585021777, "lat": 50.707617, "lon": 9.671505}, {"type": "node", "id": 1585021779, "lat": 50.7110451, "lon": 9.6650071}, {"type": "node", "id": 1585021784, "lat": 50.7112007, "lon": 9.6646836}, {"type": "node", "id": 1585021790, "lat": 50.7112243, "lon": 9.6651753}, {"type": "node", "id": 1585021796, "lat": 50.7113522, "lon": 9.6649119}, {"type": "node", "id": 1585021802, "lat": 50.7117755, "lon": 9.664071}, {"type": "node", "id": 1585021804, "lat": 50.7242038, "lon": 9.648824}, {"type": "node", "id": 1598126553, "lat": 50.7023047, "lon": 9.6780349}, {"type": "node", "id": 1598126589, "lat": 50.7043892, "lon": 9.6759027}, {"type": "node", "id": 1598126614, "lat": 50.7061061, "lon": 9.6737958}, {"type": "node", "id": 1598126619, "lat": 50.7070759, "lon": 9.672859}, {"type": "node", "id": 1598126642, "lat": 50.7076706, "lon": 9.6714187}, {"type": "node", "id": 1598126647, "lat": 50.7078385, "lon": 9.6716495}, {"type": "node", "id": 1598126682, "lat": 50.7086115, "lon": 9.6703056}, {"type": "node", "id": 1598126768, "lat": 50.711665, "lon": 9.6642811, "tags": {"TMC:cid_58:tabcd_1:Class": "Point", "TMC:cid_58:tabcd_1:Direction": "positive", "TMC:cid_58:tabcd_1:LCLversion": "9.00", "TMC:cid_58:tabcd_1:LocationCode": "12303", "TMC:cid_58:tabcd_1:NextLocationCode": "59699", "TMC:cid_58:tabcd_1:PrevLocationCode": "59700", "highway": "motorway_junction", "name": "Rastst\u00e4tte Gro\u00dfenmoor", "noref": "yes"}}, {"type": "node", "id": 1598126774, "lat": 50.711356, "lon": 9.6641089}, {"type": "node", "id": 1598126860, "lat": 50.7171465, "lon": 9.6543548}, {"type": "node", "id": 1598126870, "lat": 50.7180018, "lon": 9.6533389}, {"type": "node", "id": 1598126875, "lat": 50.7181789, "lon": 9.6535243}, {"type": "node", "id": 1598126891, "lat": 50.7197152, "lon": 9.6516103}, {"type": "node", "id": 1598126893, "lat": 50.7198854, "lon": 9.6518303}, {"type": "node", "id": 1598126906, "lat": 50.7207355, "lon": 9.6507724}, {"type": "node", "id": 1598126936, "lat": 50.7249775, "lon": 9.6482175}, {"type": "node", "id": 1691610108, "lat": 50.7219659, "lon": 9.6501775}, {"type": "node", "id": 1691610109, "lat": 50.7219357, "lon": 9.6498911}, {"type": "node", "id": 1836752690, "lat": 50.7121481, "lon": 9.6654657}, {"type": "node", "id": 1836752691, "lat": 50.7122996, "lon": 9.6654519}, {"type": "node", "id": 1882821261, "lat": 50.7260486, "lon": 9.6477159}, {"type": "node", "id": 2303032737, "lat": 50.7066812, "lon": 9.6734171}, {"type": "node", "id": 2675678743, "lat": 50.7073521, "lon": 9.6532609, "tags": {"name": "Gro\u00dfenmoor", "traffic_sign": "city_limit"}}, {"type": "node", "id": 2973608889, "lat": 50.7141534, "lon": 9.6632391}, {"type": "node", "id": 2973608897, "lat": 50.71426, "lon": 9.6620837}, {"type": "node", "id": 3721840154, "lat": 50.7118264, "lon": 9.6640887}, {"type": "node", "id": 3721840165, "lat": 50.714624, "lon": 9.6579042}, {"type": "node", "id": 4486306274, "lat": 50.7063899, "lon": 9.6529802}, {"type": "node", "id": 4486306275, "lat": 50.7054505, "lon": 9.6527871}, {"type": "node", "id": 6024647513, "lat": 50.7105299, "lon": 9.6665713}, {"type": "node", "id": 6568903277, "lat": 50.7107655, "lon": 9.6628527}, {"type": "node", "id": 6568903278, "lat": 50.7113102, "lon": 9.6643095}, {"type": "node", "id": 7507451032, "lat": 50.7066237, "lon": 9.6530459}, {"type": "node", "id": 8035087222, "lat": 50.7132261, "lon": 9.6650263}, {"type": "node", "id": 9671236688, "lat": 50.7117953, "lon": 9.6654528}, {"type": "node", "id": 9671236691, "lat": 50.7137552, "lon": 9.6643075}, {"type": "node", "id": 9671236692, "lat": 50.7140202, "lon": 9.6635699}, {"type": "node", "id": 9671236694, "lat": 50.7158629, "lon": 9.6598873}, {"type": "node", "id": 10116223146, "lat": 50.706486, "lon": 9.6530072}, {"type": "way", "id": 9954770, "nodes": [1598126768, 3721840154], "tags": {"destination": "Rastst\u00e4tte Gro\u00dfenmoor", "destination:symbol": "rest_area;fuel;food", "highway": "motorway_link", "lanes": "1", "lit": "no", "oneway": "yes", "surface": "asphalt"}}, {"type": "way", "id": 24016518, "nodes": [81715387, 81715394, 81715404], "tags": {"destination": "Kassel;Erfurt;Gie\u00dfen", "destination:ref": "A 7", "highway": "motorway_link", "lanes": "1", "lit": "no", "oneway": "yes", "surface": "asphalt"}}, {"type": "way", "id": 24016519, "nodes": [260441234, 3721840165, 774561858, 260441235], "tags": {"destination": "Rastst\u00e4tte Gro\u00dfenmoor", "destination:symbol": "rest_area;fuel;food", "highway": "motorway_link", "lanes": "1", "lit": "no", "oneway": "yes", "surface": "asphalt"}}, {"type": "way", "id": 54894992, "nodes": [690921005, 690921007], "tags": {"highway": "unclassified", "maxheight": "4.2", "surface": "asphalt", "width": "4"}}, {"type": "way", "id": 54894993, "nodes": [690921007, 926293766, 9671236688, 1836752690, 1836752691, 690921010, 690921012, 690921186, 8035087222, 690921188, 9671236691, 690921190, 9671236692, 2973608889, 926293770], "tags": {"highway": "unclassified", "surface": "asphalt", "width": "4"}}, {"type": "way", "id": 79181584, "nodes": [924556495, 2675678743, 924556494], "tags": {"highway": "unclassified", "surface": "asphalt"}}, {"type": "way", "id": 79181594, "nodes": [924556494, 7507451032, 10116223146, 4486306274, 924556492, 4486306275, 924556490], "tags": {"highway": "residential", "name": "Neue Fahrt", "surface": "asphalt"}}, {"type": "way", "id": 79308255, "nodes": [690920955, 656633641], "tags": {"highway": "unclassified", "surface": "asphalt", "width": "4"}}, {"type": "way", "id": 79308256, "nodes": [656633641, 690921001, 6568903277, 926293690, 690921003, 926293694, 926293696, 926293697, 690921005], "tags": {"highway": "unclassified", "note": "nicht zugangsbeschr\u00e4nkt", "surface": "paved", "width": "4"}}, {"type": "way", "id": 79308257, "nodes": [926293770, 690921162, 690921179, 9671236694, 690921180], "tags": {"access": "agricultural;forestry", "highway": "unclassified", "motorcar": "agricultural", "motorcycle": "agricultural", "surface": "asphalt", "tracktype": "grade1", "width": "4"}}, {"type": "way", "id": 79308258, "nodes": [926293770, 2973608897, 926293797], "tags": {"access": "delivery;agricultural;forestry", "highway": "unclassified", "surface": "asphalt", "width": "4"}}, {"type": "way", "id": 145036688, "nodes": [32011440, 534889189, 1598126642, 1585021777, 12453076, 1598126614, 32011438, 1598126589, 12453152, 1598126553], "tags": {"bdouble": "yes", "highway": "motorway", "int_ref": "E 45", "lanes": "3", "lit": "no", "maxspeed": "none", "oneway": "yes", "ref": "A 7", "source:lit": "http://www.autobahn-bilder.de", "surface": "asphalt"}}, {"type": "way", "id": 145036691, "nodes": [1585021784, 1585021779], "tags": {"bdouble": "yes", "bridge": "yes", "highway": "motorway", "int_ref": "E 45", "lanes": "4", "layer": "1", "lit": "no", "maxspeed": "none", "oneway": "yes", "ref": "A 7", "source:lit": "http://www.autobahn-bilder.de", "surface": "asphalt", "turn:lanes": "none|none|none|merge_to_left"}}, {"type": "way", "id": 145036695, "nodes": [1585021790, 1585021796], "tags": {"bdouble": "yes", "bridge": "yes", "destination:lanes": "||Rastst\u00e4tte Gro\u00dfenmoor", "destination:ref:lanes": "A 7|A 7|none", "destination:symbol:lanes": "none|none|rest_area;fuel;food", "highway": "motorway", "int_ref": "E 45", "lanes": "3", "layer": "1", "lit": "no", "maxspeed": "none", "maxspeed:wet": "80", "oneway": "yes", "ref": "A 7", "source:lit": "http://www.autobahn-bilder.de", "surface": "asphalt", "turn:lanes": "none|none|slight_right"}}, {"type": "way", "id": 145036701, "nodes": [1585021796, 1598126768], "tags": {"bdouble": "yes", "destination:lanes": "||Rastst\u00e4tte Gro\u00dfenmoor", "destination:ref:lanes": "A 7|A 7|none", "destination:symbol:lanes": "none|none|rest_area;fuel;food", "highway": "motorway", "int_ref": "E 45", "lanes": "3", "lit": "no", "maxspeed": "none", "maxspeed:wet": "80", "oneway": "yes", "ref": "A 7", "source:lit": "http://www.autobahn-bilder.de", "surface": "asphalt", "turn:lanes": "none|none|slight_right"}}, {"type": "way", "id": 146530243, "nodes": [2303032737, 1598126619, 1598126647, 1598126682, 32011439, 6024647513], "tags": {"bdouble": "yes", "highway": "motorway", "int_ref": "E 45", "lanes": "2", "lit": "no", "maxspeed": "none", "maxspeed:wet": "80", "oneway": "yes", "ref": "A 7", "source:lit": "http://www.autobahn-bilder.de", "surface": "asphalt"}}, {"type": "way", "id": 146530358, "nodes": [260441239, 1598126774, 6568903278, 1585021784], "tags": {"destination": "W\u00fcrzburg", "destination:ref": "A 7", "highway": "motorway_link", "lanes": "1", "lit": "no", "oneway": "yes", "surface": "asphalt"}}, {"type": "way", "id": 177868438, "nodes": [1882821261, 1598126936, 12453073, 1691610109, 1598126906, 1598126891, 534889138, 1598126870, 1598126860, 32011442], "tags": {"bdouble": "yes", "highway": "motorway", "int_ref": "E 45", "lanes": "3", "lit": "no", "maxspeed": "none", "oneway": "yes", "ref": "A 7", "source:lit": "http://www.autobahn-bilder.de", "surface": "asphalt"}}, {"type": "way", "id": 261939842, "nodes": [924556496, 924556495], "tags": {"highway": "unclassified", "surface": "asphalt"}}, {"type": "way", "id": 261939846, "nodes": [924556496, 924556499, 924556502, 924556514, 924556517, 924556520, 926293596, 926293598, 926293611, 926293615, 926293620, 926293622, 926293624, 926293626, 926293628, 926293630, 926293647, 926293650, 926293653, 926293656, 926293658, 926293662, 926293665, 656633641], "tags": {"highway": "unclassified", "maxweight": "7.5", "surface": "asphalt"}}, {"type": "way", "id": 293775087, "nodes": [260441234, 774561874, 12453150, 1585021784], "tags": {"bdouble": "yes", "destination:ref": "A 7", "highway": "motorway", "int_ref": "E 45", "lanes": "3", "lit": "no", "maxspeed": "none", "oneway": "yes", "ref": "A 7", "source:lit": "http://www.autobahn-bilder.de", "surface": "asphalt"}}, {"type": "way", "id": 293775088, "nodes": [1598126768, 1585021802, 21464514, 32011441, 81715404], "tags": {"bdouble": "yes", "destination:ref": "A 7", "highway": "motorway", "int_ref": "E 45", "lanes": "2", "lit": "no", "maxspeed": "none", "maxspeed:wet": "80", "oneway": "yes", "ref": "A 7", "source:lit": "http://www.autobahn-bilder.de", "surface": "asphalt"}}, {"type": "way", "id": 293775090, "nodes": [21464515, 1598126875, 534889159, 1598126893, 32011444, 1691610108, 21464516, 1585021804], "tags": {"bdouble": "yes", "highway": "motorway", "int_ref": "E 45", "lanes": "2", "lit": "no", "maxspeed": "none", "maxspeed:wet": "80", "oneway": "yes", "ref": "A 7", "source:lit": "http://www.autobahn-bilder.de", "surface": "asphalt"}}, {"type": "way", "id": 639356804, "nodes": [1585021779, 32011440], "tags": {"bdouble": "yes", "highway": "motorway", "int_ref": "E 45", "lanes": "4", "lit": "no", "maxspeed": "none", "oneway": "yes", "ref": "A 7", "source:lit": "http://www.autobahn-bilder.de", "surface": "asphalt", "turn:lanes": "none|none|none|merge_to_left"}}, {"type": "way", "id": 639356805, "nodes": [81715404, 21464515], "tags": {"bdouble": "yes", "highway": "motorway", "int_ref": "E 45", "lanes": "3", "lit": "no", "maxspeed": "none", "maxspeed:wet": "80", "oneway": "yes", "ref": "A 7", "source:lit": "http://www.autobahn-bilder.de", "surface": "asphalt", "turn:lanes": "none|none|merge_to_left"}}, {"type": "way", "id": 639356807, "nodes": [6024647513, 1585021790], "tags": {"bdouble": "yes", "destination:lanes": "||Rastst\u00e4tte Gro\u00dfenmoor", "destination:ref:lanes": "A 7|A 7|none", "destination:symbol:lanes": "none|none|rest_area;fuel;food", "highway": "motorway", "int_ref": "E 45", "lanes": "3", "lit": "no", "maxspeed": "none", "maxspeed:wet": "80", "oneway": "yes", "ref": "A 7", "source:lit": "http://www.autobahn-bilder.de", "surface": "asphalt", "turn:lanes": "none|none|slight_right"}}, {"type": "way", "id": 639356808, "nodes": [32011442, 260441234], "tags": {"bdouble": "yes", "destination:lanes": "|||Rastst\u00e4tte Gro\u00dfenmoor", "destination:ref:lanes": "A 7|A 7|A 7|none", "destination:symbol:lanes": "none|none|none|rest_area;fuel;food", "highway": "motorway", "int_ref": "E 45", "lanes": "4", "lit": "no", "maxspeed": "none", "oneway": "yes", "ref": "A 7", "source:lit": "http://www.autobahn-bilder.de", "surface": "asphalt", "turn:lanes": "none|none|none|slight_right"}}]}