{"version": 0.6, "generator": "Overpass API 0.7.59.2 0994154d", "osm3s": {"timestamp_osm_base": "2023-03-12T20:25:52Z", "copyright": "The data included in this document is from www.openstreetmap.org. The data is made available under ODbL."}, "elements": [{"type": "node", "id": 122427, "lat": 53.4678408, "lon": 9.9270046}, {"type": "node", "id": 122428, "lat": 53.4681802, "lon": 9.9272138}, {"type": "node", "id": 122429, "lat": 53.4706532, "lon": 9.9274866, "tags": {"TMC:cid_58:tabcd_1:Class": "Point", "TMC:cid_58:tabcd_1:Direction": "both", "TMC:cid_58:tabcd_1:LCLversion": "8.00", "TMC:cid_58:tabcd_1:LocationCode": "25004", "TMC:cid_58:tabcd_1:NextLocationCode": "25005", "TMC:cid_58:tabcd_1:PrevLocationCode": "35839", "note": "415 Pfeilwegweiser auf Bundesstra\u00dfen", "source": "GPS and Videomapping", "source:traffic_sign": "https://de.wikipedia.org/wiki/Bildtafel_der_Verkehrszeichen_in_der_Bundesrepublik_Deutschland_seit_2017", "traffic_sign": "DE:415"}}, {"type": "node", "id": 491178, "lat": 53.4706538, "lon": 9.9203443, "tags": {"ele": "14.56", "time": "2003-09-27T15:51:12Z"}}, {"type": "node", "id": 491179, "lat": 53.4688273, "lon": 9.9224162, "tags": {"TMC:cid_58:tabcd_1:Class": "Point", "TMC:cid_58:tabcd_1:Direction": "negative", "TMC:cid_58:tabcd_1:LCLversion": "8.00", "TMC:cid_58:tabcd_1:LocationCode": "12373", "TMC:cid_58:tabcd_1:NextLocationCode": "12374", "TMC:cid_58:tabcd_1:PrevLocationCode": "12372", "ele": "16.0", "highway": "motorway_junction", "name": "Hamburg-Heimfeld", "ref": "32", "time": "2003-09-27T15:51:17Z"}}, {"type": "node", "id": 491180, "lat": 53.466934, "lon": 9.9247784}, {"type": "node", "id": 491181, "lat": 53.4664782, "lon": 9.9252757}, {"type": "node", "id": 491183, "lat": 53.4648263, "lon": 9.9269111, "tags": {"ele": "25.61", "time": "2003-09-27T15:51:34Z"}}, {"type": "node", "id": 491184, "lat": 53.4637127, "lon": 9.9277002, "tags": {"ele": "27.05", "time": "2003-09-27T15:51:38Z"}}, {"type": "node", "id": 491185, "lat": 53.4630881, "lon": 9.9279928, "tags": {"ele": "30.9", "time": "2003-09-27T15:51:41Z"}}, {"type": "node", "id": 491186, "lat": 53.4625362, "lon": 9.9282085, "tags": {"ele": "30.9", "time": "2003-09-27T15:51:42Z"}}, {"type": "node", "id": 491187, "lat": 53.4610716, "lon": 9.9284762, "tags": {"ele": "33.3", "time": "2003-09-27T15:51:46Z"}}, {"type": "node", "id": 491188, "lat": 53.4601581, "lon": 9.9284424, "tags": {"ele": "34.74", "time": "2003-09-27T15:51:49Z"}}, {"type": "node", "id": 491189, "lat": 53.4597086, "lon": 9.9283515, "tags": {"ele": "36.67", "time": "2003-09-27T15:51:52Z"}}, {"type": "node", "id": 491190, "lat": 53.458655, "lon": 9.9280052, "tags": {"ele": "40.51", "time": "2003-09-27T15:51:55Z"}}, {"type": "node", "id": 491191, "lat": 53.4580567, "lon": 9.9277139}, {"type": "node", "id": 491193, "lat": 53.4567062, "lon": 9.92673, "tags": {"ele": "46.76", "time": "2003-09-27T15:52:02Z"}}, {"type": "node", "id": 491194, "lat": 53.4560579, "lon": 9.9261056, "tags": {"ele": "50.61", "time": "2003-09-27T15:52:06Z"}}, {"type": "node", "id": 491195, "lat": 53.4551933, "lon": 9.9251773, "tags": {"ele": "51.09", "time": "2003-09-27T15:52:08Z"}}, {"type": "node", "id": 491196, "lat": 53.4545039, "lon": 9.9243654, "tags": {"ele": "53.97", "time": "2003-09-27T15:52:11Z"}}, {"type": "node", "id": 491197, "lat": 53.4537515, "lon": 9.9234583, "tags": {"ele": "57.82", "time": "2003-09-27T15:52:14Z"}}, {"type": "node", "id": 491198, "lat": 53.4526635, "lon": 9.9222056, "tags": {"ele": "61.66", "time": "2003-09-27T15:52:18Z"}}, {"type": "node", "id": 491199, "lat": 53.4516507, "lon": 9.921176, "tags": {"ele": "65.03", "time": "2003-09-27T15:52:22Z"}}, {"type": "node", "id": 491201, "lat": 53.4504933, "lon": 9.9202336, "tags": {"ele": "70.31", "time": "2003-09-27T15:52:26Z"}}, {"type": "node", "id": 495996, "lat": 53.4626012, "lon": 9.928466, "tags": {"ele": "39.55", "time": "2003-09-18T19:05:48Z"}}, {"type": "node", "id": 495997, "lat": 53.4632184, "lon": 9.9282028, "tags": {"ele": "40.99", "time": "2003-09-18T19:05:50Z"}}, {"type": "node", "id": 495998, "lat": 53.4637835, "lon": 9.9279234, "tags": {"TMC:cid_58:tabcd_1:Class": "Point", "TMC:cid_58:tabcd_1:Direction": "positive", "TMC:cid_58:tabcd_1:LCLversion": "8.00", "TMC:cid_58:tabcd_1:LocationCode": "12373", "TMC:cid_58:tabcd_1:NextLocationCode": "12374", "TMC:cid_58:tabcd_1:PrevLocationCode": "12372", "ele": "38.59", "highway": "motorway_junction", "name": "Hamburg-Heimfeld", "ref": "32", "time": "2003-09-18T19:05:52Z"}}, {"type": "node", "id": 495999, "lat": 53.4650425, "lon": 9.9270241, "tags": {"ele": "34.74", "time": "2003-09-18T19:05:57Z"}}, {"type": "node", "id": 496002, "lat": 53.4665538, "lon": 9.9255192}, {"type": "node", "id": 496003, "lat": 53.4677951, "lon": 9.9240632, "tags": {"ele": "28.5", "time": "2003-09-18T19:06:08Z"}}, {"type": "node", "id": 496004, "lat": 53.4695184, "lon": 9.9219733, "tags": {"ele": "25.13", "time": "2003-09-18T19:06:15Z"}}, {"type": "node", "id": 496006, "lat": 53.47073, "lon": 9.9206295, "tags": {"ele": "22.73", "time": "2003-09-18T19:06:21Z"}}, {"type": "node", "id": 496007, "lat": 53.4724252, "lon": 9.9189371, "tags": {"ele": "19.84", "time": "2003-09-18T19:06:30Z"}}, {"type": "node", "id": 496010, "lat": 53.4759336, "lon": 9.9164668, "tags": {"ele": "18.88", "time": "2003-09-18T19:06:46Z"}}, {"type": "node", "id": 10210551, "lat": 53.4708787, "lon": 9.9069536}, {"type": "node", "id": 10210552, "lat": 53.4704301, "lon": 9.9145354}, {"type": "node", "id": 10377757, "lat": 53.4672617, "lon": 9.9262213}, {"type": "node", "id": 10377758, "lat": 53.4669837, "lon": 9.9257349}, {"type": "node", "id": 10377759, "lat": 53.4665732, "lon": 9.924317}, {"type": "node", "id": 10377760, "lat": 53.4666764, "lon": 9.9232321}, {"type": "node", "id": 10377761, "lat": 53.4669064, "lon": 9.922959}, {"type": "node", "id": 10377762, "lat": 53.4674135, "lon": 9.9237099}, {"type": "node", "id": 10377764, "lat": 53.4673599, "lon": 9.9232665}, {"type": "node", "id": 10377765, "lat": 53.4683675, "lon": 9.9271406}, {"type": "node", "id": 12217094, "lat": 53.470681, "lon": 9.92602, "tags": {"note": "430 Pfeilwegweiser zur Autobahn", "source": "GPS and Videomapping", "source:traffic_sign": "https://de.wikipedia.org/wiki/Bildtafel_der_Verkehrszeichen_in_der_Bundesrepublik_Deutschland_seit_2017", "traffic_sign": "DE:430"}}, {"type": "node", "id": 12217095, "lat": 53.4704601, "lon": 9.9272827, "tags": {"name": "Hamburg", "traffic_sign": "city_limit"}}, {"type": "node", "id": 13328438, "lat": 53.4766988, "lon": 9.9301577}, {"type": "node", "id": 20834531, "lat": 53.4704768, "lon": 9.9164995}, {"type": "node", "id": 20834533, "lat": 53.4714287, "lon": 9.9164934}, {"type": "node", "id": 20834534, "lat": 53.4713139, "lon": 9.9119315, "tags": {"highway": "turning_circle"}}, {"type": "node", "id": 21479665, "lat": 53.4717006, "lon": 9.9352639}, {"type": "node", "id": 24302167, "lat": 53.4710041, "lon": 9.9370951, "tags": {"bicycle": "yes", "button_operated": "yes", "crossing": "traffic_signals", "crossing:island": "yes", "highway": "crossing", "tactile_paving": "no", "traffic_signals:sound": "no"}}, {"type": "node", "id": 25984392, "lat": 53.4705585, "lon": 9.9197462}, {"type": "node", "id": 25984393, "lat": 53.4705902, "lon": 9.9210068}, {"type": "node", "id": 26400784, "lat": 53.471882, "lon": 9.9172321}, {"type": "node", "id": 26400809, "lat": 53.4718819, "lon": 9.9213267}, {"type": "node", "id": 26400810, "lat": 53.4718542, "lon": 9.9223106}, {"type": "node", "id": 26805104, "lat": 53.4700038, "lon": 9.9214247}, {"type": "node", "id": 26805105, "lat": 53.46993, "lon": 9.9211321, "tags": {"note": "Exit Hamburg-Heimfeld", "source": "GPS and Videomapping", "source:traffic_sign": "https://de.wikipedia.org/wiki/Bildtafel_der_Verkehrszeichen_in_der_Bundesrepublik_Deutschland_seit_2017", "traffic_sign": "DE:332"}}, {"type": "node", "id": 27370272, "lat": 53.477386, "lon": 9.9256434}, {"type": "node", "id": 27370275, "lat": 53.4761512, "lon": 9.9242846}, {"type": "node", "id": 27370277, "lat": 53.4758136, "lon": 9.927916}, {"type": "node", "id": 27370278, "lat": 53.4756556, "lon": 9.9296514}, {"type": "node", "id": 27370279, "lat": 53.4755015, "lon": 9.9312528}, {"type": "node", "id": 27370281, "lat": 53.4740953, "lon": 9.9272092}, {"type": "node", "id": 27370282, "lat": 53.4738231, "lon": 9.9288837}, {"type": "node", "id": 27370283, "lat": 53.473576, "lon": 9.9304623}, {"type": "node", "id": 27370284, "lat": 53.4725155, "lon": 9.9320724}, {"type": "node", "id": 27370285, "lat": 53.4726983, "lon": 9.9319559}, {"type": "node", "id": 27370288, "lat": 53.4739531, "lon": 9.932669}, {"type": "node", "id": 27370291, "lat": 53.4744783, "lon": 9.9337056}, {"type": "node", "id": 27370298, "lat": 53.4717256, "lon": 9.9331057}, {"type": "node", "id": 27370299, "lat": 53.4717514, "lon": 9.93177}, {"type": "node", "id": 27370300, "lat": 53.4717749, "lon": 9.9297175}, {"type": "node", "id": 27370301, "lat": 53.4717819, "lon": 9.9280795}, {"type": "node", "id": 27370302, "lat": 53.4717955, "lon": 9.926214}, {"type": "node", "id": 27370303, "lat": 53.4717073, "lon": 9.9345792}, {"type": "node", "id": 27370336, "lat": 53.4758732, "lon": 9.9272831, "tags": {"traffic_calming": "choker"}}, {"type": "node", "id": 27370337, "lat": 53.4758002, "lon": 9.9280648, "tags": {"traffic_calming": "choker"}}, {"type": "node", "id": 27370345, "lat": 53.4753854, "lon": 9.9325856}, {"type": "node", "id": 30473149, "lat": 53.4681459, "lon": 9.9229191}, {"type": "node", "id": 30694890, "lat": 53.4670072, "lon": 9.9249934}, {"type": "node", "id": 30773700, "lat": 53.4746348, "lon": 9.9172767}, {"type": "node", "id": 30773702, "lat": 53.4744731, "lon": 9.9173855}, {"type": "node", "id": 32575169, "lat": 53.46776, "lon": 9.9259914}, {"type": "node", "id": 32575170, "lat": 53.4677862, "lon": 9.9252134}, {"type": "node", "id": 32575171, "lat": 53.4680383, "lon": 9.9244364}, {"type": "node", "id": 33565684, "lat": 53.46418, "lon": 9.9332194}, {"type": "node", "id": 33565708, "lat": 53.4644871, "lon": 9.9268668}, {"type": "node", "id": 33565710, "lat": 53.4644144, "lon": 9.9265717}, {"type": "node", "id": 94170560, "lat": 53.4620239, "lon": 9.9283466}, {"type": "node", "id": 94178363, "lat": 53.4670558, "lon": 9.9260937}, {"type": "node", "id": 94178380, "lat": 53.4678119, "lon": 9.9229056}, {"type": "node", "id": 94178382, "lat": 53.467735, "lon": 9.9267609}, {"type": "node", "id": 94178387, "lat": 53.467636, "lon": 9.9268305}, {"type": "node", "id": 94178392, "lat": 53.4687785, "lon": 9.9274163}, {"type": "node", "id": 94178394, "lat": 53.4706568, "lon": 9.9272824, "tags": {"note": "430 Pfeilwegweiser zur Autobahn", "source": "GPS and Videomapping", "source:traffic_sign": "https://de.wikipedia.org/wiki/Bildtafel_der_Verkehrszeichen_in_der_Bundesrepublik_Deutschland_seit_2017", "traffic_sign": "DE:430"}}, {"type": "node", "id": 94178399, "lat": 53.4680948, "lon": 9.926851}, {"type": "node", "id": 94178401, "lat": 53.4678861, "lon": 9.9265047}, {"type": "node", "id": 94178403, "lat": 53.4667397, "lon": 9.9251013}, {"type": "node", "id": 94178406, "lat": 53.4665614, "lon": 9.9237749}, {"type": "node", "id": 94178408, "lat": 53.4671722, "lon": 9.9229862}, {"type": "node", "id": 94178410, "lat": 53.467315, "lon": 9.9241283}, {"type": "node", "id": 94186701, "lat": 53.4793179, "lon": 9.9150406, "tags": {"TMC:cid_58:tabcd_1:Class": "Point", "TMC:cid_58:tabcd_1:Direction": "positive", "TMC:cid_58:tabcd_1:LCLversion": "8.00", "TMC:cid_58:tabcd_1:LocationCode": "12374", "TMC:cid_58:tabcd_1:NextLocationCode": "12375", "TMC:cid_58:tabcd_1:PrevLocationCode": "12373", "highway": "motorway_junction", "name": "Hamburg-Hausbruch", "old_name": "Hamburg-Moorburg", "ref": "31"}}, {"type": "node", "id": 199057380, "lat": 53.4709164, "lon": 9.9327871}, {"type": "node", "id": 199057382, "lat": 53.4712304, "lon": 9.9329164}, {"type": "node", "id": 199058420, "lat": 53.4717415, "lon": 9.9323929, "tags": {"crossing": "unmarked", "highway": "crossing"}}, {"type": "node", "id": 254455695, "lat": 53.4725323, "lon": 9.9329229}, {"type": "node", "id": 254455696, "lat": 53.4733031, "lon": 9.933268}, {"type": "node", "id": 254455697, "lat": 53.4734305, "lon": 9.9332494}, {"type": "node", "id": 254456000, "lat": 53.4768515, "lon": 9.9292075}, {"type": "node", "id": 254456002, "lat": 53.4766332, "lon": 9.9309062}, {"type": "node", "id": 254456005, "lat": 53.4766102, "lon": 9.9316791}, {"type": "node", "id": 254456008, "lat": 53.4766183, "lon": 9.9320397}, {"type": "node", "id": 273402378, "lat": 53.4647173, "lon": 9.9277703}, {"type": "node", "id": 277783027, "lat": 53.4704184, "lon": 9.9125653}, {"type": "node", "id": 277783046, "lat": 53.4704408, "lon": 9.9150668}, {"type": "node", "id": 278711883, "lat": 53.4699329, "lon": 9.9273024}, {"type": "node", "id": 290351150, "lat": 53.4681626, "lon": 9.9277848}, {"type": "node", "id": 298511648, "lat": 53.466786, "lon": 9.9271487}, {"type": "node", "id": 309552483, "lat": 53.4718839, "lon": 9.9207418}, {"type": "node", "id": 318626148, "lat": 53.4647495, "lon": 9.9279084}, {"type": "node", "id": 431520567, "lat": 53.4760726, "lon": 9.9252483}, {"type": "node", "id": 431520580, "lat": 53.4768147, "lon": 9.924862}, {"type": "node", "id": 431520581, "lat": 53.477179, "lon": 9.9253498}, {"type": "node", "id": 431520588, "lat": 53.4759855, "lon": 9.926161, "tags": {"crossing": "unmarked", "highway": "crossing"}}, {"type": "node", "id": 431520592, "lat": 53.4766488, "lon": 9.924636}, {"type": "node", "id": 431520608, "lat": 53.4761757, "lon": 9.9239531}, {"type": "node", "id": 462742924, "lat": 53.4718833, "lon": 9.9208591, "tags": {"bus": "yes", "name": "Heykenaubrook", "public_transport": "stop_position"}}, {"type": "node", "id": 462742937, "lat": 53.471884, "lon": 9.9207019}, {"type": "node", "id": 462742943, "lat": 53.4718824, "lon": 9.9211913}, {"type": "node", "id": 462742967, "lat": 53.4718175, "lon": 9.9234053}, {"type": "node", "id": 462742973, "lat": 53.4718068, "lon": 9.9240576}, {"type": "node", "id": 590842473, "lat": 53.4760835, "lon": 9.9250902}, {"type": "node", "id": 700978924, "lat": 53.4709042, "lon": 9.9325182, "tags": {"button_operated": "yes", "crossing": "traffic_signals", "highway": "crossing", "tactile_paving": "no", "traffic_signals:sound": "yes"}}, {"type": "node", "id": 904439274, "lat": 53.457755, "lon": 9.9275305, "tags": {"note": "Exit Dreieck Hamburg-S\u00fcdwest in 2000m", "source": "GPS and Videomapping", "source:traffic_sign": "https://de.wikipedia.org/wiki/Bildtafel_der_Verkehrszeichen_in_der_Bundesrepublik_Deutschland_seit_2017", "traffic_sign": "DE:448"}}, {"type": "node", "id": 904439276, "lat": 53.4644728, "lon": 9.9272019}, {"type": "node", "id": 904439281, "lat": 53.4592828, "lon": 9.9282375}, {"type": "node", "id": 904439292, "lat": 53.4714853, "lon": 9.9194978}, {"type": "node", "id": 904439295, "lat": 53.4615551, "lon": 9.9284368}, {"type": "node", "id": 904439305, "lat": 53.4520978, "lon": 9.9216085}, {"type": "node", "id": 904439306, "lat": 53.4653954, "lon": 9.9263972}, {"type": "node", "id": 904439309, "lat": 53.4500954, "lon": 9.9199707}, {"type": "node", "id": 904439311, "lat": 53.4556094, "lon": 9.9256285}, {"type": "node", "id": 904439318, "lat": 53.4510704, "lon": 9.9206707}, {"type": "node", "id": 904439319, "lat": 53.457272, "lon": 9.9271949}, {"type": "node", "id": 904439325, "lat": 53.4606263, "lon": 9.9284799}, {"type": "node", "id": 914940027, "lat": 53.4654508, "lon": 9.926649}, {"type": "node", "id": 914940028, "lat": 53.465814, "lon": 9.926286}, {"type": "node", "id": 914940032, "lat": 53.4645168, "lon": 9.9274386}, {"type": "node", "id": 914941176, "lat": 53.4716269, "lon": 9.919689}, {"type": "node", "id": 914943907, "lat": 53.4733748, "lon": 9.9181469}, {"type": "node", "id": 914951655, "lat": 53.4764577, "lon": 9.9161826}, {"type": "node", "id": 914951664, "lat": 53.4729794, "lon": 9.9184592}, {"type": "node", "id": 937904942, "lat": 53.4737602, "lon": 9.9178716}, {"type": "node", "id": 938641844, "lat": 53.4657381, "lon": 9.9260558}, {"type": "node", "id": 1122404433, "lat": 53.4718347, "lon": 9.9229581}, {"type": "node", "id": 1122404435, "lat": 53.4718832, "lon": 9.9209406}, {"type": "node", "id": 1122404450, "lat": 53.4718256, "lon": 9.9231293}, {"type": "node", "id": 1329457814, "lat": 53.4705011, "lon": 9.9274835, "tags": {"highway": "traffic_signals"}}, {"type": "node", "id": 1329457816, "lat": 53.4705038, "lon": 9.9271844}, {"type": "node", "id": 1329457818, "lat": 53.4705683, "lon": 9.9268671}, {"type": "node", "id": 1329457837, "lat": 53.4706767, "lon": 9.9265524}, {"type": "node", "id": 1329457840, "lat": 53.4706954, "lon": 9.9251901}, {"type": "node", "id": 1329457845, "lat": 53.4707448, "lon": 9.9298234}, {"type": "node", "id": 1329457858, "lat": 53.4707471, "lon": 9.9259886}, {"type": "node", "id": 1329457860, "lat": 53.4707754, "lon": 9.9273799}, {"type": "node", "id": 1329457862, "lat": 53.4707836, "lon": 9.9276434, "tags": {"highway": "traffic_signals"}}, {"type": "node", "id": 1329457864, "lat": 53.4707914, "lon": 9.931027}, {"type": "node", "id": 1329457866, "lat": 53.4707969, "lon": 9.9311694}, {"type": "node", "id": 1329457868, "lat": 53.4708216, "lon": 9.9316806}, {"type": "node", "id": 1329457887, "lat": 53.4708465, "lon": 9.932016}, {"type": "node", "id": 1329457889, "lat": 53.4708752, "lon": 9.9310263}, {"type": "node", "id": 1329457891, "lat": 53.4708878, "lon": 9.9314244}, {"type": "node", "id": 1329457893, "lat": 53.4709028, "lon": 9.9319648}, {"type": "node", "id": 1329457897, "lat": 53.4718038, "lon": 9.924392}, {"type": "node", "id": 1329457910, "lat": 53.4720602, "lon": 9.9280729}, {"type": "node", "id": 1329457937, "lat": 53.472956, "lon": 9.9284743}, {"type": "node", "id": 1329461216, "lat": 53.4708107, "lon": 9.9286037}, {"type": "node", "id": 1329461217, "lat": 53.4708177, "lon": 9.9289011}, {"type": "node", "id": 1329489259, "lat": 53.470623, "lon": 9.9223099}, {"type": "node", "id": 1329489266, "lat": 53.4706279, "lon": 9.9225742}, {"type": "node", "id": 1329489268, "lat": 53.4706479, "lon": 9.9233028}, {"type": "node", "id": 1329489270, "lat": 53.4706583, "lon": 9.9237152}, {"type": "node", "id": 1329489325, "lat": 53.4712394, "lon": 9.9167478}, {"type": "node", "id": 1329489337, "lat": 53.4713419, "lon": 9.9167241}, {"type": "node", "id": 1376856125, "lat": 53.4767659, "lon": 9.9296767}, {"type": "node", "id": 1548998521, "lat": 53.467745, "lon": 9.9256207}, {"type": "node", "id": 1549002234, "lat": 53.463473, "lon": 9.9264093}, {"type": "node", "id": 1611670265, "lat": 53.4683742, "lon": 9.922796}, {"type": "node", "id": 1703646589, "lat": 53.4709871, "lon": 9.9363644}, {"type": "node", "id": 1705387867, "lat": 53.4717232, "lon": 9.9334084}, {"type": "node", "id": 1705387879, "lat": 53.4718629, "lon": 9.9219696}, {"type": "node", "id": 1705387885, "lat": 53.4718744, "lon": 9.9216893}, {"type": "node", "id": 1705387887, "lat": 53.4718805, "lon": 9.9214065}, {"type": "node", "id": 1705388817, "lat": 53.4752006, "lon": 9.93459}, {"type": "node", "id": 1705388824, "lat": 53.4752298, "lon": 9.9311952}, {"type": "node", "id": 1705388876, "lat": 53.4753821, "lon": 9.9295875}, {"type": "node", "id": 1705388905, "lat": 53.4755883, "lon": 9.9278671}, {"type": "node", "id": 1705388909, "lat": 53.4757481, "lon": 9.9285971}, {"type": "node", "id": 1705389035, "lat": 53.4797498, "lon": 9.914852}, {"type": "node", "id": 1705403281, "lat": 53.4713429, "lon": 9.9140191}, {"type": "node", "id": 1705403282, "lat": 53.4713506, "lon": 9.9121404}, {"type": "node", "id": 1705403284, "lat": 53.4718716, "lon": 9.9181346}, {"type": "node", "id": 1705403285, "lat": 53.4718926, "lon": 9.9185811}, {"type": "node", "id": 1705403364, "lat": 53.4762289, "lon": 9.9233356}, {"type": "node", "id": 1705486885, "lat": 53.4709559, "lon": 9.935396}, {"type": "node", "id": 2080670385, "lat": 53.470571, "lon": 9.9202447}, {"type": "node", "id": 2171848974, "lat": 53.449636, "lon": 9.9196853, "tags": {"note": "Exit Dreieck Hamburg-S\u00fcdwest in 1000m", "source": "GPS and Videomapping", "source:traffic_sign": "https://de.wikipedia.org/wiki/Bildtafel_der_Verkehrszeichen_in_der_Bundesrepublik_Deutschland_seit_2017", "traffic_sign": "DE:449"}}, {"type": "node", "id": 2171848981, "lat": 53.453148, "lon": 9.9227393, "tags": {"distance": "169.0", "highway": "milestone", "ref": "169.0", "source": "GPS and Videomapping"}}, {"type": "node", "id": 2186528449, "lat": 53.4607881, "lon": 9.9284803, "tags": {"distance": "168.0", "highway": "milestone", "ref": "168.0", "source": "GPS and Videomapping"}}, {"type": "node", "id": 2186528452, "lat": 53.4625655, "lon": 9.9284812, "tags": {"note": "Exit Hamburg-Heimfeld", "source": "GPS and Videomapping", "source:traffic_sign": "https://de.wikipedia.org/wiki/Bildtafel_der_Verkehrszeichen_in_der_Bundesrepublik_Deutschland_seit_2017", "traffic_sign": "DE:332"}}, {"type": "node", "id": 2186528454, "lat": 53.4651397, "lon": 9.9266403}, {"type": "node", "id": 2186528458, "lat": 53.4665526, "lon": 9.9239559}, {"type": "node", "id": 2186528459, "lat": 53.4665598, "lon": 9.9241663}, {"type": "node", "id": 2186528462, "lat": 53.4665879, "lon": 9.9235623}, {"type": "node", "id": 2186528463, "lat": 53.466597, "lon": 9.9244796}, {"type": "node", "id": 2186528464, "lat": 53.4666258, "lon": 9.9233763}, {"type": "node", "id": 2186528466, "lat": 53.4666537, "lon": 9.9247688}, {"type": "node", "id": 2186528467, "lat": 53.4667413, "lon": 9.9231184}, {"type": "node", "id": 2186528469, "lat": 53.4668221, "lon": 9.9230288}, {"type": "node", "id": 2186528470, "lat": 53.4668507, "lon": 9.9254238}, {"type": "node", "id": 2186528472, "lat": 53.4669494, "lon": 9.9258912}, {"type": "node", "id": 2186528473, "lat": 53.466986, "lon": 9.9229355}, {"type": "node", "id": 2186528475, "lat": 53.4671497, "lon": 9.9260446}, {"type": "node", "id": 2186528477, "lat": 53.4670804, "lon": 9.92294}, {"type": "node", "id": 2186528480, "lat": 53.4672603, "lon": 9.9230658}, {"type": "node", "id": 2186528481, "lat": 53.4672751, "lon": 9.9264289}, {"type": "node", "id": 2186528482, "lat": 53.467315, "lon": 9.9231535}, {"type": "node", "id": 2186528483, "lat": 53.4673631, "lon": 9.9240006}, {"type": "node", "id": 2186528485, "lat": 53.4673979, "lon": 9.923408}, {"type": "node", "id": 2186528486, "lat": 53.4673982, "lon": 9.9238573}, {"type": "node", "id": 2186528487, "lat": 53.4674128, "lon": 9.9235474}, {"type": "node", "id": 2186528488, "lat": 53.4674707, "lon": 9.9266649}, {"type": "node", "id": 2186528489, "lat": 53.467496, "lon": 9.9265294}, {"type": "node", "id": 2186528490, "lat": 53.4676853, "lon": 9.9228551}, {"type": "node", "id": 2186528491, "lat": 53.4677417, "lon": 9.9258162}, {"type": "node", "id": 2186528492, "lat": 53.4677559, "lon": 9.9254183}, {"type": "node", "id": 2186528493, "lat": 53.4677929, "lon": 9.9261861}, {"type": "node", "id": 2186528494, "lat": 53.4678373, "lon": 9.9263705}, {"type": "node", "id": 2186528495, "lat": 53.4678383, "lon": 9.9249964}, {"type": "node", "id": 2186528496, "lat": 53.467917, "lon": 9.924745}, {"type": "node", "id": 2186528497, "lat": 53.4679261, "lon": 9.9229295}, {"type": "node", "id": 2186528498, "lat": 53.467951, "lon": 9.9266407}, {"type": "node", "id": 2186528499, "lat": 53.4679576, "lon": 9.9269282, "tags": {"note": "Exit T\u00f6tensen", "source": "GPS and Videomapping", "source:traffic_sign": "https://de.wikipedia.org/wiki/Bildtafel_der_Verkehrszeichen_in_der_Bundesrepublik_Deutschland_seit_2017", "traffic_sign": "DE:332"}}, {"type": "node", "id": 2186528500, "lat": 53.4680128, "lon": 9.9267499, "tags": {"note": "Exit T\u00f6tensen", "source": "GPS and Videomapping", "source:traffic_sign": "https://de.wikipedia.org/wiki/Bildtafel_der_Verkehrszeichen_in_der_Bundesrepublik_Deutschland_seit_2017", "traffic_sign": "DE:332"}}, {"type": "node", "id": 2186528501, "lat": 53.4680208, "lon": 9.9229339}, {"type": "node", "id": 2186528503, "lat": 53.4681479, "lon": 9.9241953}, {"type": "node", "id": 2186528504, "lat": 53.4682103, "lon": 9.9270682}, {"type": "node", "id": 2186528505, "lat": 53.4681987, "lon": 9.926969}, {"type": "node", "id": 2186528506, "lat": 53.4682422, "lon": 9.9228823}, {"type": "node", "id": 2186528507, "lat": 53.4683799, "lon": 9.9237773}, {"type": "node", "id": 2186528508, "lat": 53.4684803, "lon": 9.9273344}, {"type": "node", "id": 2186528509, "lat": 53.4686954, "lon": 9.9232457}, {"type": "node", "id": 2186528510, "lat": 53.4685839, "lon": 9.9272203}, {"type": "node", "id": 2186528511, "lat": 53.4690736, "lon": 9.9274474}, {"type": "node", "id": 2186528512, "lat": 53.4687504, "lon": 9.9272652}, {"type": "node", "id": 2186528513, "lat": 53.4693245, "lon": 9.9274539, "tags": {"name": "Hamburg", "source": "GPS and Videomapping", "traffic_sign": "city_limit"}}, {"type": "node", "id": 2186528514, "lat": 53.4698476, "lon": 9.927467}, {"type": "node", "id": 2186528515, "lat": 53.4705409, "lon": 9.9270435, "tags": {"highway": "traffic_signals"}}, {"type": "node", "id": 2186528516, "lat": 53.4706068, "lon": 9.9266023}, {"type": "node", "id": 2186528517, "lat": 53.4706544, "lon": 9.923558, "tags": {"note": "440 Vorwegweiser zur Autobahn", "source": "GPS and Videomapping", "source:traffic_sign": "https://de.wikipedia.org/wiki/Bildtafel_der_Verkehrszeichen_in_der_Bundesrepublik_Deutschland_seit_2017", "traffic_sign": "DE:440"}}, {"type": "node", "id": 2186528519, "lat": 53.4706634, "lon": 9.9281006}, {"type": "node", "id": 2186528520, "lat": 53.4707955, "lon": 9.9281015, "tags": {"note": "440 Vorwegweiser zur Autobahn", "source": "GPS and Videomapping", "source:traffic_sign": "https://de.wikipedia.org/wiki/Bildtafel_der_Verkehrszeichen_in_der_Bundesrepublik_Deutschland_seit_2017", "traffic_sign": "DE:440"}}, {"type": "node", "id": 2186547767, "lat": 53.468958, "lon": 9.9272942}, {"type": "node", "id": 2186547771, "lat": 53.4604149, "lon": 9.928463, "tags": {"note": "Rastplatz Harburger Berge in 5,5 Km", "source": "GPS and Videomapping", "source:traffic_sign": "https://de.wikipedia.org/wiki/Bildtafel_der_Verkehrszeichen_in_der_Bundesrepublik_Deutschland_seit_2017", "traffic_sign": "DE:448"}}, {"type": "node", "id": 2186547774, "lat": 53.4693385, "lon": 9.9274541, "tags": {"note": "439 gegliederter Vorwegweiser", "source": "GPS and Videomapping", "source:traffic_sign": "https://de.wikipedia.org/wiki/Bildtafel_der_Verkehrszeichen_in_der_Bundesrepublik_Deutschland_seit_2017", "traffic_sign": "DE:439"}}, {"type": "node", "id": 2186547775, "lat": 53.469326, "lon": 9.9273113, "tags": {"note": "Exit T\u00f6tensen", "source": "GPS and Videomapping", "source:traffic_sign": "https://de.wikipedia.org/wiki/Bildtafel_der_Verkehrszeichen_in_der_Bundesrepublik_Deutschland_seit_2017", "traffic_sign": "DE:332"}}, {"type": "node", "id": 2186558850, "lat": 53.4690776, "lon": 9.9224949, "tags": {"distance": "167.0", "highway": "milestone", "ref": "167.0", "source": "GPS and Videomapping"}}, {"type": "node", "id": 2186558854, "lat": 53.4741472, "lon": 9.9176027, "tags": {"note": "Exit Hamburg-Moorburg in 500 m", "source": "GPS and Videomapping", "source:traffic_sign": "https://de.wikipedia.org/wiki/Bildtafel_der_Verkehrszeichen_in_der_Bundesrepublik_Deutschland_seit_2017", "traffic_sign": "DE:449"}}, {"type": "node", "id": 2186558867, "lat": 53.4769355, "lon": 9.9159433, "tags": {"distance": "166.0", "highway": "milestone", "source": "GPS and Videomapping"}}, {"type": "node", "id": 2186558871, "lat": 53.4774409, "lon": 9.9157062}, {"type": "node", "id": 2186558873, "lat": 53.478369, "lon": 9.9153467, "tags": {"ele": "16.96", "time": "2003-09-18T19:06:49Z"}}, {"type": "node", "id": 2186558876, "lat": 53.4786123, "lon": 9.9152579, "tags": {"note": "Exit Hamburg-Moorburg", "source": "GPS and Videomapping", "source:traffic_sign": "https://de.wikipedia.org/wiki/Bildtafel_der_Verkehrszeichen_in_der_Bundesrepublik_Deutschland_seit_2017", "traffic_sign": "DE:332"}}, {"type": "node", "id": 2186558889, "lat": 53.4757596, "lon": 9.9165749, "tags": {"guidepost": "overhead", "note": "Verkehrsbeeinflussungsanlage", "source": "GPS and Videomapping"}}, {"type": "node", "id": 2206161982, "lat": 53.4708364, "lon": 9.9295735}, {"type": "node", "id": 2229897854, "lat": 53.4689938, "lon": 9.9222155, "tags": {"distance": "167.0", "highway": "milestone", "ref": "167.0", "source": "GPS and Videomapping"}}, {"type": "node", "id": 2239534032, "lat": 53.4730844, "lon": 9.9331737}, {"type": "node", "id": 2239534035, "lat": 53.4731232, "lon": 9.9321444}, {"type": "node", "id": 2507162089, "lat": 53.4718657, "lon": 9.9180206}, {"type": "node", "id": 2590674807, "lat": 53.4717066, "lon": 9.9348777}, {"type": "node", "id": 2711745969, "lat": 53.4704872, "lon": 9.9169102}, {"type": "node", "id": 2827008431, "lat": 53.4686062, "lon": 9.9225747}, {"type": "node", "id": 3175147432, "lat": 53.4718432, "lon": 9.9225913}, {"type": "node", "id": 3175147433, "lat": 53.471885, "lon": 9.9204106}, {"type": "node", "id": 3175147434, "lat": 53.471886, "lon": 9.9201309}, {"type": "node", "id": 3464734095, "lat": 53.4762053, "lon": 9.9235962}, {"type": "node", "id": 3464734098, "lat": 53.4763005, "lon": 9.9225859, "tags": {"access": "private", "barrier": "lift_gate", "name": "Tor 1"}}, {"type": "node", "id": 3464812819, "lat": 53.4769128, "lon": 9.9289376}, {"type": "node", "id": 3464833580, "lat": 53.4761583, "lon": 9.9241717}, {"type": "node", "id": 3465594377, "lat": 53.4641153, "lon": 9.9264082}, {"type": "node", "id": 3465594379, "lat": 53.4642519, "lon": 9.92642}, {"type": "node", "id": 3529202635, "lat": 53.4709738, "lon": 9.9358876, "tags": {"bus": "yes", "name": "Krankenhaus Mariahilf", "public_transport": "stop_position"}}, {"type": "node", "id": 3529202636, "lat": 53.471, "lon": 9.9368998, "tags": {"bus": "yes", "name": "Krankenhaus Mariahilf", "public_transport": "stop_position"}}, {"type": "node", "id": 3529202856, "lat": 53.4710089, "lon": 9.93729}, {"type": "node", "id": 3561092710, "lat": 53.4733528, "lon": 9.9322451}, {"type": "node", "id": 3561092859, "lat": 53.4726026, "lon": 9.931986}, {"type": "node", "id": 3740881945, "lat": 53.4706394, "lon": 9.9229629}, {"type": "node", "id": 3740881947, "lat": 53.4707609, "lon": 9.9266679}, {"type": "node", "id": 3740881955, "lat": 53.4709486, "lon": 9.9351074}, {"type": "node", "id": 3740882017, "lat": 53.4713669, "lon": 9.9329706, "tags": {"highway": "turning_circle"}}, {"type": "node", "id": 3740886639, "lat": 53.472262, "lon": 9.9319568}, {"type": "node", "id": 3740886658, "lat": 53.4738353, "lon": 9.9334322}, {"type": "node", "id": 4242775790, "lat": 53.4689864, "lon": 9.9279981, "tags": {"highway": "turning_circle"}}, {"type": "node", "id": 5186816403, "lat": 53.4704633, "lon": 9.91596, "tags": {"bus": "yes", "name": "F\u00f6rsterkamp", "network": "HVV", "public_transport": "stop_position"}}, {"type": "node", "id": 5186816404, "lat": 53.4705851, "lon": 9.9164936, "tags": {"button_operated": "no", "crossing": "traffic_signals", "crossing:island": "no", "highway": "crossing", "tactile_paving": "no", "traffic_signals:sound": "no"}}, {"type": "node", "id": 5186816405, "lat": 53.4706408, "lon": 9.9165017, "tags": {"highway": "traffic_signals", "traffic_signals:direction": "backward"}}, {"type": "node", "id": 5186816406, "lat": 53.4707035, "lon": 9.9165224}, {"type": "node", "id": 5186817670, "lat": 53.4708824, "lon": 9.9067672}, {"type": "node", "id": 5186817673, "lat": 53.4708681, "lon": 9.9071979}, {"type": "node", "id": 5186817674, "lat": 53.4708528, "lon": 9.9075181}, {"type": "node", "id": 5186817675, "lat": 53.4707868, "lon": 9.9082479}, {"type": "node", "id": 5186817676, "lat": 53.4706709, "lon": 9.9095048}, {"type": "node", "id": 5186817677, "lat": 53.4704336, "lon": 9.9122765}, {"type": "node", "id": 5186817678, "lat": 53.4704144, "lon": 9.9127959}, {"type": "node", "id": 5186817679, "lat": 53.4704144, "lon": 9.9130592}, {"type": "node", "id": 5186817680, "lat": 53.4704186, "lon": 9.9137372}, {"type": "node", "id": 5186817681, "lat": 53.4704708, "lon": 9.9162596, "tags": {"highway": "traffic_signals", "traffic_signals:direction": "forward"}}, {"type": "node", "id": 5186817682, "lat": 53.4704851, "lon": 9.9168289, "tags": {"highway": "traffic_signals", "traffic_signals:direction": "backward"}}, {"type": "node", "id": 5186817683, "lat": 53.4704838, "lon": 9.9167749, "tags": {"bicycle": "yes", "button_operated": "yes", "crossing": "traffic_signals", "crossing:island": "yes", "highway": "crossing", "tactile_paving": "no", "traffic_signals:sound": "yes"}}, {"type": "node", "id": 5186817684, "lat": 53.4704524, "lon": 9.9155292}, {"type": "node", "id": 5186817685, "lat": 53.470509, "lon": 9.9177796}, {"type": "node", "id": 5186817788, "lat": 53.4705934, "lon": 9.921134, "tags": {"bicycle": "yes", "button_operated": "yes", "crossing": "traffic_signals", "crossing:island": "yes", "highway": "crossing", "tactile_paving": "no", "traffic_signals:sound": "yes"}}, {"type": "node", "id": 5186817789, "lat": 53.470608, "lon": 9.9217169}, {"type": "node", "id": 5188443320, "lat": 53.4704512, "lon": 9.9120173}, {"type": "node", "id": 5188449899, "lat": 53.4706577, "lon": 9.9278448}, {"type": "node", "id": 5188449900, "lat": 53.4706616, "lon": 9.9271677, "tags": {"button_operated": "yes", "crossing": "traffic_signals", "highway": "crossing", "tactile_paving": "no", "traffic_signals:sound": "yes"}}, {"type": "node", "id": 5188449902, "lat": 53.4707718, "lon": 9.927202, "tags": {"button_operated": "yes", "crossing": "traffic_signals", "highway": "crossing", "tactile_paving": "no", "traffic_signals:sound": "yes"}}, {"type": "node", "id": 5188449904, "lat": 53.4705741, "lon": 9.9274854, "tags": {"button_operated": "no", "crossing": "traffic_signals", "highway": "crossing", "tactile_paving": "no", "traffic_signals:sound": "yes"}}, {"type": "node", "id": 5188449906, "lat": 53.4705848, "lon": 9.9272827, "tags": {"button_operated": "no", "crossing": "traffic_signals", "highway": "crossing", "tactile_paving": "no", "traffic_signals:sound": "yes"}}, {"type": "node", "id": 5188449911, "lat": 53.4705284, "lon": 9.9271042, "tags": {"button_operated": "yes", "crossing": "traffic_signals", "highway": "crossing", "tactile_paving": "no", "traffic_signals:sound": "yes"}}, {"type": "node", "id": 5188452521, "lat": 53.4705466, "lon": 9.9109087}, {"type": "node", "id": 5188452522, "lat": 53.4712891, "lon": 9.9167479}, {"type": "node", "id": 5188452523, "lat": 53.4713837, "lon": 9.9166816}, {"type": "node", "id": 5188452524, "lat": 53.471413, "lon": 9.9166091}, {"type": "node", "id": 5292133526, "lat": 53.4766182, "lon": 9.9312906}, {"type": "node", "id": 5292133527, "lat": 53.4766633, "lon": 9.9305295}, {"type": "node", "id": 5574735471, "lat": 53.4717541, "lon": 9.9315112}, {"type": "node", "id": 5695460633, "lat": 53.4708771, "lon": 9.9323615, "tags": {"bus": "yes", "name": "Bostelbek", "network": "HVV", "public_transport": "stop_position"}}, {"type": "node", "id": 5695460643, "lat": 53.4705796, "lon": 9.9205869, "tags": {"bus": "yes", "name": "Moorstieg", "network": "HVV", "public_transport": "stop_position"}}, {"type": "node", "id": 5695460644, "lat": 53.4705878, "lon": 9.9209112, "tags": {"bus": "yes", "name": "Moorstieg", "network": "HVV", "public_transport": "stop_position"}}, {"type": "node", "id": 5695460645, "lat": 53.4704961, "lon": 9.9172638, "tags": {"bus": "yes", "name": "F\u00f6rsterkamp", "network": "HVV", "public_transport": "stop_position"}}, {"type": "node", "id": 5695472052, "lat": 53.4721079, "lon": 9.9192364}, {"type": "node", "id": 5695472053, "lat": 53.4721114, "lon": 9.9189073}, {"type": "node", "id": 5695472059, "lat": 53.4702158, "lon": 9.921197}, {"type": "node", "id": 5695472060, "lat": 53.4701987, "lon": 9.9208402}, {"type": "node", "id": 5695472089, "lat": 53.4709921, "lon": 9.9328108, "tags": {"crossing": "unmarked", "crossing:island": "no", "highway": "crossing", "kerb": "flush", "tactile_paving": "no"}}, {"type": "node", "id": 5704964483, "lat": 53.4708926, "lon": 9.9315959, "tags": {"bus": "yes", "name": "Bostelbek", "network": "HVV", "public_transport": "stop_position"}}, {"type": "node", "id": 5757149941, "lat": 53.4706201, "lon": 9.9221969}, {"type": "node", "id": 5757150048, "lat": 53.471858, "lon": 9.9221558}, {"type": "node", "id": 5757289811, "lat": 53.4718877, "lon": 9.9171647}, {"type": "node", "id": 5757289812, "lat": 53.4718617, "lon": 9.9178087}, {"type": "node", "id": 5757289813, "lat": 53.4719575, "lon": 9.9183886}, {"type": "node", "id": 5757289814, "lat": 53.4719855, "lon": 9.918304}, {"type": "node", "id": 5757289815, "lat": 53.4719973, "lon": 9.918248}, {"type": "node", "id": 5757289816, "lat": 53.47199, "lon": 9.9182085}, {"type": "node", "id": 5757289817, "lat": 53.4719741, "lon": 9.9181778}, {"type": "node", "id": 5757289818, "lat": 53.4719514, "lon": 9.9181648}, {"type": "node", "id": 5757289819, "lat": 53.471927, "lon": 9.9181675}, {"type": "node", "id": 5757289820, "lat": 53.4719063, "lon": 9.9181832}, {"type": "node", "id": 5757290021, "lat": 53.4718905, "lon": 9.9182119}, {"type": "node", "id": 5757290022, "lat": 53.4718824, "lon": 9.9182678}, {"type": "node", "id": 5757290023, "lat": 53.4718824, "lon": 9.9183415}, {"type": "node", "id": 5757290025, "lat": 53.4717981, "lon": 9.9253564, "tags": {"bus": "yes", "name": "Am Radeland", "network": "HVV", "public_transport": "stop_position"}}, {"type": "node", "id": 5757290027, "lat": 53.4717985, "lon": 9.9251771, "tags": {"bus": "yes", "name": "Am Radeland", "network": "HVV", "public_transport": "stop_position"}}, {"type": "node", "id": 5757290055, "lat": 53.4717606, "lon": 9.9309337, "tags": {"bus": "yes", "name": "Zum F\u00fcrstenmoor", "network": "HVV", "public_transport": "stop_position"}}, {"type": "node", "id": 5757290056, "lat": 53.4717553, "lon": 9.9313936, "tags": {"bus": "yes", "name": "Zum F\u00fcrstenmoor", "network": "HVV", "public_transport": "stop_position"}}, {"type": "node", "id": 5757290057, "lat": 53.4718298, "lon": 9.9297128, "tags": {"crossing": "unmarked", "highway": "crossing"}}, {"type": "node", "id": 5757290060, "lat": 53.4718154, "lon": 9.9317736}, {"type": "node", "id": 5757290071, "lat": 53.4718393, "lon": 9.9331113, "tags": {"crossing": "uncontrolled", "highway": "crossing"}}, {"type": "node", "id": 5781475976, "lat": 53.4714327, "lon": 9.9160576}, {"type": "node", "id": 5781505071, "lat": 53.4709333, "lon": 9.9335618}, {"type": "node", "id": 5916498256, "lat": 53.4719123, "lon": 9.9297299}, {"type": "node", "id": 5916498416, "lat": 53.4718528, "lon": 9.9280778, "tags": {"crossing": "unmarked", "highway": "crossing"}}, {"type": "node", "id": 5916498417, "lat": 53.4718622, "lon": 9.9262314, "tags": {"crossing": "unmarked", "highway": "crossing"}}, {"type": "node", "id": 5916502322, "lat": 53.4721993, "lon": 9.9319282}, {"type": "node", "id": 6066043553, "lat": 53.4678574, "lon": 9.9276983, "tags": {"barrier": "gate"}}, {"type": "node", "id": 6066043554, "lat": 53.4679318, "lon": 9.9277258}, {"type": "node", "id": 6066043572, "lat": 53.4678348, "lon": 9.92769}, {"type": "node", "id": 6066043573, "lat": 53.4677161, "lon": 9.9276126}, {"type": "node", "id": 6066043574, "lat": 53.4674752, "lon": 9.9274383}, {"type": "node", "id": 6066043575, "lat": 53.4672832, "lon": 9.92733}, {"type": "node", "id": 6066043576, "lat": 53.4671276, "lon": 9.9272527}, {"type": "node", "id": 6066043577, "lat": 53.4669497, "lon": 9.9271932}, {"type": "node", "id": 6066043578, "lat": 53.4667286, "lon": 9.9271387}, {"type": "node", "id": 6066043579, "lat": 53.4666249, "lon": 9.9271216}, {"type": "node", "id": 6066043580, "lat": 53.4665498, "lon": 9.9271199}, {"type": "node", "id": 6066043581, "lat": 53.4664543, "lon": 9.9271387}, {"type": "node", "id": 6066043582, "lat": 53.4663651, "lon": 9.9271769}, {"type": "node", "id": 6066043583, "lat": 53.4662502, "lon": 9.9272356}, {"type": "node", "id": 6066043584, "lat": 53.4658842, "lon": 9.9274489}, {"type": "node", "id": 6066043785, "lat": 53.465587, "lon": 9.9276159}, {"type": "node", "id": 6066043786, "lat": 53.46522, "lon": 9.9278251}, {"type": "node", "id": 6066043787, "lat": 53.4651018, "lon": 9.9279025}, {"type": "node", "id": 6066043788, "lat": 53.4650237, "lon": 9.9279742}, {"type": "node", "id": 6066043789, "lat": 53.4647244, "lon": 9.9294971}, {"type": "node", "id": 6066043792, "lat": 53.4648186, "lon": 9.9281549}, {"type": "node", "id": 6066043793, "lat": 53.464967, "lon": 9.9280499}, {"type": "node", "id": 6066043794, "lat": 53.4649151, "lon": 9.9281517}, {"type": "node", "id": 6066043795, "lat": 53.4648632, "lon": 9.9282974}, {"type": "node", "id": 6066043796, "lat": 53.4648487, "lon": 9.9284326}, {"type": "node", "id": 6066043797, "lat": 53.4648317, "lon": 9.9286826}, {"type": "node", "id": 6066043798, "lat": 53.4647862, "lon": 9.92908}, {"type": "node", "id": 6066043799, "lat": 53.4646558, "lon": 9.9299611}, {"type": "node", "id": 6066043800, "lat": 53.4645535, "lon": 9.9306549}, {"type": "node", "id": 6066043801, "lat": 53.4644371, "lon": 9.9314538}, {"type": "node", "id": 6066043802, "lat": 53.4643814, "lon": 9.9318552}, {"type": "node", "id": 6066043803, "lat": 53.4642563, "lon": 9.9326744}, {"type": "node", "id": 6066043804, "lat": 53.4641196, "lon": 9.933523}, {"type": "node", "id": 6066043805, "lat": 53.4641438, "lon": 9.9334155}, {"type": "node", "id": 6066043808, "lat": 53.4640746, "lon": 9.9336735}, {"type": "node", "id": 6066043986, "lat": 53.4706833, "lon": 9.9285968}, {"type": "node", "id": 6066043987, "lat": 53.4707859, "lon": 9.9308852}, {"type": "node", "id": 6066043988, "lat": 53.470855, "lon": 9.9303316}, {"type": "node", "id": 6276935885, "lat": 53.4714436, "lon": 9.9146893}, {"type": "node", "id": 6276935886, "lat": 53.4714339, "lon": 9.9145924}, {"type": "node", "id": 6276935887, "lat": 53.4714023, "lon": 9.9144347}, {"type": "node", "id": 6276935888, "lat": 53.4713523, "lon": 9.9141818}, {"type": "node", "id": 6276935894, "lat": 53.4707249, "lon": 9.9165314}, {"type": "node", "id": 6276935914, "lat": 53.4708959, "lon": 9.9166033}, {"type": "node", "id": 6295334008, "lat": 53.4777667, "lon": 9.9262817, "tags": {"bicycle": "yes", "button_operated": "no", "crossing": "traffic_signals", "highway": "crossing", "tactile_paving": "no", "traffic_signals:sound": "no"}}, {"type": "node", "id": 6295334010, "lat": 53.4777291, "lon": 9.9260413}, {"type": "node", "id": 6295334021, "lat": 53.4775868, "lon": 9.9258833}, {"type": "node", "id": 6295334022, "lat": 53.4778529, "lon": 9.9264099}, {"type": "node", "id": 6295334023, "lat": 53.4777364, "lon": 9.9262366, "tags": {"highway": "traffic_signals"}}, {"type": "node", "id": 6295334024, "lat": 53.4775644, "lon": 9.9259584}, {"type": "node", "id": 6295334025, "lat": 53.4778051, "lon": 9.9265163, "tags": {"highway": "traffic_signals"}}, {"type": "node", "id": 6295334026, "lat": 53.4775984, "lon": 9.9269682}, {"type": "node", "id": 6295334027, "lat": 53.4773729, "lon": 9.9274772}, {"type": "node", "id": 6295334028, "lat": 53.4772061, "lon": 9.9279036}, {"type": "node", "id": 6295334029, "lat": 53.4770624, "lon": 9.9283549}, {"type": "node", "id": 6295334030, "lat": 53.4769934, "lon": 9.9286064}, {"type": "node", "id": 6337537928, "lat": 53.4730961, "lon": 9.920581}, {"type": "node", "id": 6337537929, "lat": 53.4731365, "lon": 9.9203017}, {"type": "node", "id": 6337537930, "lat": 53.4733105, "lon": 9.9192315}, {"type": "node", "id": 6350951459, "lat": 53.4706631, "lon": 9.9271065, "tags": {"highway": "traffic_signals"}}, {"type": "node", "id": 6390452982, "lat": 53.4707642, "lon": 9.9274085}, {"type": "node", "id": 6390452983, "lat": 53.4707327, "lon": 9.9274517}, {"type": "node", "id": 6390452984, "lat": 53.470713, "lon": 9.9274667}, {"type": "node", "id": 6390453385, "lat": 53.4706876, "lon": 9.9274799}, {"type": "node", "id": 6390453386, "lat": 53.4707503, "lon": 9.927431}, {"type": "node", "id": 6390453387, "lat": 53.47075, "lon": 9.9273408}, {"type": "node", "id": 6390453388, "lat": 53.4707291, "lon": 9.9273118}, {"type": "node", "id": 6390453389, "lat": 53.4707011, "lon": 9.9272927}, {"type": "node", "id": 6390453413, "lat": 53.471731, "lon": 9.9327028}, {"type": "node", "id": 6390453419, "lat": 53.4738542, "lon": 9.9287869}, {"type": "node", "id": 6390453420, "lat": 53.4738013, "lon": 9.9289747}, {"type": "node", "id": 6390453421, "lat": 53.4759933, "lon": 9.9260793, "tags": {"traffic_calming": "choker"}}, {"type": "node", "id": 6390453436, "lat": 53.4754127, "lon": 9.932272, "tags": {"traffic_calming": "choker"}}, {"type": "node", "id": 6390453437, "lat": 53.4754817, "lon": 9.9314802, "tags": {"traffic_calming": "choker"}}, {"type": "node", "id": 6390453438, "lat": 53.4755678, "lon": 9.930564, "tags": {"traffic_calming": "choker"}}, {"type": "node", "id": 6390453439, "lat": 53.4756337, "lon": 9.9298791, "tags": {"traffic_calming": "choker"}}, {"type": "node", "id": 6390453440, "lat": 53.4757122, "lon": 9.9289882, "tags": {"traffic_calming": "choker"}}, {"type": "node", "id": 6428164808, "lat": 53.4673831, "lon": 9.9273864}, {"type": "node", "id": 6544348071, "lat": 53.4680246, "lon": 9.9271264}, {"type": "node", "id": 6544348072, "lat": 53.4667159, "lon": 9.9253227}, {"type": "node", "id": 6544348073, "lat": 53.4666684, "lon": 9.9251752}, {"type": "node", "id": 6544348074, "lat": 53.4667961, "lon": 9.9255346}, {"type": "node", "id": 6544348075, "lat": 53.4665986, "lon": 9.9249244}, {"type": "node", "id": 6544348076, "lat": 53.4665315, "lon": 9.9246045}, {"type": "node", "id": 6544348077, "lat": 53.4664864, "lon": 9.9243128}, {"type": "node", "id": 6544348078, "lat": 53.466458, "lon": 9.9241003}, {"type": "node", "id": 6544348079, "lat": 53.4664453, "lon": 9.923944}, {"type": "node", "id": 6544348080, "lat": 53.4664429, "lon": 9.9237261}, {"type": "node", "id": 6544348081, "lat": 53.4664481, "lon": 9.9236181}, {"type": "node", "id": 6544348082, "lat": 53.4664624, "lon": 9.9235008}, {"type": "node", "id": 6544348083, "lat": 53.466488, "lon": 9.9233573}, {"type": "node", "id": 6544348084, "lat": 53.4665115, "lon": 9.9232554}, {"type": "node", "id": 6544443785, "lat": 53.4665427, "lon": 9.9231521}, {"type": "node", "id": 6544443786, "lat": 53.4665854, "lon": 9.9230462}, {"type": "node", "id": 6544443787, "lat": 53.4666365, "lon": 9.9229496}, {"type": "node", "id": 6544443788, "lat": 53.4666852, "lon": 9.9228738}, {"type": "node", "id": 6544443789, "lat": 53.4667351, "lon": 9.9228141}, {"type": "node", "id": 6544443790, "lat": 53.4667822, "lon": 9.9227659}, {"type": "node", "id": 6544443791, "lat": 53.4668281, "lon": 9.922729}, {"type": "node", "id": 6544443792, "lat": 53.466886, "lon": 9.9226921}, {"type": "node", "id": 6544443793, "lat": 53.466943, "lon": 9.922668}, {"type": "node", "id": 6544443794, "lat": 53.4670173, "lon": 9.9226519}, {"type": "node", "id": 6544443795, "lat": 53.4671243, "lon": 9.9226472}, {"type": "node", "id": 6544443796, "lat": 53.46723, "lon": 9.9226653}, {"type": "node", "id": 6544443797, "lat": 53.4673354, "lon": 9.9227008}, {"type": "node", "id": 6544443798, "lat": 53.4674428, "lon": 9.9227471}, {"type": "node", "id": 6544443799, "lat": 53.4676635, "lon": 9.9269079}, {"type": "node", "id": 6544443800, "lat": 53.4675134, "lon": 9.9268086}, {"type": "node", "id": 6544443801, "lat": 53.4673658, "lon": 9.9267215}, {"type": "node", "id": 6544443802, "lat": 53.4661016, "lon": 9.9269497}, {"type": "node", "id": 6544443803, "lat": 53.467234, "lon": 9.9266584}, {"type": "node", "id": 6544443804, "lat": 53.4671279, "lon": 9.9266343}, {"type": "node", "id": 6544443805, "lat": 53.4670177, "lon": 9.9266236}, {"type": "node", "id": 6544443806, "lat": 53.4669243, "lon": 9.9266303}, {"type": "node", "id": 6544443807, "lat": 53.4668213, "lon": 9.9266504}, {"type": "node", "id": 6544443808, "lat": 53.4666888, "lon": 9.9266906}, {"type": "node", "id": 6544443809, "lat": 53.4664429, "lon": 9.9267952}, {"type": "node", "id": 6544443810, "lat": 53.4658681, "lon": 9.9270554}, {"type": "node", "id": 6544443811, "lat": 53.4649372, "lon": 9.9274684}, {"type": "node", "id": 6544443812, "lat": 53.464617, "lon": 9.9276133}, {"type": "node", "id": 6544443813, "lat": 53.4643967, "lon": 9.9277152}, {"type": "node", "id": 6544443814, "lat": 53.4641879, "lon": 9.9278171}, {"type": "node", "id": 6544443815, "lat": 53.4676108, "lon": 9.9266464}, {"type": "node", "id": 6544443816, "lat": 53.4673817, "lon": 9.9263875}, {"type": "node", "id": 6710966671, "lat": 53.474223, "lon": 9.9335894, "tags": {"level": "0"}}, {"type": "node", "id": 6710981799, "lat": 53.4753603, "lon": 9.9328576}, {"type": "node", "id": 6710981804, "lat": 53.4745523, "lon": 9.9329793}, {"type": "node", "id": 6710991598, "lat": 53.4728806, "lon": 9.9330775}, {"type": "node", "id": 6710991601, "lat": 53.4731115, "lon": 9.9331849}, {"type": "node", "id": 7027819867, "lat": 53.4707602, "lon": 9.9085362}, {"type": "node", "id": 7045563265, "lat": 53.4705005, "lon": 9.9174417}, {"type": "node", "id": 7045746558, "lat": 53.4705277, "lon": 9.9185218}, {"type": "node", "id": 7045746564, "lat": 53.4705317, "lon": 9.9186819}, {"type": "node", "id": 7045746569, "lat": 53.4705497, "lon": 9.9193963}, {"type": "node", "id": 7045746572, "lat": 53.4707692, "lon": 9.9270748}, {"type": "node", "id": 7118138488, "lat": 53.4710006, "lon": 9.9369266, "tags": {"crossing": "no", "highway": "traffic_signals", "traffic_signals:direction": "forward"}}, {"type": "node", "id": 7132497781, "lat": 53.4713436, "lon": 9.9138406}, {"type": "node", "id": 7134753775, "lat": 53.4708043, "lon": 9.9080407}, {"type": "node", "id": 7187572031, "lat": 53.4708502, "lon": 9.9301351}, {"type": "node", "id": 7187572046, "lat": 53.4708192, "lon": 9.9289552}, {"type": "node", "id": 7187572111, "lat": 53.4706586, "lon": 9.9096436}, {"type": "node", "id": 7187572131, "lat": 53.4705125, "lon": 9.9113242}, {"type": "node", "id": 7187572135, "lat": 53.4709554, "lon": 9.9166283}, {"type": "node", "id": 7187572137, "lat": 53.4713138, "lon": 9.9167415}, {"type": "node", "id": 7332940950, "lat": 53.4709329, "lon": 9.9343677}, {"type": "node", "id": 7332940953, "lat": 53.4709383, "lon": 9.9338755}, {"type": "node", "id": 7332969262, "lat": 53.4725682, "lon": 9.9320188}, {"type": "node", "id": 7332969263, "lat": 53.4726185, "lon": 9.9319732}, {"type": "node", "id": 7332969264, "lat": 53.4726368, "lon": 9.9319625}, {"type": "node", "id": 7332969265, "lat": 53.4726552, "lon": 9.9319544}, {"type": "node", "id": 7332969266, "lat": 53.4726775, "lon": 9.9319524}, {"type": "node", "id": 7332969267, "lat": 53.4737296, "lon": 9.9324037}, {"type": "node", "id": 7332969268, "lat": 53.4737583, "lon": 9.9324198}, {"type": "node", "id": 7332969269, "lat": 53.4737771, "lon": 9.9324379}, {"type": "node", "id": 7332969270, "lat": 53.4737982, "lon": 9.9324667}, {"type": "node", "id": 7332969271, "lat": 53.473884, "lon": 9.9325988}, {"type": "node", "id": 7332969272, "lat": 53.4739044, "lon": 9.9326277}, {"type": "node", "id": 7332969273, "lat": 53.4739228, "lon": 9.9326471}, {"type": "node", "id": 7332969283, "lat": 53.474385, "lon": 9.9328455}, {"type": "node", "id": 7333015907, "lat": 53.4744843, "lon": 9.9328879}, {"type": "node", "id": 7333015908, "lat": 53.4745039, "lon": 9.9329019}, {"type": "node", "id": 7333015909, "lat": 53.474519, "lon": 9.932916}, {"type": "node", "id": 7333015910, "lat": 53.474533, "lon": 9.9329375}, {"type": "node", "id": 7333015911, "lat": 53.474544, "lon": 9.9329593}, {"type": "node", "id": 7333015912, "lat": 53.4745613, "lon": 9.9330052}, {"type": "node", "id": 7333015913, "lat": 53.4745669, "lon": 9.9330313}, {"type": "node", "id": 7333015914, "lat": 53.4745717, "lon": 9.9330682}, {"type": "node", "id": 7333015915, "lat": 53.4745713, "lon": 9.9331111}, {"type": "node", "id": 7333015916, "lat": 53.4745669, "lon": 9.9331561}, {"type": "node", "id": 7333015960, "lat": 53.4722362, "lon": 9.9332911, "tags": {"traffic_calming": "choker"}}, {"type": "node", "id": 7333043259, "lat": 53.473245, "lon": 9.9321978}, {"type": "node", "id": 7333044941, "lat": 53.4718693, "lon": 9.9317777}, {"type": "node", "id": 7333044942, "lat": 53.4724258, "lon": 9.9320315}, {"type": "node", "id": 7333044943, "lat": 53.4725207, "lon": 9.9321261}, {"type": "node", "id": 7333044944, "lat": 53.4725195, "lon": 9.9321603}, {"type": "node", "id": 7333044945, "lat": 53.4725195, "lon": 9.9322012}, {"type": "node", "id": 7333044946, "lat": 53.4725155, "lon": 9.9322502}, {"type": "node", "id": 7333044947, "lat": 53.472454, "lon": 9.9326424}, {"type": "node", "id": 7333044948, "lat": 53.4724448, "lon": 9.9327222}, {"type": "node", "id": 7333044949, "lat": 53.4724421, "lon": 9.9327584}, {"type": "node", "id": 7333044950, "lat": 53.4724437, "lon": 9.93279}, {"type": "node", "id": 7333044951, "lat": 53.4724476, "lon": 9.9328201}, {"type": "node", "id": 7333044952, "lat": 53.4724544, "lon": 9.9328416}, {"type": "node", "id": 7333044953, "lat": 53.4724668, "lon": 9.9328657}, {"type": "node", "id": 7333044954, "lat": 53.4724812, "lon": 9.9328892}, {"type": "node", "id": 7333044955, "lat": 53.4725047, "lon": 9.9329086}, {"type": "node", "id": 7333054573, "lat": 53.4744193, "lon": 9.9336741}, {"type": "node", "id": 7333054577, "lat": 53.4745684, "lon": 9.9331409}, {"type": "node", "id": 7358990328, "lat": 53.4764422, "lon": 9.9244334}, {"type": "node", "id": 7358990329, "lat": 53.4762552, "lon": 9.9243309}, {"type": "node", "id": 7358990330, "lat": 53.4763236, "lon": 9.9243656}, {"type": "node", "id": 7358990331, "lat": 53.4763982, "lon": 9.9244073}, {"type": "node", "id": 7358990332, "lat": 53.4764838, "lon": 9.924461}, {"type": "node", "id": 7358990333, "lat": 53.4765377, "lon": 9.9245037}, {"type": "node", "id": 7358990334, "lat": 53.4765846, "lon": 9.9245535}, {"type": "node", "id": 7358990350, "lat": 53.4720213, "lon": 9.9262826}, {"type": "node", "id": 7358990351, "lat": 53.4729078, "lon": 9.9266749}, {"type": "node", "id": 7358990352, "lat": 53.4744176, "lon": 9.9340893}, {"type": "node", "id": 7848250478, "lat": 53.4714447, "lon": 9.9148034}, {"type": "node", "id": 7848250481, "lat": 53.4714365, "lon": 9.9156451}, {"type": "node", "id": 8636392750, "lat": 53.4643906, "lon": 9.926519}, {"type": "node", "id": 8636392752, "lat": 53.464345, "lon": 9.9264687}, {"type": "node", "id": 8636392753, "lat": 53.4642108, "lon": 9.9264098}, {"type": "node", "id": 8636392762, "lat": 53.4630403, "lon": 9.9264466}, {"type": "node", "id": 9327811331, "lat": 53.4728832, "lon": 9.9184191}, {"type": "node", "id": 9327811332, "lat": 53.4733208, "lon": 9.9180688}, {"type": "node", "id": 9327811333, "lat": 53.4743601, "lon": 9.9173178}, {"type": "node", "id": 9327811334, "lat": 53.4745229, "lon": 9.9172057}, {"type": "node", "id": 9327811335, "lat": 53.4769962, "lon": 9.915832}, {"type": "node", "id": 9327811336, "lat": 53.475618, "lon": 9.9165211}, {"type": "node", "id": 9327811337, "lat": 53.4763146, "lon": 9.9161534}, {"type": "node", "id": 9327811338, "lat": 53.4776641, "lon": 9.9155432}, {"type": "node", "id": 9327811339, "lat": 53.4792554, "lon": 9.914983}, {"type": "node", "id": 9327811340, "lat": 53.4804559, "lon": 9.9146693}, {"type": "node", "id": 9327811342, "lat": 53.4818525, "lon": 9.9143934}, {"type": "node", "id": 9954813870, "lat": 53.4646212, "lon": 9.9270798}, {"type": "way", "id": 1978, "nodes": [10210552, 277783046, 5186817684], "tags": {"bicycle": "use_sidepath", "foot": "use_sidepath", "highway": "primary", "lanes": "4", "lit": "yes", "maxspeed": "50", "name": "Cuxhavener Stra\u00dfe", "ref": "B 73", "sidewalk": "separate", "smoothness": "good", "surface": "asphalt", "wikidata": "Q106605121"}}, {"type": "way", "id": 3042432, "nodes": [491181, 938641844, 904439306, 2186528454], "tags": {"bdouble": "yes", "highway": "motorway", "int_ref": "E 45", "lanes": "4", "lit": "no", "maxspeed": "80", "oneway": "yes", "ref": "A 7", "source": "GPS and Videomapping", "surface": "asphalt", "turn:lanes": "none|none|none|merge_to_left"}}, {"type": "way", "id": 3042480, "nodes": [495998, 6544443814, 6544443813, 6544443812], "tags": {"destination": "HH-Heimfeld;-Harburg;Cuxhaven", "destination:ref": "B 73", "highway": "motorway_link", "lanes": "1", "lit": "no", "maxspeed": "120", "oneway": "yes", "surface": "asphalt"}}, {"type": "way", "id": 3988032, "nodes": [7187572137, 1329489337, 5188452523, 5188452524, 20834533, 5781475976, 7848250481, 7848250478, 6276935885, 6276935886, 6276935887, 6276935888, 1705403281, 7132497781, 1705403282, 20834534], "tags": {"cycleway:both": "no", "highway": "unclassified", "lane_markings": "no", "lit": "yes", "maxspeed": "50", "name": "F\u00f6rsterkamp", "oneway": "no", "sidewalk": "left", "smoothness": "good", "surface": "asphalt"}}, {"type": "way", "id": 4241680, "nodes": [10210552, 5186817680, 5186817679, 5186817678, 277783027, 5186817677, 5188443320, 7187572131, 5188452521, 7187572111, 5186817676, 7027819867, 5186817675, 7134753775, 5186817674, 5186817673, 10210551, 5186817670], "tags": {"bicycle": "use_sidepath", "foot": "use_sidepath", "highway": "primary", "lanes": "4", "lit": "yes", "maxspeed": "50", "name": "Cuxhavener Stra\u00dfe", "ref": "B 73", "sidewalk": "both", "surface": "asphalt", "wikidata": "Q106605121"}}, {"type": "way", "id": 4359547, "nodes": [12217094, 2186528516, 1329457818, 2186528515, 5188449911], "tags": {"cycleway:right": "track", "destination": "Hannover;Bremen;Flensburg;Kiel", "destination:ref": "A 7", "highway": "motorway_link", "lanes": "2", "lit": "yes", "maxspeed": "50", "motorroad": "no", "oneway": "yes", "sidewalk": "right", "surface": "asphalt", "turn:lanes": "right|right"}}, {"type": "way", "id": 4389125, "nodes": [5695472059, 496006, 914941176, 5695472052], "tags": {"bdouble": "yes", "bridge": "yes", "hazmat:water": "permissive", "highway": "motorway", "int_ref": "E 45", "lanes": "4", "layer": "1", "lit": "no", "maxspeed": "80", "maxspeed:variable": "signals", "oneway": "yes", "ref": "A 7", "source": "GPS and Videomapping", "surface": "asphalt", "turn:lanes": "none|none|none|merge_to_left"}}, {"type": "way", "id": 4389127, "nodes": [5695472053, 904439292, 491178, 5695472060], "tags": {"bdouble": "yes", "bridge": "yes", "destination:lanes": "Hannover Bremen;HH-S\u00fcdwest|Hannover Bremen;HH-S\u00fcdwest|Hannover Bremen;HH-S\u00fcdwest|HH-Heimfeld;-Harburg;Cuxhaven", "highway": "motorway", "int_ref": "E 45", "lanes": "4", "layer": "1", "lit": "no", "maxspeed": "80", "oneway": "yes", "ref": "A 7", "source": "GPS and Videomapping", "surface": "asphalt", "turn:lanes": "none|none|none|slight_right"}}, {"type": "way", "id": 4389128, "nodes": [30773700, 2186558889, 496010, 914951655, 2186558867], "tags": {"bdouble": "yes", "destination:lanes": "Flensburg;HH-Waltershof|Flensburg;HH-Waltershof|Flensburg;HH-Waltershof;HH-Hausbruch;Hafen Harburg", "destination:ref:lanes": "A 7|A 7|A 7", "highway": "motorway", "int_ref": "E 45", "lanes": "3", "lit": "no", "maxspeed": "80", "maxspeed:variable": "signals", "oneway": "yes", "ref": "A 7", "source": "GPS and Videomapping", "surface": "asphalt", "turn:lanes": "through|through|through;slight_right"}}, {"type": "way", "id": 4462746, "nodes": [27370272, 431520581, 431520580, 431520592, 7358990334, 7358990333, 7358990332, 7358990328], "tags": {"cycleway:left": "opposite_track", "cycleway:right": "track", "highway": "unclassified", "lanes": "2", "lit": "yes", "maxspeed:type": "DE:urban", "name": "Mercedesstra\u00dfe", "oneway": "no", "sidewalk": "both", "surface": "asphalt"}}, {"type": "way", "id": 4462747, "nodes": [27370275, 3464833580, 431520608, 3464734095, 1705403364, 3464734098], "tags": {"cycleway:both": "no", "highway": "unclassified", "lanes": "2", "lit": "yes", "maxspeed:type": "DE:urban", "name": "Ellernweg", "oneway": "no", "sidewalk": "right", "surface": "asphalt"}}, {"type": "way", "id": 4462748, "nodes": [27370302, 5916498417, 7358990350, 7358990351, 27370281, 1705388905, 27370277], "tags": {"bicycle": "yes", "foot": "designated", "highway": "residential", "lit": "yes", "maxspeed:type": "DE:urban", "name": "Hoffstra\u00dfe", "surface": "asphalt", "vehicle": "destination"}}, {"type": "way", "id": 4462749, "nodes": [27370301, 5916498416, 1329457910, 1329457937, 27370282, 1705388876, 27370278], "tags": {"bicycle": "yes", "foot": "designated", "highway": "residential", "lit": "yes", "maxspeed:type": "DE:urban", "name": "Heidebruch", "vehicle": "destination"}}, {"type": "way", "id": 4462750, "nodes": [27370281, 6390453419, 27370282, 6390453420, 27370283], "tags": {"bicycle": "yes", "foot": "designated", "highway": "residential", "lit": "yes", "maxspeed:type": "DE:urban", "name": "Falkenweg", "vehicle": "destination"}}, {"type": "way", "id": 4462751, "nodes": [27370300, 5757290057, 5916498256, 27370283, 1705388824, 27370279], "tags": {"bicycle": "yes", "foot": "designated", "highway": "residential", "lit": "yes", "maxspeed:type": "DE:urban", "name": "Am Reiherhorst", "vehicle": "destination"}}, {"type": "way", "id": 4462752, "nodes": [27370284, 7333044943, 7333044944, 7333044945, 7333044946, 7333044947, 7333044948, 7333044949, 7333044950, 7333044951, 7333044952, 7333044953, 7333044954, 7333044955, 254455695, 6710991598, 2239534032, 6710991601, 254455696, 254455697, 3740886658, 6710966671, 7333054573, 27370291], "tags": {"highway": "residential", "lanes": "1", "lit": "yes", "maxspeed": "50", "maxspeed:type": "DE:urban", "name": "Tempowerkring", "narrow": "yes", "sidewalk": "both", "smoothness": "excellent", "surface": "asphalt"}}, {"type": "way", "id": 4462753, "nodes": [7358990352, 27370291, 7333015916, 7333054577, 7333015915, 7333015914, 7333015913, 7333015912, 6710981804, 7333015911, 7333015910, 7333015909, 7333015908, 7333015907, 7332969283, 27370288, 7332969273, 7332969272, 7332969271, 7332969270, 7332969269, 7332969268, 7332969267, 3561092710, 7333043259, 2239534035, 27370285, 7332969266, 7332969265, 7332969264, 7332969263, 3561092859, 7332969262, 27370284], "tags": {"highway": "residential", "lanes": "2", "lit": "yes", "maxspeed": "50", "maxspeed:type": "DE:urban", "name": "Tempowerkring", "narrow": "yes", "sidewalk": "left", "smoothness": "excellent", "surface": "asphalt"}}, {"type": "way", "id": 4769447, "nodes": [491179, 2827008431, 1611670265, 2186528506], "tags": {"destination": "HH-Heimfeld;-Harburg;Cuxhaven", "destination:ref": "B 73", "highway": "motorway_link", "lanes": "1", "lit": "no", "maxspeed": "none", "oneway": "yes", "surface": "asphalt"}}, {"type": "way", "id": 4789093, "nodes": [496002, 30694890], "tags": {"bdouble": "yes", "bridge": "yes", "hazard": "deer_crossing", "hazmat:water": "permissive", "highway": "motorway", "int_ref": "E 45", "lanes": "3", "layer": "1", "lit": "no", "maxspeed": "80", "maxspeed:variable": "signals", "oneway": "yes", "ref": "A 7", "source": "GPS and Videomapping", "surface": "asphalt"}}, {"type": "way", "id": 4789094, "nodes": [26805105, 2229897854, 491179], "tags": {"bdouble": "yes", "highway": "motorway", "int_ref": "E 45", "lanes": "4", "lit": "no", "maxspeed": "80", "oneway": "yes", "ref": "A 7", "source": "GPS and Videomapping", "surface": "asphalt", "turn:lanes": "none|none|none|slight_right"}}, {"type": "way", "id": 4789095, "nodes": [491180, 491181], "tags": {"bdouble": "yes", "bridge": "yes", "highway": "motorway", "int_ref": "E 45", "lanes": "4", "layer": "1", "lit": "no", "maxspeed": "80", "oneway": "yes", "ref": "A 7", "source": "GPS and Videomapping", "surface": "asphalt", "turn:lanes": "none|none|none|merge_to_left"}}, {"type": "way", "id": 4796390, "nodes": [496007, 914951664, 914943907, 937904942, 2186558854], "tags": {"bdouble": "yes", "destination:lanes": "Flensburg;HH-Waltershof|Flensburg;HH-Waltershof|Flensburg;HH-Waltershof;HH-Hausbruch;Hafen Harburg", "destination:ref:lanes": "A 7|A 7|A 7", "hazmat:water": "permissive", "highway": "motorway", "int_ref": "E 45", "lanes": "3", "lit": "no", "maxspeed": "80", "maxspeed:variable": "signals", "oneway": "yes", "ref": "A 7", "source": "GPS and Videomapping", "surface": "asphalt", "turn:lanes": "through|through|through;slight_right"}}, {"type": "way", "id": 4796391, "nodes": [30773702, 30773700], "tags": {"bdouble": "yes", "bridge": "yes", "destination:lanes": "Flensburg;HH-Waltershof|Flensburg;HH-Waltershof|Flensburg;HH-Waltershof;HH-Hausbruch;Hafen Harburg", "destination:ref:lanes": "A 7|A 7|A 7", "highway": "motorway", "int_ref": "E 45", "lanes": "3", "layer": "1", "lit": "no", "maxspeed": "80", "maxspeed:variable": "signals", "oneway": "yes", "ref": "A 7", "source": "GPS and Videomapping", "surface": "asphalt", "turn:lanes": "through|through|through;slight_right"}}, {"type": "way", "id": 4943634, "nodes": [10377765, 2186528505, 94178399, 2186528500, 2186528498, 94178401, 2186528494, 2186528493, 32575169, 2186528491, 1548998521, 2186528492, 32575170, 2186528495, 2186528496, 32575171, 2186528503, 2186528507, 2186528509, 496004], "tags": {"destination": "Flensburg;Kiel;Hamburg", "destination:ref": "A 7", "destination:symbol": "airport", "highway": "motorway_link", "lanes": "1", "lit": "no", "maxspeed": "none", "oneway": "yes", "surface": "asphalt"}}, {"type": "way", "id": 5028258, "nodes": [6066043553, 6066043572, 6066043573, 6066043574, 6428164808, 6066043575, 6066043576, 6066043577, 298511648, 6066043578, 6066043579, 6066043580, 6066043581, 6066043582, 6066043583, 6066043584, 6066043785, 6066043786, 6066043787, 6066043788, 6066043793, 6066043794, 6066043795], "tags": {"highway": "unclassified", "lane_markings": "no", "lit": "no", "maxspeed:type": "DE:urban", "name": "Kuhtrift", "surface": "asphalt", "wikidata": "Q106605590"}}, {"type": "way", "id": 10661057, "nodes": [1329457860, 6390453387, 6390453388, 6390453389, 94178394], "tags": {"destination": "Hannover;Bremen;Flensburg;Kiel", "destination:ref": "A 7", "highway": "motorway_link", "lanes": "2", "lit": "yes", "maxspeed": "50", "motorroad": "no", "oneway": "yes", "surface": "asphalt"}}, {"type": "way", "id": 19190459, "nodes": [199057380, 5695472089, 199057382], "tags": {"highway": "residential", "lanes": "2", "lit": "yes", "maxspeed": "50", "maxspeed:type": "DE:urban", "name": "Zum F\u00fcrstenmoor", "surface": "asphalt"}}, {"type": "way", "id": 23630617, "nodes": [33565710, 8636392750, 8636392752, 3465594379, 8636392753, 3465594377, 1549002234, 8636392762], "tags": {"highway": "unclassified", "lane_markings": "no", "lit": "no", "maxspeed:type": "DE:urban", "name": "Kuhtrift", "operator:type": "private", "surface": "asphalt", "wikidata": "Q106605590"}}, {"type": "way", "id": 25111751, "nodes": [33565708, 33565710], "tags": {"cycleway:both": "no", "highway": "unclassified", "lane_markings": "no", "lit": "no", "maxspeed:type": "DE:urban", "name": "Kuhtrift", "operator:type": "private", "surface": "asphalt", "wikidata": "Q106605590"}}, {"type": "way", "id": 25111760, "nodes": [273402378, 33565708], "tags": {"cycleway:both": "no", "highway": "unclassified", "lane_markings": "no", "layer": "-1", "lit": "no", "maxheight": "default", "maxspeed:type": "DE:urban", "name": "Kuhtrift", "operator:type": "private", "surface": "asphalt", "tunnel": "yes", "wikidata": "Q106605590"}}, {"type": "way", "id": 28115865, "nodes": [21479665, 2590674807, 27370303, 1705387867, 27370298], "tags": {"highway": "unclassified", "maxspeed": "50", "maxspeed:type": "DE:urban", "name": "Am Radeland", "surface": "asphalt"}}, {"type": "way", "id": 30712131, "nodes": [4242775790, 290351150, 6066043554, 6066043553], "tags": {"access": "permissive", "highway": "unclassified", "name": "Kuhtrift", "wikidata": "Q106605590"}}, {"type": "way", "id": 30979729, "nodes": [5757290021, 5757289820, 5757289819, 5757289818, 5757289817, 5757289816, 5757289815, 5757289814, 5757289813, 1705403285], "tags": {"highway": "unclassified", "maxspeed": "30", "name": "Am Radeland", "surface": "asphalt"}}, {"type": "way", "id": 32979104, "nodes": [27370275, 590842473, 431520567, 6390453421, 431520588, 27370336, 27370277], "tags": {"highway": "unclassified", "maxspeed": "30", "maxspeed:type": "DE:zone30", "name": "Ellernweg", "surface": "asphalt"}}, {"type": "way", "id": 32979105, "nodes": [27370277, 27370337, 1705388909, 6390453440, 27370278, 6390453439, 6390453438, 27370279, 6390453437, 6390453436, 27370345, 6710981799, 1705388817], "tags": {"highway": "residential", "lanes": "2", "lit": "yes", "maxspeed": "30", "maxspeed:type": "DE:zone30", "name": "Ellernweg", "surface": "asphalt"}}, {"type": "way", "id": 32979106, "nodes": [27370302, 5757290025, 5757290027, 1329457897, 462742973, 462742967, 1122404450, 1122404433, 3175147432, 26400810, 5757150048], "tags": {"highway": "unclassified", "lanes": "2", "lit": "yes", "maxspeed": "30", "maxspeed:type": "DE:zone30", "name": "Am Radeland", "oneway": "no", "sidewalk": "right", "smoothness": "good", "surface": "asphalt"}}, {"type": "way", "id": 32979107, "nodes": [26400809, 462742943, 1122404435, 462742924], "tags": {"highway": "unclassified", "lanes": "2", "lit": "yes", "maxspeed": "30", "maxspeed:type": "DE:zone30", "name": "Am Radeland", "surface": "asphalt"}}, {"type": "way", "id": 39627946, "nodes": [6066043808, 6066043804, 6066043805, 33565684, 6066043803, 6066043802, 6066043801, 6066043800, 6066043799, 6066043789], "tags": {"cycleway:both": "no", "highway": "unclassified", "lane_markings": "no", "lit": "no", "maxspeed:type": "DE:urban", "name": "Kuhtrift", "operator:type": "private", "surface": "asphalt", "wikidata": "Q106605590"}}, {"type": "way", "id": 69595320, "nodes": [2080670385, 5695460643, 5695460644, 25984393, 5186817788, 5186817789, 5757149941], "tags": {"bicycle:backward": "use_sidepath", "bicycle:forward": "use_sidepath", "highway": "primary", "lanes": "4", "lit": "yes", "maxheight": "default", "maxspeed": "50", "name": "Stader Stra\u00dfe", "ref": "B 73", "sidewalk": "separate", "surface": "asphalt", "wikidata": "Q106605949"}}, {"type": "way", "id": 118148689, "nodes": [1329457840, 12217094], "tags": {"cycleway:right": "track", "destination": "Elbbr\u00fccken", "destination:ref": "B 73", "highway": "primary", "lanes": "2", "lit": "yes", "maxspeed": "50", "name": "Stader Stra\u00dfe", "oneway": "yes", "ref": "B 73", "sidewalk": "right", "surface": "asphalt", "wikidata": "Q106605949"}}, {"type": "way", "id": 118148690, "nodes": [700978924, 1329457893, 5704964483, 1329457891], "tags": {"cycleway:right": "use_sidepath", "highway": "primary", "lanes": "2", "lit": "yes", "maxspeed": "50", "name": "Stader Stra\u00dfe", "oneway": "yes", "ref": "B 73", "sidewalk": "right", "surface": "asphalt", "wikidata": "Q106605949"}}, {"type": "way", "id": 118148691, "nodes": [700978924, 199057380, 5781505071, 7332940953, 7332940950, 3740881955, 1705486885, 3529202635, 1703646589, 3529202636, 7118138488, 24302167, 3529202856], "tags": {"highway": "primary", "lanes": "4", "lanes:backward": "2", "lanes:forward": "2", "lit": "yes", "maxspeed": "50", "name": "Stader Stra\u00dfe", "ref": "B 73", "smoothness": "good", "surface": "asphalt", "wikidata": "Q106605949"}}, {"type": "way", "id": 136483040, "nodes": [94178394, 5188449906, 12217095], "tags": {"destination": "Hannover;Bremen;Flensburg;Kiel", "destination:ref": "A 7", "highway": "motorway_link", "lanes": "2", "lit": "yes", "maxspeed": "50", "motorroad": "no", "oneway": "yes", "surface": "asphalt"}}, {"type": "way", "id": 136483043, "nodes": [122429, 6390453385, 6390452984, 6390452983, 6390453386, 6390452982, 1329457860], "tags": {"destination": "Cuxhaven;Stade;Neugraben", "destination:ref": "B 73", "highway": "motorway_link", "lanes": "2", "lit": "yes", "maxspeed": "50", "motorroad": "no", "oneway": "yes", "surface": "asphalt", "turn:lanes": "left|left"}}, {"type": "way", "id": 136483051, "nodes": [94178394, 122429], "tags": {"cycleway": "track", "destination": "Elbbr\u00fccken", "destination:ref": "B 73", "highway": "primary", "lanes": "2", "lit": "yes", "maxspeed": "50", "name": "Stader Stra\u00dfe", "oneway": "yes", "ref": "B 73", "shoulder": "no", "sidewalk": "no", "surface": "asphalt", "turn:lanes": "through|through", "wikidata": "Q106605949"}}, {"type": "way", "id": 136483052, "nodes": [1329457860, 5188449902, 7045746572, 3740881947, 1329457858], "tags": {"cycleway:right": "use_sidepath", "destination": "Stade;Cuxhaven", "destination:ref": "B 73", "highway": "primary", "lanes": "2", "lit": "yes", "maxspeed": "50", "name": "Stader Stra\u00dfe", "oneway": "yes", "ref": "B 73", "sidewalk": "right", "surface": "asphalt", "wikidata": "Q106605949"}}, {"type": "way", "id": 136483053, "nodes": [122429, 5188449899], "tags": {"cycleway:right": "separate", "destination": "Elbbr\u00fccken", "destination:ref": "B 73", "highway": "primary", "lanes": "2", "lit": "yes", "maxspeed": "50", "name": "Stader Stra\u00dfe", "oneway": "yes", "ref": "B 73", "shoulder": "no", "sidewalk": "no", "surface": "asphalt", "wikidata": "Q106605949"}}, {"type": "way", "id": 183798237, "nodes": [6066043795, 6066043792, 318626148, 273402378], "tags": {"cycleway:both": "no", "highway": "unclassified", "lane_markings": "no", "lit": "no", "maxspeed:type": "DE:urban", "name": "Kuhtrift", "operator:type": "private", "surface": "asphalt", "wikidata": "Q106605590"}}, {"type": "way", "id": 197867913, "nodes": [10377765, 2186528504, 2186528499, 94178382, 6544443815, 2186528489, 6544443816, 10377757, 2186528475], "tags": {"destination": "Hannover;Bremen", "destination:ref": "A 7", "highway": "motorway_link", "lanes": "2", "lit": "no", "maxspeed": "none", "oneway": "yes", "surface": "asphalt"}}, {"type": "way", "id": 197868475, "nodes": [6544348071, 122428, 2186528508, 94178392, 2186528511, 2186528513], "tags": {"destination:ref": "B 73", "highway": "motorway_link", "lanes": "3", "lit": "no", "maxspeed": "60", "motorroad": "no", "oneway": "yes", "surface": "asphalt"}}, {"type": "way", "id": 208354260, "nodes": [491179, 491180], "tags": {"bdouble": "yes", "destination": "Hannover Bremen;HH-S\u00fcdwest", "destination:ref": "A 7", "destination:symbol": "interchange", "highway": "motorway", "int_ref": "E 45", "lanes": "3", "lit": "no", "maxspeed": "80", "oneway": "yes", "ref": "A 7", "source": "GPS and Videomapping", "surface": "asphalt"}}, {"type": "way", "id": 208354261, "nodes": [496004, 26805104], "tags": {"bdouble": "yes", "hazard": "deer_crossing", "hazmat:water": "permissive", "highway": "motorway", "int_ref": "E 45", "lanes": "4", "lit": "no", "maxspeed": "80", "maxspeed:variable": "signals", "oneway": "yes", "ref": "A 7", "source": "GPS and Videomapping", "surface": "asphalt", "turn:lanes": "none|none|none|merge_to_left"}}, {"type": "way", "id": 208354262, "nodes": [9954813870, 904439276, 491184, 491185, 491186, 94170560, 904439295, 491187, 2186528449, 904439325, 2186547771, 491188, 491189, 904439281, 491190, 491191, 904439274, 904439319, 491193, 491194, 904439311, 491195, 491196, 491197, 2171848981, 491198, 904439305, 491199, 904439318, 491201, 904439309, 2171848974], "tags": {"bdouble": "yes", "highway": "motorway", "int_ref": "E 45", "lanes": "3", "lit": "no", "maxheight": "default", "maxspeed": "none", "oneway": "yes", "ref": "A 7", "source": "GPS and Videomapping", "surface": "asphalt"}}, {"type": "way", "id": 208354263, "nodes": [2186528452, 495996, 495997, 495998], "tags": {"bdouble": "yes", "hazard": "deer_crossing", "hazmat:water": "permissive", "highway": "motorway", "int_ref": "E 45", "lanes": "4", "lit": "no", "maxspeed": "80", "maxspeed:variable": "signals", "oneway": "yes", "ref": "A 7", "source": "GPS and Videomapping", "surface": "asphalt", "turn:lanes": "none|none|none|slight_right"}}, {"type": "way", "id": 208354264, "nodes": [495998, 914940032, 495999, 914940027, 914940028, 496002], "tags": {"bdouble": "yes", "destination": "Flensburg Kiel;HH-Hausbruch", "destination:ref": "A 7", "hazard": "deer_crossing", "hazmat:water": "permissive", "highway": "motorway", "int_ref": "E 45", "lanes": "3", "lit": "no", "maxspeed": "80", "maxspeed:variable": "signals", "oneway": "yes", "ref": "A 7", "source": "GPS and Videomapping", "surface": "asphalt"}}, {"type": "way", "id": 208354266, "nodes": [12217095, 278711883, 2186547775, 2186547767], "tags": {"destination": "Hannover;Bremen;Flensburg;Kiel", "destination:ref": "A 7", "highway": "motorway_link", "lanes": "2", "lit": "yes", "maxspeed": "none", "motorroad": "yes", "oneway": "yes", "surface": "asphalt"}}, {"type": "way", "id": 208354267, "nodes": [2186528463, 10377759, 2186528459, 2186528458, 94178406, 2186528462, 2186528464, 10377760, 2186528467, 2186528469, 10377761, 2186528473, 2186528477, 94178408, 2186528480, 2186528482, 10377764, 2186528485, 2186528487, 10377762, 2186528486, 2186528483, 94178410, 491180], "tags": {"destination": "Hannover;Bremen", "destination:ref": "A 7", "highway": "motorway_link", "lanes": "1", "lit": "no", "maxspeed": "none", "oneway": "yes", "surface": "asphalt"}}, {"type": "way", "id": 208354268, "nodes": [2186528513, 2186547774, 2186528514], "tags": {"destination:ref": "B 73", "hazmat:water": "permissive", "highway": "motorway_link", "lanes": "3", "lit": "yes", "maxspeed": "50", "motorroad": "no", "oneway": "yes", "surface": "asphalt", "turn:lanes": "left|right|right"}}, {"type": "way", "id": 208354269, "nodes": [2186528514, 1329457814, 5188449904, 122429], "tags": {"destination:ref": "B 73", "hazmat:water": "permissive", "highway": "motorway_link", "lanes": "4", "lit": "yes", "maxspeed": "50", "motorroad": "no", "oneway": "yes", "surface": "asphalt", "turn:lanes": "left|left|right|right"}}, {"type": "way", "id": 208354270, "nodes": [1329457858, 1329457840], "tags": {"cycleway:right": "use_sidepath", "destination": "Stade;Cuxhaven", "destination:ref": "B 73", "highway": "primary", "lanes": "2", "lit": "yes", "maxspeed": "50", "name": "Stader Stra\u00dfe", "oneway": "yes", "ref": "B 73", "sidewalk": "right", "surface": "asphalt", "wikidata": "Q106605949"}}, {"type": "way", "id": 208354271, "nodes": [2186528520, 1329457862, 1329457860], "tags": {"cycleway:right": "use_sidepath", "destination:lanes": "Hannover;Bremen;Flensburg;Kiel|Hannover;Bremen;Flensburg;Kiel|Stade;Cuxhaven|Stade;Cuxhaven", "highway": "primary", "lanes": "4", "lit": "yes", "maxspeed": "50", "name": "Stader Stra\u00dfe", "oneway": "yes", "ref": "B 73", "sidewalk": "right", "surface": "asphalt", "turn:lanes": "left|left|through|through", "wikidata": "Q106605949"}}, {"type": "way", "id": 208354272, "nodes": [12217094, 1329457837, 6350951459, 5188449900, 94178394], "tags": {"cycleway:right": "no", "destination": "Elbbr\u00fccken", "destination:ref": "B 73", "highway": "primary", "lanes": "2", "lit": "yes", "maxspeed": "50", "name": "Stader Stra\u00dfe", "oneway": "yes", "ref": "B 73", "shoulder": "no", "sidewalk": "no", "surface": "asphalt", "turn:lanes": "through|through", "wikidata": "Q106605949"}}, {"type": "way", "id": 208354273, "nodes": [2186528517, 1329489270, 1329457840], "tags": {"bicycle:backward": "use_sidepath", "cycleway:right": "track", "highway": "primary", "lanes": "4", "lit": "yes", "maxspeed": "50", "name": "Stader Stra\u00dfe", "ref": "B 73", "sidewalk:left": "separate", "sidewalk:right": "yes", "surface": "asphalt", "wikidata": "Q106605949"}}, {"type": "way", "id": 208354274, "nodes": [2186528519, 6066043986, 1329457845, 6066043987, 1329457864, 1329457866, 1329457868, 1329457887, 5695460633, 700978924], "tags": {"cycleway:right": "track", "highway": "primary", "lanes": "2", "lit": "yes", "maxspeed": "50", "name": "Stader Stra\u00dfe", "oneway": "yes", "ref": "B 73", "sidewalk": "right", "surface": "asphalt", "wikidata": "Q106605949"}}, {"type": "way", "id": 208355765, "nodes": [2186547767, 2186528512, 2186528510, 10377765], "tags": {"destination": "Hannover;Bremen;Flensburg;Kiel", "destination:ref": "A 7", "highway": "motorway_link", "lanes": "3", "lit": "no", "maxspeed": "none", "oneway": "yes", "surface": "asphalt", "turn:lanes": "through|through|slight_right"}}, {"type": "way", "id": 208356736, "nodes": [30694890, 496003, 2186558850, 496004], "tags": {"bdouble": "yes", "hazard": "deer_crossing", "hazmat:water": "permissive", "highway": "motorway", "int_ref": "E 45", "lanes": "3", "lit": "no", "maxspeed": "80", "maxspeed:variable": "signals", "oneway": "yes", "ref": "A 7", "source": "GPS and Videomapping", "surface": "asphalt"}}, {"type": "way", "id": 208356739, "nodes": [2186558867, 2186558871], "tags": {"bdouble": "yes", "destination:lanes": "Flensburg;HH-Waltershof|Flensburg;HH-Waltershof|Flensburg;HH-Waltershof;HH-Hausbruch;Hafen Harburg", "destination:ref:lanes": "A 7|A 7|A 7", "highway": "motorway", "int_ref": "E 45", "lanes": "3", "lit": "no", "maxspeed": "80", "maxspeed:variable": "signals", "oneway": "yes", "ref": "A 7", "source": "GPS and Videomapping", "surface": "asphalt", "turn:lanes": "through|through|through;slight_right"}}, {"type": "way", "id": 208356740, "nodes": [2186558854, 30773702], "tags": {"bdouble": "yes", "destination:lanes": "Flensburg;HH-Waltershof|Flensburg;HH-Waltershof|Flensburg;HH-Waltershof;HH-Hausbruch;Hafen Harburg", "destination:ref:lanes": "A 7|A 7|A 7", "highway": "motorway", "int_ref": "E 45", "lanes": "3", "lit": "no", "maxspeed": "80", "maxspeed:variable": "signals", "oneway": "yes", "ref": "A 7", "source": "GPS and Videomapping", "surface": "asphalt", "turn:lanes": "through|through|through;slight_right"}}, {"type": "way", "id": 208356743, "nodes": [2186558871, 2186558873, 2186558876, 94186701], "tags": {"bdouble": "yes", "destination:lanes": "Flensburg;HH-Waltershof|Flensburg;HH-Waltershof|Flensburg;HH-Waltershof|HH-Hausbruch;Hafen Harburg", "destination:ref:lanes": "A 7|A 7|A 7|", "highway": "motorway", "int_ref": "E 45", "lanes": "4", "lit": "no", "maxspeed": "80", "maxspeed:variable": "signals", "oneway": "yes", "ref": "A 7", "source": "GPS and Videomapping", "surface": "asphalt", "turn:lanes": "none|none|none|slight_right"}}, {"type": "way", "id": 210532014, "nodes": [6066043988, 7187572031, 2206161982, 7187572046, 1329461217], "tags": {"cycleway:right": "use_sidepath", "highway": "primary", "lanes": "3", "lit": "yes", "maxspeed": "50", "name": "Stader Stra\u00dfe", "oneway": "yes", "ref": "B 73", "sidewalk": "right", "surface": "asphalt", "wikidata": "Q106605949"}}, {"type": "way", "id": 219349419, "nodes": [2186528472, 94178363, 2186528481, 2186528488, 94178387, 122427], "tags": {"destination": "Hamburg-Heimfeld;Hamburg-Harburg;Cuxhaven", "destination:ref": "B 73", "highway": "motorway_link", "lanes": "2", "lit": "no", "maxspeed": "60", "oneway": "yes", "source": "GPS and Videomapping", "surface": "asphalt"}}, {"type": "way", "id": 265524732, "nodes": [5186817685, 7045746558, 7045746564, 7045746569, 25984392, 2080670385], "tags": {"bicycle": "use_sidepath", "foot": "use_sidepath", "highway": "primary", "lanes": "4", "lit": "yes", "maxheight": "default", "maxspeed": "50", "name": "Stader Stra\u00dfe", "ref": "B 73", "sidewalk": "separate", "surface": "asphalt", "wikidata": "Q106605949"}}, {"type": "way", "id": 286935418, "nodes": [2186528506, 30473149, 2186528501, 2186528497, 94178380, 2186528490, 6544443798, 6544443797, 6544443796, 6544443795, 6544443794, 6544443793, 6544443792, 6544443791, 6544443790, 6544443789, 6544443788, 6544443787, 6544443786, 6544443785, 6544348084, 6544348083, 6544348082, 6544348081, 6544348080, 6544348079, 6544348078, 6544348077, 6544348076, 6544348075, 6544348073, 6544348072, 6544348074, 2186528472], "tags": {"highway": "motorway_link", "lanes": "2", "lit": "no", "maxheight": "default", "maxspeed": "none", "oneway": "yes", "source": "GPS and Videomapping", "surface": "asphalt"}}, {"type": "way", "id": 534974654, "nodes": [5186817684, 5186816403, 5186817681, 20834531], "tags": {"bicycle": "use_sidepath", "foot": "use_sidepath", "highway": "primary", "lanes": "5", "lanes:forward": "3", "lit": "yes", "maxspeed": "50", "name": "Cuxhavener Stra\u00dfe", "ref": "B 73", "sidewalk": "separate", "surface": "asphalt", "turn:lanes:forward": "left|through|through", "wikidata": "Q106605121"}}, {"type": "way", "id": 534974655, "nodes": [2711745969, 5695460645, 7045563265, 5186817685], "tags": {"bicycle": "use_sidepath", "foot": "use_sidepath", "highway": "primary", "lanes": "4", "lit": "yes", "maxspeed": "50", "name": "Stader Stra\u00dfe", "ref": "B 73", "sidewalk": "separate", "surface": "asphalt", "turn:lanes:backward": "through|through;right", "wikidata": "Q106605949"}}, {"type": "way", "id": 534974656, "nodes": [20834531, 5186817683, 5186817682, 2711745969], "tags": {"bicycle": "use_sidepath", "foot": "use_sidepath", "highway": "primary", "lanes": "4", "lit": "yes", "maxspeed": "50", "name": "Stader Stra\u00dfe", "ref": "B 73", "sidewalk": "separate", "surface": "asphalt", "turn:lanes:backward": "through|through;right", "wikidata": "Q106605949"}}, {"type": "way", "id": 535223127, "nodes": [20834531, 5186816404, 5186816405, 5186816406, 6276935894, 6276935914, 7187572135, 1329489325, 5188452522, 7187572137], "tags": {"cycleway:both": "no", "highway": "unclassified", "lane_markings": "no", "lit": "yes", "maxspeed": "50", "name": "F\u00f6rsterkamp", "oneway": "no", "sidewalk": "both", "smoothness": "good", "surface": "asphalt"}}, {"type": "way", "id": 535223128, "nodes": [5188449899, 2186528519], "tags": {"cycleway:right": "track", "destination": "Elbbr\u00fccken", "destination:ref": "B 73", "highway": "primary", "lanes": "2", "lit": "yes", "maxspeed": "50", "name": "Stader Stra\u00dfe", "oneway": "yes", "ref": "B 73", "sidewalk": "right", "surface": "asphalt", "wikidata": "Q106605949"}}, {"type": "way", "id": 535223129, "nodes": [5188449911, 1329457816, 12217095], "tags": {"destination": "Hannover;Bremen;Flensburg;Kiel", "destination:ref": "A 7", "highway": "motorway_link", "lanes": "2", "lit": "yes", "maxspeed": "50", "motorroad": "no", "oneway": "yes", "surface": "asphalt", "turn:lanes": "right|right"}}, {"type": "way", "id": 589937705, "nodes": [5757290056, 5757290055, 27370300, 27370301, 27370302], "tags": {"highway": "unclassified", "lanes": "2", "lit": "yes", "maxspeed": "30", "maxspeed:type": "DE:zone30", "name": "Am Radeland", "sidewalk": "both", "surface": "asphalt"}}, {"type": "way", "id": 598409912, "nodes": [5695472052, 496007], "tags": {"bdouble": "yes", "hazmat:water": "permissive", "highway": "motorway", "int_ref": "E 45", "lanes": "4", "lit": "no", "maxspeed": "80", "maxspeed:variable": "signals", "oneway": "yes", "ref": "A 7", "source": "GPS and Videomapping", "surface": "asphalt", "turn:lanes": "none|none|none|merge_to_left"}}, {"type": "way", "id": 598409913, "nodes": [5695472060, 26805105], "tags": {"bdouble": "yes", "destination:lanes": "Hannover Bremen;HH-S\u00fcdwest|Hannover Bremen;HH-S\u00fcdwest|Hannover Bremen;HH-S\u00fcdwest|HH-Heimfeld;-Harburg;Cuxhaven", "highway": "motorway", "int_ref": "E 45", "lanes": "4", "lit": "no", "maxspeed": "80", "oneway": "yes", "ref": "A 7", "source": "GPS and Videomapping", "surface": "asphalt", "turn:lanes": "none|none|none|slight_right"}}, {"type": "way", "id": 598409915, "nodes": [26805104, 5695472059], "tags": {"bdouble": "yes", "hazmat:water": "permissive", "highway": "motorway", "int_ref": "E 45", "lanes": "4", "lit": "no", "maxspeed": "80", "maxspeed:variable": "signals", "oneway": "yes", "ref": "A 7", "source": "GPS and Videomapping", "surface": "asphalt", "turn:lanes": "none|none|none|merge_to_left"}}, {"type": "way", "id": 607482337, "nodes": [5757150048, 1705387879, 1705387885, 1705387887, 26400809], "tags": {"highway": "unclassified", "lanes": "2", "lit": "yes", "maxspeed": "30", "maxspeed:type": "DE:zone30", "name": "Am Radeland", "sidewalk": "both", "surface": "asphalt"}}, {"type": "way", "id": 607482342, "nodes": [5757149941, 1329489259, 1329489266, 3740881945, 1329489268, 2186528517], "tags": {"bicycle:backward": "use_sidepath", "cycleway:right": "track", "highway": "primary", "lanes": "4", "lit": "yes", "maxspeed": "50", "name": "Stader Stra\u00dfe", "ref": "B 73", "sidewalk:left": "separate", "sidewalk:right": "yes", "sidewalk:right:surface": "asphalt", "surface": "asphalt", "wikidata": "Q106605949"}}, {"type": "way", "id": 607482397, "nodes": [27370298, 6390453413, 199058420], "tags": {"highway": "unclassified", "maxspeed": "50", "maxspeed:type": "DE:urban", "name": "Am Radeland", "sidewalk": "right", "sidewalk:right:surface": "paving_stones", "surface": "asphalt"}}, {"type": "way", "id": 607482398, "nodes": [199058420, 27370299, 5574735471, 5757290056], "tags": {"highway": "unclassified", "lanes": "2", "lit": "yes", "maxspeed": "50", "maxspeed:type": "DE:urban", "name": "Am Radeland", "sidewalk": "left", "surface": "asphalt"}}, {"type": "way", "id": 607498284, "nodes": [5757289811, 26400784, 5757289812, 2507162089, 1705403284, 5757290021], "tags": {"highway": "unclassified", "name": "Heykenaubrook", "surface": "asphalt"}}, {"type": "way", "id": 607502258, "nodes": [1705403285, 5757290023, 5757290022, 5757290021], "tags": {"highway": "unclassified", "maxspeed": "30", "name": "Am Radeland", "surface": "asphalt"}}, {"type": "way", "id": 607502262, "nodes": [462742924, 309552483, 462742937, 3175147433, 3175147434, 1705403285], "tags": {"highway": "unclassified", "lanes": "2", "lit": "yes", "maxheight": "default", "maxspeed": "30", "maxspeed:type": "DE:zone30", "name": "Am Radeland", "surface": "asphalt"}}, {"type": "way", "id": 645259425, "nodes": [6066043789, 6066043798, 6066043797, 6066043796, 6066043795], "tags": {"cycleway:both": "no", "highway": "unclassified", "lane_markings": "no", "lit": "no", "maxspeed:type": "DE:urban", "name": "Kuhtrift", "operator:type": "private", "surface": "asphalt", "wikidata": "Q106605590"}}, {"type": "way", "id": 645259428, "nodes": [1329461217, 1329461216, 2186528520], "tags": {"cycleway:right": "use_sidepath", "highway": "primary", "lanes": "4", "lit": "yes", "maxspeed": "50", "name": "Stader Stra\u00dfe", "oneway": "yes", "ref": "B 73", "sidewalk": "right", "surface": "asphalt", "turn:lanes": "left|left|through|through", "wikidata": "Q106605949"}}, {"type": "way", "id": 645259429, "nodes": [1329457889, 6066043988], "tags": {"cycleway:right": "use_sidepath", "highway": "primary", "lanes": "2", "lit": "yes", "maxspeed": "50", "name": "Stader Stra\u00dfe", "oneway": "yes", "ref": "B 73", "sidewalk": "right", "smoothness": "good", "surface": "asphalt", "wikidata": "Q106605949"}}, {"type": "way", "id": 645259431, "nodes": [1329457891, 1329457889], "tags": {"cycleway:right": "use_sidepath", "highway": "primary", "lanes": "3", "lit": "yes", "maxspeed": "50", "name": "Stader Stra\u00dfe", "oneway": "yes", "ref": "B 73", "sidewalk": "right", "surface": "asphalt", "turn:lanes": "left|none|none", "wikidata": "Q106605949"}}, {"type": "way", "id": 651193394, "nodes": [199057382, 3740882017], "tags": {"highway": "residential", "lanes": "2", "lit": "yes", "maxspeed": "50", "maxspeed:type": "DE:urban", "name": "Zum F\u00fcrstenmoor", "surface": "asphalt"}}, {"type": "way", "id": 672269221, "nodes": [6295334010, 6295334021, 27370272], "tags": {"cycleway:right": "track", "highway": "unclassified", "lanes": "1", "lit": "yes", "maxspeed:type": "DE:urban", "name": "Mercedesstra\u00dfe", "oneway": "yes", "sidewalk": "right", "surface": "asphalt"}}, {"type": "way", "id": 672269225, "nodes": [27370272, 6295334024, 6295334023, 6295334008], "tags": {"cycleway:right": "track", "highway": "unclassified", "lanes": "2", "lit": "yes", "maxspeed:type": "DE:urban", "name": "Mercedesstra\u00dfe", "oneway": "yes", "sidewalk": "right", "surface": "asphalt", "turn:lanes": "left|right"}}, {"type": "way", "id": 672269227, "nodes": [6295334022, 6295334025, 6295334026, 6295334027], "tags": {"bdouble": "yes", "highway": "secondary", "lanes": "3", "lanes:backward": "2", "lanes:forward": "1", "maxspeed": "60", "name": "F\u00fcrstenmoordamm", "oneway": "no", "overtaking": "no", "surface": "asphalt", "turn:lanes:backward": "left|through"}}, {"type": "way", "id": 672269228, "nodes": [6295334027, 6295334028, 6295334029], "tags": {"bdouble": "yes", "cycleway:both": "no", "highway": "secondary", "lanes": "2", "lanes:backward": "1", "lanes:forward": "1", "maxspeed": "60", "name": "F\u00fcrstenmoordamm", "oneway": "no", "overtaking": "no", "surface": "asphalt"}}, {"type": "way", "id": 672269229, "nodes": [6295334029, 6295334030, 3464812819, 254456000, 1376856125, 13328438, 5292133527, 254456002, 5292133526, 254456005, 254456008], "tags": {"bdouble": "yes", "cycleway:both": "no", "highway": "secondary", "lanes": "2", "lanes:backward": "1", "lanes:forward": "1", "maxspeed": "60", "name": "F\u00fcrstenmoordamm", "oneway": "no", "surface": "asphalt"}}, {"type": "way", "id": 676773598, "nodes": [6337537928, 6337537929, 6337537930], "tags": {"highway": "residential"}}, {"type": "way", "id": 696864655, "nodes": [122427, 6544348071], "tags": {"destination:ref": "B 73", "highway": "motorway_link", "lanes": "3", "lit": "no", "maxspeed": "60", "oneway": "yes", "surface": "asphalt"}}, {"type": "way", "id": 696864656, "nodes": [6544443804, 6544443803, 6544443801, 6544443800, 6544443799, 122427], "tags": {"destination": "HH-Heimfeld;-Harburg;Cuxhaven", "destination:ref": "B 73", "highway": "motorway_link", "lanes": "1", "lit": "no", "maxspeed": "60", "oneway": "yes", "surface": "asphalt"}}, {"type": "way", "id": 696864657, "nodes": [6544443809, 6544443808, 6544443807, 6544443806, 6544443805, 6544443804], "tags": {"destination": "HH-Heimfeld;-Harburg;Cuxhaven", "destination:ref": "B 73", "highway": "motorway_link", "lanes": "2", "lit": "no", "maxspeed": "60", "oneway": "yes", "surface": "asphalt", "turn:lanes": "merge_to_right|merge_to_left"}}, {"type": "way", "id": 696864658, "nodes": [6544443812, 6544443811, 6544443810, 6544443802, 6544443809], "tags": {"destination": "HH-Heimfeld;-Harburg;Cuxhaven", "destination:ref": "B 73", "highway": "motorway_link", "lanes": "2", "lit": "no", "maxspeed": "120", "oneway": "yes", "surface": "asphalt"}}, {"type": "way", "id": 696864659, "nodes": [2186528475, 10377758, 2186528470, 94178403, 2186528466, 2186528463], "tags": {"destination": "Hannover;Bremen", "destination:ref": "A 7", "highway": "motorway_link", "lanes": "2", "lit": "no", "maxheight": "default", "maxspeed": "none", "oneway": "yes", "surface": "asphalt", "turn:lanes": "merge_to_right|merge_to_left"}}, {"type": "way", "id": 784893330, "nodes": [7333015960, 5757290071, 27370298], "tags": {"highway": "residential", "lanes": "2", "lit": "yes", "maxspeed": "50", "maxspeed:type": "DE:urban", "name": "Zum F\u00fcrstenmoor", "surface": "asphalt"}}, {"type": "way", "id": 784898789, "nodes": [27370284, 7333044942, 3740886639, 5916502322, 7333044941, 5757290060, 27370299], "tags": {"highway": "residential", "lanes": "1", "lit": "yes", "maxspeed": "50", "maxspeed:type": "DE:urban", "name": "Tempowerkring", "narrow": "yes", "sidewalk": "both", "smoothness": "excellent", "surface": "asphalt"}}, {"type": "way", "id": 787151350, "nodes": [7358990328, 7358990331, 7358990330, 7358990329, 27370275], "tags": {"cycleway:left": "opposite_track", "cycleway:right": "lane", "highway": "unclassified", "lanes": "2", "lit": "yes", "maxspeed:type": "DE:urban", "name": "Mercedesstra\u00dfe", "oneway": "no", "sidewalk": "both", "surface": "asphalt"}}, {"type": "way", "id": 1011037634, "nodes": [9327811333, 9327811332, 9327811331, 5695472053], "tags": {"highway": "motorway", "int_ref": "E 45", "lanes": "3", "lit": "no", "maxspeed": "80", "oneway": "yes", "ref": "A 7", "surface": "asphalt"}}, {"type": "way", "id": 1011037635, "nodes": [9327811334, 9327811333], "tags": {"bridge": "yes", "highway": "motorway", "int_ref": "E 45", "lanes": "3", "layer": "1", "lit": "no", "maxspeed": "80", "oneway": "yes", "ref": "A 7", "surface": "asphalt"}}, {"type": "way", "id": 1011037636, "nodes": [9327811342, 9327811340, 1705389035, 9327811339, 9327811338, 9327811335, 9327811337, 9327811336, 9327811334], "tags": {"destination": "Hannover;Bremen;HH-Heimfeld", "destination:ref": "A 7", "highway": "motorway", "int_ref": "E 45", "lanes": "3", "lit": "no", "maxspeed": "80", "oneway": "yes", "ref": "A 7", "surface": "asphalt"}}, {"type": "way", "id": 1086435471, "nodes": [2186528454, 491183, 9954813870], "tags": {"bdouble": "yes", "highway": "motorway", "int_ref": "E 45", "lanes": "3", "lit": "no", "maxheight": "default", "maxspeed": "80", "oneway": "yes", "ref": "A 7", "source": "GPS and Videomapping", "surface": "asphalt"}}]}