{"version": 0.6, "generator": "Overpass API 0.7.59.2 0994154d", "osm3s": {"timestamp_osm_base": "2023-03-12T20:08:39Z", "copyright": "The data included in this document is from www.openstreetmap.org. The data is made available under ODbL."}, "elements": [{"type": "node", "id": 2006484, "lat": 47.820211, "lon": 12.3772171}, {"type": "node", "id": 2006504, "lat": 47.8217393, "lon": 12.3796078}, {"type": "node", "id": 2006514, "lat": 47.8233832, "lon": 12.3813604}, {"type": "node", "id": 2006536, "lat": 47.8300971, "lon": 12.3862069}, {"type": "node", "id": 2006546, "lat": 47.8309678, "lon": 12.3870534}, {"type": "node", "id": 2006555, "lat": 47.8323947, "lon": 12.3891059}, {"type": "node", "id": 2006564, "lat": 47.8335043, "lon": 12.3917675}, {"type": "node", "id": 2006568, "lat": 47.8341755, "lon": 12.3955319}, {"type": "node", "id": 17291436, "lat": 47.8201643, "lon": 12.3773518}, {"type": "node", "id": 17291437, "lat": 47.8216631, "lon": 12.3797175}, {"type": "node", "id": 17291438, "lat": 47.8233193, "lon": 12.381507}, {"type": "node", "id": 17291442, "lat": 47.8282402, "lon": 12.3851039}, {"type": "node", "id": 17291443, "lat": 47.8292021, "lon": 12.3857288}, {"type": "node", "id": 17291445, "lat": 47.830932, "lon": 12.387219}, {"type": "node", "id": 17291446, "lat": 47.8323119, "lon": 12.3892184}, {"type": "node", "id": 17291447, "lat": 47.833403, "lon": 12.3918457}, {"type": "node", "id": 17291449, "lat": 47.8340631, "lon": 12.3955427}, {"type": "node", "id": 17291570, "lat": 47.8339148, "lon": 12.3934569}, {"type": "node", "id": 17291572, "lat": 47.8338067, "lon": 12.3934984}, {"type": "node", "id": 17291573, "lat": 47.8340856, "lon": 12.3945672}, {"type": "node", "id": 17291574, "lat": 47.8339745, "lon": 12.3946022}, {"type": "node", "id": 17291575, "lat": 47.8337816, "lon": 12.3928211}, {"type": "node", "id": 17291576, "lat": 47.8336736, "lon": 12.3928708}, {"type": "node", "id": 17291578, "lat": 47.8331589, "lon": 12.3907532}, {"type": "node", "id": 17291580, "lat": 47.8330654, "lon": 12.3908438}, {"type": "node", "id": 17291581, "lat": 47.8314521, "lon": 12.3876376}, {"type": "node", "id": 17291582, "lat": 47.8314024, "lon": 12.3877944}, {"type": "node", "id": 17291583, "lat": 47.8305617, "lon": 12.3866237}, {"type": "node", "id": 17291585, "lat": 47.8305156, "lon": 12.386785}, {"type": "node", "id": 17291586, "lat": 47.8248001, "lon": 12.3828067}, {"type": "node", "id": 17291588, "lat": 47.8247391, "lon": 12.3825492}, {"type": "node", "id": 17291590, "lat": 47.8225755, "lon": 12.3807569}, {"type": "node", "id": 17291591, "lat": 47.8226281, "lon": 12.3806032}, {"type": "node", "id": 17291592, "lat": 47.8214132, "lon": 12.3793855}, {"type": "node", "id": 17291593, "lat": 47.8207899, "lon": 12.37825}, {"type": "node", "id": 17291595, "lat": 47.8193579, "lon": 12.3757855}, {"type": "node", "id": 17291597, "lat": 47.8194097, "lon": 12.3757164}, {"type": "node", "id": 60643407, "lat": 47.82639, "lon": 12.3858935}, {"type": "node", "id": 60643411, "lat": 47.8263532, "lon": 12.3863182}, {"type": "node", "id": 60643413, "lat": 47.8265674, "lon": 12.3862101}, {"type": "node", "id": 60643415, "lat": 47.8265556, "lon": 12.3859906}, {"type": "node", "id": 60643417, "lat": 47.8266936, "lon": 12.3844483}, {"type": "node", "id": 60643418, "lat": 47.826971, "lon": 12.3834852}, {"type": "node", "id": 60643420, "lat": 47.827268, "lon": 12.3832313}, {"type": "node", "id": 60643422, "lat": 47.8275585, "lon": 12.3833047}, {"type": "node", "id": 60643424, "lat": 47.8282934, "lon": 12.383796}, {"type": "node", "id": 60643428, "lat": 47.8290659, "lon": 12.3835144}, {"type": "node", "id": 60643430, "lat": 47.8293358, "lon": 12.383639}, {"type": "node", "id": 60643432, "lat": 47.8295894, "lon": 12.3838898, "tags": {"alt_name": "Schifffahrt Bernau Felden", "bus": "yes", "highway": "bus_stop", "name": "Felden Abzweigung Dampfersteg", "operator": "Regionalverkehr Oberbayern GmbH", "public_transport": "stop_position", "route_ref": "9502;9586", "website": "https://www.rovg.de/php/linienbetreiber.php"}}, {"type": "node", "id": 60643434, "lat": 47.8296896, "lon": 12.38422}, {"type": "node", "id": 60643439, "lat": 47.8302992, "lon": 12.3858221}, {"type": "node", "id": 60643441, "lat": 47.8304281, "lon": 12.3860254}, {"type": "node", "id": 60643443, "lat": 47.8306523, "lon": 12.3862009}, {"type": "node", "id": 60643445, "lat": 47.8309419, "lon": 12.3863635}, {"type": "node", "id": 60643447, "lat": 47.8312599, "lon": 12.3866525}, {"type": "node", "id": 60643449, "lat": 47.8314626, "lon": 12.3866044}, {"type": "node", "id": 60643454, "lat": 47.8260684, "lon": 12.3865306}, {"type": "node", "id": 60643456, "lat": 47.8259281, "lon": 12.3869668}, {"type": "node", "id": 60643458, "lat": 47.8257396, "lon": 12.3874251}, {"type": "node", "id": 60643460, "lat": 47.8254967, "lon": 12.3877845}, {"type": "node", "id": 60643462, "lat": 47.8251294, "lon": 12.3881111}, {"type": "node", "id": 60643466, "lat": 47.8202821, "lon": 12.3906543}, {"type": "node", "id": 60902774, "lat": 47.8193512, "lon": 12.3858792}, {"type": "node", "id": 60902779, "lat": 47.8187705, "lon": 12.3801516}, {"type": "node", "id": 60902780, "lat": 47.82129, "lon": 12.3820617}, {"type": "node", "id": 60902781, "lat": 47.8234512, "lon": 12.3836847}, {"type": "node", "id": 60902782, "lat": 47.8209027, "lon": 12.3902925}, {"type": "node", "id": 60902783, "lat": 47.821951, "lon": 12.3897514}, {"type": "node", "id": 60902787, "lat": 47.8238163, "lon": 12.388798}, {"type": "node", "id": 60902788, "lat": 47.8244746, "lon": 12.3884635}, {"type": "node", "id": 60902790, "lat": 47.8254239, "lon": 12.3852963}, {"type": "node", "id": 60902792, "lat": 47.8188896, "lon": 12.3806809}, {"type": "node", "id": 60902794, "lat": 47.8192571, "lon": 12.3809481}, {"type": "node", "id": 60902796, "lat": 47.8194655, "lon": 12.3818792}, {"type": "node", "id": 60902801, "lat": 47.8196537, "lon": 12.3827861}, {"type": "node", "id": 60902803, "lat": 47.8205999, "lon": 12.3834173}, {"type": "node", "id": 60902806, "lat": 47.8215996, "lon": 12.3829643}, {"type": "node", "id": 60902808, "lat": 47.8223555, "lon": 12.383479}, {"type": "node", "id": 60902812, "lat": 47.8225665, "lon": 12.3842596}, {"type": "node", "id": 60902813, "lat": 47.8221027, "lon": 12.3845268}, {"type": "node", "id": 60902814, "lat": 47.8214693, "lon": 12.3848514}, {"type": "node", "id": 60902815, "lat": 47.8208355, "lon": 12.3851503}, {"type": "node", "id": 60902816, "lat": 47.820747, "lon": 12.3852025}, {"type": "node", "id": 60902817, "lat": 47.8199527, "lon": 12.3855869}, {"type": "node", "id": 60902820, "lat": 47.822715, "lon": 12.3841762}, {"type": "node", "id": 60902821, "lat": 47.8231566, "lon": 12.3839356}, {"type": "node", "id": 60902822, "lat": 47.8237625, "lon": 12.3846145}, {"type": "node", "id": 60902823, "lat": 47.8244317, "lon": 12.3850543}, {"type": "node", "id": 60902824, "lat": 47.824656, "lon": 12.3858809}, {"type": "node", "id": 60902826, "lat": 47.8239636, "lon": 12.3861994}, {"type": "node", "id": 60902844, "lat": 47.8232683, "lon": 12.3864504}, {"type": "node", "id": 60902845, "lat": 47.8225638, "lon": 12.3868129}, {"type": "node", "id": 60902848, "lat": 47.8219305, "lon": 12.3871667}, {"type": "node", "id": 60902850, "lat": 47.8214763, "lon": 12.3874261}, {"type": "node", "id": 60902852, "lat": 47.8212239, "lon": 12.3875703}, {"type": "node", "id": 60902854, "lat": 47.8204422, "lon": 12.388015}, {"type": "node", "id": 60902856, "lat": 47.8206001, "lon": 12.3825437, "tags": {"created_by": "JOSM"}}, {"type": "node", "id": 60902858, "lat": 47.8212158, "lon": 12.3822279}, {"type": "node", "id": 60902860, "lat": 47.8224759, "lon": 12.3836511}, {"type": "node", "id": 60905675, "lat": 47.8266333, "lon": 12.3840555, "tags": {"TMC:cid_58:tabcd_1:Class": "Point", "TMC:cid_58:tabcd_1:Direction": "positive", "TMC:cid_58:tabcd_1:LCLversion": "8.00", "TMC:cid_58:tabcd_1:LocationCode": "12589", "TMC:cid_58:tabcd_1:NextLocationCode": "12590", "TMC:cid_58:tabcd_1:PrevLocationCode": "12588", "highway": "motorway_junction", "name": "Felden", "ref": "107"}}, {"type": "node", "id": 60905676, "lat": 47.8271996, "lon": 12.3842367}, {"type": "node", "id": 60905677, "lat": 47.8271549, "lon": 12.3847009}, {"type": "node", "id": 60905678, "lat": 47.8271885, "lon": 12.3851755}, {"type": "node", "id": 60905681, "lat": 47.827383, "lon": 12.3851408}, {"type": "node", "id": 60905682, "lat": 47.8276139, "lon": 12.384966}, {"type": "node", "id": 60905683, "lat": 47.8279748, "lon": 12.3845609}, {"type": "node", "id": 60905685, "lat": 47.8278497, "lon": 12.3838561}, {"type": "node", "id": 60905686, "lat": 47.827785, "lon": 12.3840857}, {"type": "node", "id": 60905687, "lat": 47.827551, "lon": 12.3843018}, {"type": "node", "id": 60905688, "lat": 47.8280031, "lon": 12.3836414}, {"type": "node", "id": 60905689, "lat": 47.8266702, "lon": 12.3859349}, {"type": "node", "id": 60909356, "lat": 47.8279326, "lon": 12.3835944}, {"type": "node", "id": 60909359, "lat": 47.8270841, "lon": 12.3854931}, {"type": "node", "id": 75175362, "lat": 47.8216259, "lon": 12.3822933}, {"type": "node", "id": 75175366, "lat": 47.8213975, "lon": 12.3821411}, {"type": "node", "id": 75175370, "lat": 47.8216455, "lon": 12.3823073}, {"type": "node", "id": 75316582, "lat": 47.8265799, "lon": 12.386141}, {"type": "node", "id": 75316585, "lat": 47.8264776, "lon": 12.3858997}, {"type": "node", "id": 75316586, "lat": 47.826276, "lon": 12.3861642}, {"type": "node", "id": 75316587, "lat": 47.826385, "lon": 12.3863374}, {"type": "node", "id": 75634351, "lat": 47.8262802, "lon": 12.386045}, {"type": "node", "id": 75925236, "lat": 47.8234102, "lon": 12.3843351}, {"type": "node", "id": 75925239, "lat": 47.8237725, "lon": 12.3853126}, {"type": "node", "id": 181658876, "lat": 47.8239637, "lon": 12.381894}, {"type": "node", "id": 181658882, "lat": 47.8239001, "lon": 12.3820276}, {"type": "node", "id": 266509639, "lat": 47.8207308, "lon": 12.3842775}, {"type": "node", "id": 268123239, "lat": 47.8243181, "lon": 12.3823999}, {"type": "node", "id": 268141932, "lat": 47.828172, "lon": 12.3848787, "tags": {"TMC:cid_58:tabcd_1:Class": "Point", "TMC:cid_58:tabcd_1:Direction": "negative", "TMC:cid_58:tabcd_1:LCLversion": "8.00", "TMC:cid_58:tabcd_1:LocationCode": "12589", "TMC:cid_58:tabcd_1:NextLocationCode": "12590", "TMC:cid_58:tabcd_1:PrevLocationCode": "12588", "highway": "motorway_junction", "name": "Felden", "ref": "107"}}, {"type": "node", "id": 268511739, "lat": 47.8207271, "lon": 12.3816234}, {"type": "node", "id": 268512807, "lat": 47.8225091, "lon": 12.3868433}, {"type": "node", "id": 268512808, "lat": 47.8228008, "lon": 12.3880071, "tags": {"noexit": "yes"}}, {"type": "node", "id": 268512810, "lat": 47.8219925, "lon": 12.3871315}, {"type": "node", "id": 268512812, "lat": 47.8222752, "lon": 12.3884146}, {"type": "node", "id": 268512813, "lat": 47.8210478, "lon": 12.3876708}, {"type": "node", "id": 268512815, "lat": 47.8212775, "lon": 12.3888067}, {"type": "node", "id": 268512816, "lat": 47.8217012, "lon": 12.3885761}, {"type": "node", "id": 277646059, "lat": 47.8223619, "lon": 12.3803085}, {"type": "node", "id": 277646060, "lat": 47.8223052, "lon": 12.3804668}, {"type": "node", "id": 292229945, "lat": 47.8302448, "lon": 12.3856474}, {"type": "node", "id": 292229948, "lat": 47.8300787, "lon": 12.3852202}, {"type": "node", "id": 292229950, "lat": 47.8301728, "lon": 12.3854234}, {"type": "node", "id": 359723779, "lat": 47.83281, "lon": 12.3899306}, {"type": "node", "id": 359723780, "lat": 47.8327107, "lon": 12.3900118}, {"type": "node", "id": 359723781, "lat": 47.8319317, "lon": 12.3883262}, {"type": "node", "id": 359723782, "lat": 47.8318657, "lon": 12.3884477}, {"type": "node", "id": 359723783, "lat": 47.8300041, "lon": 12.3863159}, {"type": "node", "id": 359723784, "lat": 47.8292543, "lon": 12.3855801}, {"type": "node", "id": 370894556, "lat": 47.8292428, "lon": 12.3835352, "tags": {"highway": "mini_roundabout", "junction": "roundabout"}}, {"type": "node", "id": 370894557, "lat": 47.8297956, "lon": 12.3845917}, {"type": "node", "id": 373724078, "lat": 47.8327038, "lon": 12.3913356}, {"type": "node", "id": 373724083, "lat": 47.8318508, "lon": 12.3896628}, {"type": "node", "id": 373724087, "lat": 47.8324396, "lon": 12.3888796}, {"type": "node", "id": 457321167, "lat": 47.8264532, "lon": 12.3852698}, {"type": "node", "id": 457323844, "lat": 47.8271091, "lon": 12.3832952}, {"type": "node", "id": 457323845, "lat": 47.8274264, "lon": 12.3832314}, {"type": "node", "id": 457323846, "lat": 47.826403, "lon": 12.3856695}, {"type": "node", "id": 457323847, "lat": 47.8263475, "lon": 12.3859195}, {"type": "node", "id": 457323848, "lat": 47.8264532, "lon": 12.3863426}, {"type": "node", "id": 457323849, "lat": 47.8318329, "lon": 12.3862416}, {"type": "node", "id": 462190331, "lat": 47.8237741, "lon": 12.3839429, "tags": {"bus": "yes", "name": "Bernau Chiemseestr/ Abzw.Kampenwand", "operator": "Regionalverkehr Oberbayern GmbH", "public_transport": "stop_position", "ref:IFOPT": "de:09187:43716:0:2", "route_ref": "9502", "website": "https://www.rovg.de/php/linienbetreiber.php"}}, {"type": "node", "id": 527665341, "lat": 47.8317945, "lon": 12.3895266}, {"type": "node", "id": 527665343, "lat": 47.8316217, "lon": 12.3889261}, {"type": "node", "id": 527665345, "lat": 47.831425, "lon": 12.3884504}, {"type": "node", "id": 527665347, "lat": 47.8309449, "lon": 12.387792}, {"type": "node", "id": 527665348, "lat": 47.8302279, "lon": 12.3870172}, {"type": "node", "id": 527665351, "lat": 47.8294201, "lon": 12.3863744}, {"type": "node", "id": 527665353, "lat": 47.8280181, "lon": 12.3854545}, {"type": "node", "id": 527665355, "lat": 47.8278352, "lon": 12.3854018}, {"type": "node", "id": 527665356, "lat": 47.8274758, "lon": 12.385531}, {"type": "node", "id": 527665358, "lat": 47.8273522, "lon": 12.3856833}, {"type": "node", "id": 527665361, "lat": 47.8272397, "lon": 12.3858967}, {"type": "node", "id": 527665363, "lat": 47.8271099, "lon": 12.3862982}, {"type": "node", "id": 527665364, "lat": 47.8269853, "lon": 12.3865072}, {"type": "node", "id": 527665366, "lat": 47.8268407, "lon": 12.3865514}, {"type": "node", "id": 527665367, "lat": 47.8267245, "lon": 12.3864696}, {"type": "node", "id": 529783534, "lat": 47.8321602, "lon": 12.3892316, "tags": {"name": "Felden", "traffic_sign": "city_limit"}}, {"type": "node", "id": 699767043, "lat": 47.8262727, "lon": 12.3861243}, {"type": "node", "id": 699767044, "lat": 47.8265755, "lon": 12.3861763}, {"type": "node", "id": 701179467, "lat": 47.8194172, "lon": 12.3813211}, {"type": "node", "id": 701179503, "lat": 47.8195626, "lon": 12.3826625}, {"type": "node", "id": 701179505, "lat": 47.8198045, "lon": 12.3827691}, {"type": "node", "id": 701179511, "lat": 47.8204472, "lon": 12.3825993}, {"type": "node", "id": 701179512, "lat": 47.8205207, "lon": 12.3829692}, {"type": "node", "id": 701182854, "lat": 47.8255749, "lon": 12.3876917}, {"type": "node", "id": 701182855, "lat": 47.8259466, "lon": 12.3878872}, {"type": "node", "id": 701182856, "lat": 47.8263217, "lon": 12.3879987}, {"type": "node", "id": 701182860, "lat": 47.8278279, "lon": 12.3879684}, {"type": "node", "id": 703860202, "lat": 47.8270736, "lon": 12.3879893}, {"type": "node", "id": 703860211, "lat": 47.8271978, "lon": 12.3879851}, {"type": "node", "id": 703860213, "lat": 47.8285814, "lon": 12.3879509}, {"type": "node", "id": 703860214, "lat": 47.8286618, "lon": 12.3880206}, {"type": "node", "id": 703860215, "lat": 47.8286949, "lon": 12.3881217}, {"type": "node", "id": 703860217, "lat": 47.8287869, "lon": 12.389051}, {"type": "node", "id": 703860218, "lat": 47.8288325, "lon": 12.3893933}, {"type": "node", "id": 703860219, "lat": 47.8289857, "lon": 12.390213}, {"type": "node", "id": 703860220, "lat": 47.8291587, "lon": 12.3908253}, {"type": "node", "id": 703860237, "lat": 47.832747, "lon": 12.3941211}, {"type": "node", "id": 703899812, "lat": 47.8284337, "lon": 12.3837961, "tags": {"traffic_sign": "city_limit"}}, {"type": "node", "id": 703899853, "lat": 47.8294556, "lon": 12.3837496}, {"type": "node", "id": 703899876, "lat": 47.8329174, "lon": 12.388345}, {"type": "node", "id": 703899886, "lat": 47.8323135, "lon": 12.3905017}, {"type": "node", "id": 703899888, "lat": 47.8319308, "lon": 12.3898694}, {"type": "node", "id": 703899890, "lat": 47.8329259, "lon": 12.3921192}, {"type": "node", "id": 703899892, "lat": 47.832548, "lon": 12.3909252}, {"type": "node", "id": 703899895, "lat": 47.8329981, "lon": 12.3925533}, {"type": "node", "id": 703942955, "lat": 47.8257386, "lon": 12.3855668}, {"type": "node", "id": 704332123, "lat": 47.8222017, "lon": 12.3896229}, {"type": "node", "id": 704363794, "lat": 47.8316957, "lon": 12.3891876}, {"type": "node", "id": 708032265, "lat": 47.8194313, "lon": 12.3816166}, {"type": "node", "id": 708032415, "lat": 47.8194502, "lon": 12.3817539}, {"type": "node", "id": 708032433, "lat": 47.8188529, "lon": 12.3805494}, {"type": "node", "id": 882608229, "lat": 47.8233019, "lon": 12.3838612}, {"type": "node", "id": 1203034333, "lat": 47.8265412, "lon": 12.3859627}, {"type": "node", "id": 1376213747, "lat": 47.8208602, "lon": 12.3903169}, {"type": "node", "id": 1376213749, "lat": 47.8210989, "lon": 12.390194}, {"type": "node", "id": 1579617810, "lat": 47.8329837, "lon": 12.3930361}, {"type": "node", "id": 1731998828, "lat": 47.8320747, "lon": 12.3866529}, {"type": "node", "id": 1731998831, "lat": 47.8322406, "lon": 12.3869366}, {"type": "node", "id": 1731998832, "lat": 47.8325505, "lon": 12.3875041}, {"type": "node", "id": 1731998833, "lat": 47.8327251, "lon": 12.3878882}, {"type": "node", "id": 1772010541, "lat": 47.8226291, "lon": 12.3873234}, {"type": "node", "id": 1772010542, "lat": 47.8227702, "lon": 12.3879064}, {"type": "node", "id": 1772010547, "lat": 47.8233065, "lon": 12.3866111}, {"type": "node", "id": 1772010549, "lat": 47.8233911, "lon": 12.386976}, {"type": "node", "id": 1772010550, "lat": 47.8234629, "lon": 12.3872815}, {"type": "node", "id": 1772010565, "lat": 47.8235793, "lon": 12.3877912}, {"type": "node", "id": 1772010571, "lat": 47.8236405, "lon": 12.3880418}, {"type": "node", "id": 1772010575, "lat": 47.8241487, "lon": 12.3870431}, {"type": "node", "id": 1772010577, "lat": 47.8242204, "lon": 12.3873494}, {"type": "node", "id": 1772010579, "lat": 47.8243089, "lon": 12.3877374}, {"type": "node", "id": 1772010581, "lat": 47.8243765, "lon": 12.3880408}, {"type": "node", "id": 1772010588, "lat": 47.8245824, "lon": 12.3858796}, {"type": "node", "id": 1772010589, "lat": 47.824736, "lon": 12.3862238}, {"type": "node", "id": 1772010605, "lat": 47.8251188, "lon": 12.3856723}, {"type": "node", "id": 1772010624, "lat": 47.8258288, "lon": 12.3872293, "tags": {"traffic_sign": "city_limit"}}, {"type": "node", "id": 1772741062, "lat": 47.8190258, "lon": 12.3808161}, {"type": "node", "id": 1772756555, "lat": 47.8206287, "lon": 12.390452}, {"type": "node", "id": 1772756570, "lat": 47.821484, "lon": 12.3899957}, {"type": "node", "id": 1772756582, "lat": 47.8224692, "lon": 12.3894778}, {"type": "node", "id": 1772756585, "lat": 47.8230857, "lon": 12.3891638}, {"type": "node", "id": 1772756587, "lat": 47.8234209, "lon": 12.3889955}, {"type": "node", "id": 1772972086, "lat": 47.8276006, "lon": 12.3879765}, {"type": "node", "id": 1772972442, "lat": 47.8319986, "lon": 12.3899814}, {"type": "node", "id": 1772972454, "lat": 47.8321917, "lon": 12.3903005}, {"type": "node", "id": 2066000616, "lat": 47.8253382, "lon": 12.3854683}, {"type": "node", "id": 2342045886, "lat": 47.8270977, "lon": 12.3845711}, {"type": "node", "id": 2342045887, "lat": 47.8271578, "lon": 12.3853081}, {"type": "node", "id": 2342045888, "lat": 47.8271901, "lon": 12.3848581}, {"type": "node", "id": 2342045889, "lat": 47.8275255, "lon": 12.3850038}, {"type": "node", "id": 2342045890, "lat": 47.8276723, "lon": 12.384248}, {"type": "node", "id": 2342045891, "lat": 47.8278128, "lon": 12.383995}, {"type": "node", "id": 2342045892, "lat": 47.8278961, "lon": 12.3841663}, {"type": "node", "id": 2342045893, "lat": 47.8279071, "lon": 12.3843153}, {"type": "node", "id": 2450744055, "lat": 47.8317064, "lon": 12.3863334}, {"type": "node", "id": 2569545319, "lat": 47.8276874, "lon": 12.3854059}, {"type": "node", "id": 2829133318, "lat": 47.8321834, "lon": 12.3889864}, {"type": "node", "id": 2829133319, "lat": 47.832274, "lon": 12.388884}, {"type": "node", "id": 2922598188, "lat": 47.8254166, "lon": 12.3832505}, {"type": "node", "id": 2922598189, "lat": 47.825632, "lon": 12.3832098, "tags": {"distance": "79.0", "highway": "milestone"}}, {"type": "node", "id": 2922598190, "lat": 47.826769, "lon": 12.3858659}, {"type": "node", "id": 2922598191, "lat": 47.8269054, "lon": 12.3840435}, {"type": "node", "id": 2922598192, "lat": 47.8272008, "lon": 12.3850063}, {"type": "node", "id": 2922598193, "lat": 47.8272107, "lon": 12.3853648}, {"type": "node", "id": 2922598194, "lat": 47.8272817, "lon": 12.3844763}, {"type": "node", "id": 2922598195, "lat": 47.827445, "lon": 12.3850744}, {"type": "node", "id": 2922598196, "lat": 47.827707, "lon": 12.3849522}, {"type": "node", "id": 2922598197, "lat": 47.8279284, "lon": 12.3838851}, {"type": "node", "id": 2922598198, "lat": 47.8279031, "lon": 12.3840311}, {"type": "node", "id": 2922598199, "lat": 47.8279345, "lon": 12.3844454}, {"type": "node", "id": 2922598200, "lat": 47.8294583, "lon": 12.3859047}, {"type": "node", "id": 2922599001, "lat": 47.8295093, "lon": 12.3857539}, {"type": "node", "id": 2922599002, "lat": 47.8324909, "lon": 12.3895554}, {"type": "node", "id": 2922599003, "lat": 47.832584, "lon": 12.3894613}, {"type": "node", "id": 2922599004, "lat": 47.8328921, "lon": 12.3904223, "tags": {"distance": "80.0", "highway": "milestone"}}, {"type": "node", "id": 2922599005, "lat": 47.8329864, "lon": 12.3903232, "tags": {"distance": "80.0", "highway": "milestone"}}, {"type": "node", "id": 2922599006, "lat": 47.833238, "lon": 12.3913206}, {"type": "node", "id": 2922599007, "lat": 47.8333388, "lon": 12.3912364}, {"type": "node", "id": 2922599017, "lat": 47.8335428, "lon": 12.3923411}, {"type": "node", "id": 2922599020, "lat": 47.8336492, "lon": 12.3922767}, {"type": "node", "id": 2922599024, "lat": 47.8339064, "lon": 12.3940798}, {"type": "node", "id": 2922599025, "lat": 47.8340161, "lon": 12.3940352}, {"type": "node", "id": 2922599026, "lat": 47.8340228, "lon": 12.3950574}, {"type": "node", "id": 2922599030, "lat": 47.8341336, "lon": 12.3950359}, {"type": "node", "id": 2924607771, "lat": 47.827736, "lon": 12.3841805}, {"type": "node", "id": 2924616065, "lat": 47.8315392, "lon": 12.3886741}, {"type": "node", "id": 3304796932, "lat": 47.8224122, "lon": 12.3835226}, {"type": "node", "id": 3304796936, "lat": 47.8237679, "lon": 12.3849901}, {"type": "node", "id": 3304796939, "lat": 47.8216439, "lon": 12.382971}, {"type": "node", "id": 3304796942, "lat": 47.8237634, "lon": 12.3847842}, {"type": "node", "id": 3304796944, "lat": 47.821727, "lon": 12.3830002}, {"type": "node", "id": 3304796945, "lat": 47.8215309, "lon": 12.3829636}, {"type": "node", "id": 3333680086, "lat": 47.8264125, "lon": 12.3855317}, {"type": "node", "id": 3333680087, "lat": 47.826662, "lon": 12.3841525}, {"type": "node", "id": 3333680088, "lat": 47.8268998, "lon": 12.3843132}, {"type": "node", "id": 3333680089, "lat": 47.8269714, "lon": 12.3843857}, {"type": "node", "id": 3333680090, "lat": 47.8272913, "lon": 12.3842179}, {"type": "node", "id": 3333680091, "lat": 47.8274259, "lon": 12.3842933}, {"type": "node", "id": 3333680093, "lat": 47.8277652, "lon": 12.3834619}, {"type": "node", "id": 3333680094, "lat": 47.8277954, "lon": 12.3835907}, {"type": "node", "id": 3333680095, "lat": 47.8278231, "lon": 12.3837002}, {"type": "node", "id": 3333680096, "lat": 47.827889, "lon": 12.3849589}, {"type": "node", "id": 3333680097, "lat": 47.8280236, "lon": 12.384646}, {"type": "node", "id": 3333680098, "lat": 47.8280866, "lon": 12.3847342}, {"type": "node", "id": 3333680099, "lat": 47.828101, "lon": 12.3850912}, {"type": "node", "id": 3333680100, "lat": 47.8281045, "lon": 12.3837091}, {"type": "node", "id": 3333680101, "lat": 47.8281982, "lon": 12.3837624}, {"type": "node", "id": 3358307677, "lat": 47.8326896, "lon": 12.3882619}, {"type": "node", "id": 3358307678, "lat": 47.8323873, "lon": 12.3882619}, {"type": "node", "id": 3464794041, "lat": 47.8316596, "lon": 12.386387}, {"type": "node", "id": 3464794042, "lat": 47.8315264, "lon": 12.3865479}, {"type": "node", "id": 3464794043, "lat": 47.8313625, "lon": 12.3866472}, {"type": "node", "id": 4170418796, "lat": 47.8307924, "lon": 12.3876272}, {"type": "node", "id": 4172217010, "lat": 47.826199, "lon": 12.3859472, "tags": {"crossing": "unmarked", "highway": "crossing", "kerb": "flush", "tactile_paving": "no"}}, {"type": "node", "id": 4172227193, "lat": 47.8259454, "lon": 12.3857323}, {"type": "node", "id": 4172227197, "lat": 47.8260702, "lon": 12.3858494}, {"type": "node", "id": 4172227201, "lat": 47.8261572, "lon": 12.3858119}, {"type": "node", "id": 4172227203, "lat": 47.8261793, "lon": 12.3863008}, {"type": "node", "id": 4172227204, "lat": 47.8262266, "lon": 12.3858546, "tags": {"crossing": "unmarked", "highway": "crossing", "kerb": "flush", "tactile_paving": "no"}}, {"type": "node", "id": 4172227205, "lat": 47.8262537, "lon": 12.3858713}, {"type": "node", "id": 4172227206, "lat": 47.826441, "lon": 12.3853435}, {"type": "node", "id": 4172227207, "lat": 47.8264445, "lon": 12.3855109}, {"type": "node", "id": 4172227208, "lat": 47.8264592, "lon": 12.3856386}, {"type": "node", "id": 4172227209, "lat": 47.8264789, "lon": 12.3858074}, {"type": "node", "id": 4172227210, "lat": 47.8264886, "lon": 12.3858713}, {"type": "node", "id": 4172227211, "lat": 47.8265045, "lon": 12.3859183}, {"type": "node", "id": 4172227212, "lat": 47.8264862, "lon": 12.3863282}, {"type": "node", "id": 4172227214, "lat": 47.8265531, "lon": 12.3862477}, {"type": "node", "id": 4172227215, "lat": 47.8265806, "lon": 12.3861051}, {"type": "node", "id": 4172227216, "lat": 47.8265781, "lon": 12.3863953}, {"type": "node", "id": 4172227217, "lat": 47.8266752, "lon": 12.3860384}, {"type": "node", "id": 4172227218, "lat": 47.8266669, "lon": 12.3864699}, {"type": "node", "id": 4172227219, "lat": 47.8267486, "lon": 12.3859869}, {"type": "node", "id": 4172227220, "lat": 47.8267577, "lon": 12.3865202}, {"type": "node", "id": 4172227221, "lat": 47.8268063, "lon": 12.3859181}, {"type": "node", "id": 4172227222, "lat": 47.8268713, "lon": 12.3858291}, {"type": "node", "id": 4172227223, "lat": 47.8269248, "lon": 12.3857167}, {"type": "node", "id": 4172230027, "lat": 47.8253855, "lon": 12.3853758, "tags": {"kerb": "no"}}, {"type": "node", "id": 4172237117, "lat": 47.8263185, "lon": 12.3859529}, {"type": "node", "id": 4172237118, "lat": 47.8264489, "lon": 12.3858892}, {"type": "node", "id": 4172237119, "lat": 47.826524, "lon": 12.3859384}, {"type": "node", "id": 4172237120, "lat": 47.8265733, "lon": 12.3860454}, {"type": "node", "id": 4172240347, "lat": 47.8240429, "lon": 12.3841872}, {"type": "node", "id": 4172240348, "lat": 47.8242652, "lon": 12.3843872}, {"type": "node", "id": 4172240349, "lat": 47.8244959, "lon": 12.3845715}, {"type": "node", "id": 4172604518, "lat": 47.8197994, "lon": 12.3766366}, {"type": "node", "id": 4172604519, "lat": 47.8207439, "lon": 12.3783924}, {"type": "node", "id": 4172604520, "lat": 47.8212023, "lon": 12.3789017}, {"type": "node", "id": 4172647989, "lat": 47.8187905, "lon": 12.3802849}, {"type": "node", "id": 4172647994, "lat": 47.8189065, "lon": 12.3807232}, {"type": "node", "id": 4172647995, "lat": 47.8189333, "lon": 12.3807668}, {"type": "node", "id": 4172650877, "lat": 47.8194175, "lon": 12.381448}, {"type": "node", "id": 4172650878, "lat": 47.8196034, "lon": 12.3827323}, {"type": "node", "id": 4172650879, "lat": 47.8197138, "lon": 12.3827946}, {"type": "node", "id": 4212014465, "lat": 47.8270403, "lon": 12.3833696}, {"type": "node", "id": 4212014466, "lat": 47.8271897, "lon": 12.3832479}, {"type": "node", "id": 4242543278, "lat": 47.8326335, "lon": 12.3911237}, {"type": "node", "id": 4242544500, "lat": 47.832954, "lon": 12.3932212}, {"type": "node", "id": 4242544502, "lat": 47.8329747, "lon": 12.3923696}, {"type": "node", "id": 4242544508, "lat": 47.8330026, "lon": 12.3927612}, {"type": "node", "id": 4292889902, "lat": 47.8204575, "lon": 12.3814096}, {"type": "node", "id": 4292889903, "lat": 47.82098, "lon": 12.3823831}, {"type": "node", "id": 4562343831, "lat": 47.8299232, "lon": 12.3849552}, {"type": "node", "id": 4860998353, "lat": 47.823545, "lon": 12.38445}, {"type": "node", "id": 4860998354, "lat": 47.8233357, "lon": 12.3842616}, {"type": "node", "id": 4860998355, "lat": 47.8232071, "lon": 12.384073}, {"type": "node", "id": 4860998356, "lat": 47.8233543, "lon": 12.3838348}, {"type": "node", "id": 4860998357, "lat": 47.8233889, "lon": 12.3837993}, {"type": "node", "id": 4860998360, "lat": 47.8236423, "lon": 12.3838231, "tags": {"check_date": "2021-05-21", "traffic_calming": "island"}}, {"type": "node", "id": 4860998361, "lat": 47.8265118, "lon": 12.3863078}, {"type": "node", "id": 4860998362, "lat": 47.8265344, "lon": 12.3862807}, {"type": "node", "id": 4860998376, "lat": 47.8264806, "lon": 12.3851545}, {"type": "node", "id": 4860998377, "lat": 47.826423, "lon": 12.3854389}, {"type": "node", "id": 4860998378, "lat": 47.8263991, "lon": 12.3858196}, {"type": "node", "id": 4860998379, "lat": 47.8264193, "lon": 12.3858871}, {"type": "node", "id": 4860998380, "lat": 47.8263681, "lon": 12.3859041}, {"type": "node", "id": 4860998381, "lat": 47.8263164, "lon": 12.3859071}, {"type": "node", "id": 4860998382, "lat": 47.8262524, "lon": 12.3860043}, {"type": "node", "id": 4860998383, "lat": 47.8262605, "lon": 12.3862046}, {"type": "node", "id": 4860998384, "lat": 47.8262338, "lon": 12.3862401}, {"type": "node", "id": 4860998385, "lat": 47.8261476, "lon": 12.3863502}, {"type": "node", "id": 4860998386, "lat": 47.8261051, "lon": 12.3864344}, {"type": "node", "id": 4860998387, "lat": 47.8263211, "lon": 12.3863286}, {"type": "node", "id": 4860998388, "lat": 47.8262914, "lon": 12.3863338}, {"type": "node", "id": 4860998389, "lat": 47.8262442, "lon": 12.3863572}, {"type": "node", "id": 4860998390, "lat": 47.8261948, "lon": 12.3863988}, {"type": "node", "id": 4860998391, "lat": 47.8261412, "lon": 12.3864517}, {"type": "node", "id": 4860998392, "lat": 47.8259764, "lon": 12.3868133}, {"type": "node", "id": 4860998393, "lat": 47.8258891, "lon": 12.3870864}, {"type": "node", "id": 4860998394, "lat": 47.8262957, "lon": 12.3859955}, {"type": "node", "id": 4860998395, "lat": 47.8262741, "lon": 12.3860841}, {"type": "node", "id": 4860998396, "lat": 47.8262863, "lon": 12.3862112}, {"type": "node", "id": 4860998397, "lat": 47.8263032, "lon": 12.3862538}, {"type": "node", "id": 4860998398, "lat": 47.8263259, "lon": 12.38629}, {"type": "node", "id": 4860998399, "lat": 47.8264189, "lon": 12.3863457}, {"type": "node", "id": 4860998400, "lat": 47.8268025, "lon": 12.3865419}, {"type": "node", "id": 4860998401, "lat": 47.82671, "lon": 12.3864959}, {"type": "node", "id": 4860998402, "lat": 47.826597, "lon": 12.3862644}, {"type": "node", "id": 4860998403, "lat": 47.8270191, "lon": 12.3864751}, {"type": "node", "id": 4860998404, "lat": 47.8268858, "lon": 12.3865497}, {"type": "node", "id": 4860998405, "lat": 47.8269318, "lon": 12.3865401}, {"type": "node", "id": 4860998406, "lat": 47.8270406, "lon": 12.3864448}, {"type": "node", "id": 4860998407, "lat": 47.8270709, "lon": 12.3863893}, {"type": "node", "id": 4860998408, "lat": 47.8272916, "lon": 12.385771}, {"type": "node", "id": 4860998409, "lat": 47.8274196, "lon": 12.385588}, {"type": "node", "id": 4860998410, "lat": 47.8275634, "lon": 12.3854632}, {"type": "node", "id": 4860998411, "lat": 47.8276216, "lon": 12.3854311}, {"type": "node", "id": 4860998412, "lat": 47.8277596, "lon": 12.3853973}, {"type": "node", "id": 4860998413, "lat": 47.8279331, "lon": 12.3854172}, {"type": "node", "id": 4860998414, "lat": 47.8281625, "lon": 12.3855308}, {"type": "node", "id": 4860998434, "lat": 47.8256783, "lon": 12.3877785}, {"type": "node", "id": 4860998435, "lat": 47.8256252, "lon": 12.3877428}, {"type": "node", "id": 4860998436, "lat": 47.8252431, "lon": 12.3880269}, {"type": "node", "id": 4860998437, "lat": 47.8251168, "lon": 12.3879223}, {"type": "node", "id": 4860998438, "lat": 47.8251266, "lon": 12.388015}, {"type": "node", "id": 4860998439, "lat": 47.8253225, "lon": 12.387958}, {"type": "node", "id": 4860998440, "lat": 47.8253802, "lon": 12.3879019}, {"type": "node", "id": 4860998456, "lat": 47.8257944, "lon": 12.3873047}, {"type": "node", "id": 4860998464, "lat": 47.825619, "lon": 12.385464, "tags": {"check_date": "2021-05-21", "traffic_calming": "island"}}, {"type": "node", "id": 4860998473, "lat": 47.820486, "lon": 12.3777225}, {"type": "node", "id": 4860998474, "lat": 47.8209944, "lon": 12.3785835}, {"type": "node", "id": 4860998475, "lat": 47.8214696, "lon": 12.3792709}, {"type": "node", "id": 4860998476, "lat": 47.8220146, "lon": 12.379926}, {"type": "node", "id": 4860998477, "lat": 47.8230108, "lon": 12.3810031}, {"type": "node", "id": 4860998478, "lat": 47.8236437, "lon": 12.3816122}, {"type": "node", "id": 4860998479, "lat": 47.8211337, "lon": 12.3789868}, {"type": "node", "id": 4860998480, "lat": 47.8203317, "lon": 12.3776749}, {"type": "node", "id": 4860998481, "lat": 47.8205237, "lon": 12.3780186}, {"type": "node", "id": 4860998488, "lat": 47.8234158, "lon": 12.3837615}, {"type": "node", "id": 4860998495, "lat": 47.8253014, "lon": 12.3855257}, {"type": "node", "id": 4860998496, "lat": 47.8252225, "lon": 12.3855997}, {"type": "node", "id": 4860998497, "lat": 47.8246941, "lon": 12.3858757}, {"type": "node", "id": 4860998498, "lat": 47.824523, "lon": 12.3858981}, {"type": "node", "id": 4860998499, "lat": 47.8244849, "lon": 12.3851771}, {"type": "node", "id": 4860998500, "lat": 47.8244609, "lon": 12.3850886}, {"type": "node", "id": 5133485386, "lat": 47.8242727, "lon": 12.3860329}, {"type": "node", "id": 6342657449, "lat": 47.8262292, "lon": 12.3879888}, {"type": "node", "id": 6342657450, "lat": 47.8261349, "lon": 12.3879661}, {"type": "node", "id": 8453999512, "lat": 47.8237893, "lon": 12.3839567, "tags": {"bus": "yes", "name": "Bernau Chiemseestr/ Abzw.Kampenwand", "public_transport": "stop_position", "ref:IFOPT": "de:09187:43716:0:1"}}, {"type": "node", "id": 8497143024, "lat": 47.8290973, "lon": 12.390608}, {"type": "node", "id": 8497143025, "lat": 47.8291391, "lon": 12.3907559}, {"type": "node", "id": 8591891364, "lat": 47.8255922, "lon": 12.3833667, "tags": {"distance": "79.0", "highway": "milestone"}}, {"type": "node", "id": 8736107449, "lat": 47.8239573, "lon": 12.3861704}, {"type": "node", "id": 8736108122, "lat": 47.8258427, "lon": 12.3871963}, {"type": "node", "id": 9170423601, "lat": 47.827185, "lon": 12.386066}, {"type": "node", "id": 9502337168, "lat": 47.822334, "lon": 12.3828325}, {"type": "node", "id": 9502345995, "lat": 47.8212652, "lon": 12.3821372}, {"type": "node", "id": 9502345996, "lat": 47.8212397, "lon": 12.3821983}, {"type": "node", "id": 9502372753, "lat": 47.8232892, "lon": 12.3842086}, {"type": "node", "id": 9502372754, "lat": 47.8232499, "lon": 12.3841511}, {"type": "node", "id": 10048766930, "lat": 47.8193871, "lon": 12.3811888}, {"type": "node", "id": 10048766931, "lat": 47.819351, "lon": 12.3810821}, {"type": "node", "id": 10048766932, "lat": 47.8193163, "lon": 12.3810164}, {"type": "node", "id": 10048766970, "lat": 47.8194974, "lon": 12.382263}, {"type": "node", "id": 10048766971, "lat": 47.8195423, "lon": 12.3825599}, {"type": "node", "id": 10048767008, "lat": 47.8207514, "lon": 12.3824873}, {"type": "node", "id": 10054628574, "lat": 47.8209178, "lon": 12.3860507}, {"type": "node", "id": 10054628593, "lat": 47.8209659, "lon": 12.3877173}, {"type": "node", "id": 10054628618, "lat": 47.8224538, "lon": 12.3835824}, {"type": "node", "id": 10056702821, "lat": 47.8214656, "lon": 12.3829842}, {"type": "node", "id": 10056702822, "lat": 47.8217866, "lon": 12.3830273}, {"type": "node", "id": 10056702824, "lat": 47.8217517, "lon": 12.3830114}, {"type": "node", "id": 10056702830, "lat": 47.8220353, "lon": 12.3832248}, {"type": "node", "id": 10056702861, "lat": 47.8210774, "lon": 12.3831784}, {"type": "node", "id": 10056702862, "lat": 47.8213928, "lon": 12.3830206}, {"type": "node", "id": 10056702906, "lat": 47.8216388, "lon": 12.3838312}, {"type": "node", "id": 10056702908, "lat": 47.8212006, "lon": 12.3840466}, {"type": "node", "id": 10056702946, "lat": 47.8229532, "lon": 12.3840464}, {"type": "node", "id": 10056702972, "lat": 47.8211825, "lon": 12.3849866}, {"type": "node", "id": 10056719418, "lat": 47.8215905, "lon": 12.3854596}, {"type": "node", "id": 10059401193, "lat": 47.8222599, "lon": 12.3869823}, {"type": "node", "id": 10059401195, "lat": 47.822479, "lon": 12.3863927}, {"type": "node", "id": 10059426715, "lat": 47.8235921, "lon": 12.3878437}, {"type": "node", "id": 10059435431, "lat": 47.8230562, "lon": 12.3855703}, {"type": "node", "id": 10059435455, "lat": 47.8230147, "lon": 12.38658}, {"type": "node", "id": 10059435457, "lat": 47.8229274, "lon": 12.3850441}, {"type": "node", "id": 10059435463, "lat": 47.8230715, "lon": 12.3856326}, {"type": "node", "id": 10059435467, "lat": 47.8231497, "lon": 12.3859523}, {"type": "node", "id": 10059435470, "lat": 47.8232096, "lon": 12.3861967}, {"type": "node", "id": 10059435472, "lat": 47.8232911, "lon": 12.3865421}, {"type": "node", "id": 10059435491, "lat": 47.8236084, "lon": 12.3879103}, {"type": "node", "id": 10059435501, "lat": 47.8240935, "lon": 12.3886572}, {"type": "node", "id": 10059475929, "lat": 47.8233993, "lon": 12.3870111}, {"type": "node", "id": 10059476000, "lat": 47.8222601, "lon": 12.3883271}, {"type": "node", "id": 10061984636, "lat": 47.8214432, "lon": 12.3887308}, {"type": "node", "id": 10061984648, "lat": 47.8217511, "lon": 12.3888107}, {"type": "node", "id": 10061984660, "lat": 47.8218153, "lon": 12.3891131}, {"type": "node", "id": 10061984676, "lat": 47.821186, "lon": 12.3883543}, {"type": "node", "id": 10061998429, "lat": 47.822708, "lon": 12.3893562}, {"type": "node", "id": 10062235830, "lat": 47.8242895, "lon": 12.3876526}, {"type": "node", "id": 10062235870, "lat": 47.8237797, "lon": 12.3846258}, {"type": "node", "id": 10062235872, "lat": 47.8240042, "lon": 12.3847733}, {"type": "node", "id": 10062235888, "lat": 47.8245137, "lon": 12.3852958}, {"type": "node", "id": 10062235900, "lat": 47.8245967, "lon": 12.3856369}, {"type": "node", "id": 10062235902, "lat": 47.8245751, "lon": 12.3855482}, {"type": "node", "id": 10062235908, "lat": 47.824884, "lon": 12.3868841}, {"type": "way", "id": 8094205, "nodes": [1772010624, 8736108122, 4860998393, 60643456, 4860998392, 60643454], "tags": {"access:conditional": "destination @ (weight>7.5)", "hgv": "destination", "highway": "residential", "lanes": "2", "lanes:forward": "1", "maxspeed": "100", "name": "Hochfellnstra\u00dfe", "surface": "asphalt"}}, {"type": "way", "id": 8108286, "nodes": [277646059, 4860998476, 2006504, 4860998475, 4172604520, 4860998474, 17291593, 4860998473, 2006484, 17291597], "tags": {"bdouble": "yes", "cycleway:both": "no", "highway": "motorway", "int_ref": "E 52;E 60", "lanes": "2", "lit": "no", "maxspeed": "100", "oneway": "yes", "ref": "A 8", "source:maxspeed": "sign", "surface": "asphalt", "tmc": "DE:12588/12589"}}, {"type": "way", "id": 8113409, "nodes": [60643417, 60643418], "tags": {"bridge": "yes", "highway": "tertiary", "lanes": "2", "lanes:backward": "1", "layer": "1", "ref": "RO 14", "shoulder": "no", "surface": "asphalt"}}, {"type": "way", "id": 8113410, "nodes": [60643418, 4212014465, 457323844, 4212014466, 60643420, 457323845, 60643422, 3333680093, 60909356], "tags": {"highway": "tertiary", "lanes": "2", "lanes:backward": "1", "ref": "RO 14", "surface": "asphalt"}}, {"type": "way", "id": 8118571, "nodes": [60902779, 4172647989, 708032433, 60902792, 4172647994, 4172647995, 1772741062, 60902794, 10048766932, 10048766931, 10048766930, 701179467, 4172650877, 708032265, 708032415, 60902796, 10048766970, 10048766971, 701179503, 4172650878, 60902801, 4172650879, 701179505, 701179511, 60902856, 10048767008, 4292889903, 60902858, 9502345996, 9502345995, 60902780], "tags": {"highway": "residential", "maxspeed": "50", "name": "Alte Seestra\u00dfe"}}, {"type": "way", "id": 8118573, "nodes": [60902781, 4860998488, 4860998357, 4860998356, 882608229, 60902821, 10056702946, 60902820, 60902812, 60902813, 60902814, 10056702972, 60902815, 60902816, 60902817, 60902774], "tags": {"access:conditional": "destination @ (weight>7.5)", "cycleway:both": "no", "hgv": "destination", "highway": "residential", "lane_markings": "no", "lit": "yes", "maxspeed": "50", "maxweight": "7.5", "name": "Kampenwandstra\u00dfe", "sidewalk": "both", "surface": "asphalt"}}, {"type": "way", "id": 8118574, "nodes": [60902808, 10056702830, 10056702822, 10056702824, 3304796944, 3304796939, 60902806, 3304796945, 10056702821, 10056702862, 10056702861, 60902803], "tags": {"cycleway:both": "no", "highway": "residential", "lane_markings": "no", "lit": "yes", "maxspeed": "50", "name": "Klausenstra\u00dfe", "sidewalk": "none", "surface": "asphalt"}}, {"type": "way", "id": 8118575, "nodes": [60902808, 10056702906, 10056702908, 266509639], "tags": {"cycleway:both": "no", "highway": "residential", "lane_markings": "no", "lit": "yes", "maxspeed": "50", "name": "Rauschbergstra\u00dfe", "sidewalk": "none", "surface": "asphalt"}}, {"type": "way", "id": 8118576, "nodes": [701179512, 60902803, 266509639, 60902815], "tags": {"cycleway:both": "no", "highway": "residential", "lane_markings": "no", "lit": "yes", "maxspeed": "50", "name": "Wendelsteinstra\u00dfe", "sidewalk": "none", "surface": "asphalt"}}, {"type": "way", "id": 8118577, "nodes": [60902821, 4860998355, 9502372754, 9502372753, 4860998354, 75925236, 4860998353, 60902822, 10062235870, 10062235872, 60902823, 4860998500, 4860998499, 10062235888, 10062235902, 10062235900, 60902824, 1772010589, 10062235908, 4860998437, 4860998438, 60643462], "tags": {"highway": "residential", "lit": "yes", "maxspeed": "50", "name": "Scheibenwandstra\u00dfe", "surface": "asphalt"}}, {"type": "way", "id": 8118578, "nodes": [60902822, 3304796942, 3304796936, 75925239, 8736107449, 60902826, 1772010575, 1772010577, 10062235830, 1772010579, 1772010581, 60902788], "tags": {"highway": "residential", "lit": "yes", "maxspeed": "50", "name": "Erlbergstra\u00dfe", "surface": "asphalt"}}, {"type": "way", "id": 8118579, "nodes": [60902820, 10059435457, 10059435431, 10059435463, 10059435467, 10059435470, 60902844, 10059435472, 1772010547, 1772010549, 10059475929, 1772010550, 1772010565, 10059426715, 10059435491, 1772010571, 60902787], "tags": {"cycleway:both": "no", "highway": "residential", "lane_markings": "no", "lit": "yes", "maxspeed": "50", "name": "Zellerhornstra\u00dfe", "sidewalk": "none", "surface": "asphalt"}}, {"type": "way", "id": 8118580, "nodes": [60902813, 10059401195, 60902845], "tags": {"cycleway:both": "no", "highway": "residential", "lane_markings": "no", "lit": "yes", "maxspeed": "50", "name": "Hochplattenstra\u00dfe", "sidewalk": "none", "surface": "asphalt"}}, {"type": "way", "id": 8118581, "nodes": [60902814, 10056719418, 60902848], "tags": {"cycleway:both": "no", "highway": "residential", "lane_markings": "no", "lit": "yes", "maxspeed": "50", "name": "Eibergstra\u00dfe", "sidewalk": "none", "surface": "asphalt"}}, {"type": "way", "id": 8118582, "nodes": [60902816, 10054628574, 60902852], "tags": {"cycleway:both": "no", "highway": "residential", "lane_markings": "no", "lit": "yes", "maxspeed": "50", "name": "Gedererstra\u00dfe", "sidewalk": "none", "surface": "asphalt"}}, {"type": "way", "id": 8118585, "nodes": [60902850, 268512816, 10061984648, 10061984660, 60902783], "tags": {"cycleway:both": "no", "highway": "residential", "lane_markings": "no", "lit": "yes", "maxspeed": "50", "name": "Staffelsteinstra\u00dfe", "sidewalk": "none", "surface": "asphalt"}}, {"type": "way", "id": 8118730, "nodes": [60909356, 60905685], "tags": {"cycleway:both": "no", "destination": "M\u00fcnchen", "destination:ref": "A 8", "highway": "motorway_link", "lanes": "1", "lit": "no", "oneway": "yes", "surface": "asphalt"}}, {"type": "way", "id": 8118732, "nodes": [60902844, 10059435455, 60902845, 268512807, 10059401193, 268512810, 60902848, 60902850, 60902852, 268512813, 10054628593, 60902854], "tags": {"cycleway:both": "no", "highway": "residential", "lane_markings": "no", "lit": "yes", "maxspeed": "50", "name": "Hochgernstra\u00dfe", "sidewalk": "none", "surface": "asphalt"}}, {"type": "way", "id": 8118733, "nodes": [60902826, 5133485386, 4860998498, 1772010588, 60902824, 4860998497, 1772010605, 4860998496, 4860998495, 2066000616, 4172230027, 60902790], "tags": {"highway": "residential", "lit": "yes", "maxspeed": "50", "name": "Draxlbergstra\u00dfe", "surface": "asphalt"}}, {"type": "way", "id": 9630419, "nodes": [75175366, 75175362], "tags": {"bridge": "yes", "cycleway:both": "track", "cycleway:both:segregated": "no", "highway": "tertiary", "lanes": "2", "layer": "1", "maxspeed": "50", "name": "Chiemseestra\u00dfe", "ref": "RO 14", "sidewalk": "both", "surface": "asphalt"}}, {"type": "way", "id": 9657335, "nodes": [4172227206, 4860998377, 3333680086, 457323846, 4860998378, 60643407], "tags": {"cycleway:right": "no", "highway": "tertiary", "lanes": "1", "oneway": "yes", "ref": "RO 14", "surface": "asphalt"}}, {"type": "way", "id": 9657336, "nodes": [75175362, 75175370], "tags": {"highway": "tertiary", "lanes": "2", "maxspeed": "50", "name": "Chiemseestra\u00dfe", "ref": "RO 14", "surface": "asphalt"}}, {"type": "way", "id": 24704096, "nodes": [268512807, 1772010541, 1772010542, 268512808], "tags": {"cycleway:both": "no", "highway": "residential", "lane_markings": "no", "lit": "no", "maxspeed": "50", "name": "Schwarzbergstra\u00dfe", "sidewalk": "none", "surface": "asphalt"}}, {"type": "way", "id": 24704097, "nodes": [268512810, 10059476000, 268512812], "tags": {"cycleway:both": "no", "highway": "residential", "lane_markings": "no", "lit": "yes", "maxspeed": "50", "name": "Reifenstra\u00dfe", "noexit": "yes", "sidewalk": "none", "surface": "asphalt"}}, {"type": "way", "id": 24704098, "nodes": [268512813, 10061984676, 268512815, 10061984636, 268512816], "tags": {"cycleway:both": "no", "highway": "residential", "lane_markings": "no", "lit": "yes", "maxspeed": "50", "name": "Laubensteinstra\u00dfe", "sidewalk": "no", "smoothness": "intermediate", "surface": "asphalt", "width": "5.75"}}, {"type": "way", "id": 25479713, "nodes": [60905688, 3333680100, 3333680101, 60643424, 703899812], "tags": {"destination:backward": "M\u00fcnchen|", "highway": "unclassified", "lanes": "3", "lanes:backward": "2", "lanes:forward": "1", "lit": "no", "maxspeed": "100", "name": "Rasthausstra\u00dfe", "sidewalk": "no", "source:maxspeed": "DE:rural", "surface": "asphalt", "turn:lanes:backward": "left|through"}}, {"type": "way", "id": 25479751, "nodes": [268141932, 3333680098, 3333680097, 60905683, 2922598199, 2342045893, 2342045892, 2922598198, 2922598197, 60905688], "tags": {"cycleway:both": "no", "destination": "Felden", "highway": "motorway_link", "lanes": "1", "lit": "no", "oneway": "yes", "surface": "asphalt"}}, {"type": "way", "id": 25479806, "nodes": [17291590, 17291438, 181658882, 268123239, 17291586, 2922598188], "tags": {"bdouble": "yes", "cycleway:both": "no", "highway": "motorway", "int_ref": "E 52;E 60", "lanes": "2", "lit": "no", "maxspeed": "none", "oneway": "yes", "ref": "A 8", "source:maxspeed": "DE:motorway", "surface": "asphalt", "tmc": "DE:12588/12589"}}, {"type": "way", "id": 25479807, "nodes": [17291591, 277646059], "tags": {"bdouble": "yes", "bridge": "yes", "bridge:ref": "8140659 BW 131", "cycleway:both": "no", "highway": "motorway", "int_ref": "E 52;E 60", "lanes": "2", "layer": "1", "lit": "no", "maxspeed": "100", "oneway": "yes", "ref": "A 8", "source:maxspeed": "sign", "surface": "asphalt", "tmc": "DE:12588/12589"}}, {"type": "way", "id": 25479808, "nodes": [277646060, 17291590], "tags": {"bdouble": "yes", "bridge": "yes", "bridge:ref": "8140659 BW 131", "cycleway:both": "no", "highway": "motorway", "int_ref": "E 52;E 60", "lanes": "2", "layer": "1", "lit": "no", "maxspeed": "none", "oneway": "yes", "ref": "A 8", "source:maxspeed": "DE:motorway", "surface": "asphalt", "tmc": "DE:12588/12589"}}, {"type": "way", "id": 41750167, "nodes": [60643432, 60643434, 370894557, 4562343831, 292229948, 292229950], "tags": {"highway": "unclassified", "maxspeed": "30", "name": "Rasthausstra\u00dfe", "sidewalk": "no", "source:maxspeed": "DE:zone:30", "surface": "asphalt"}}, {"type": "way", "id": 41750450, "nodes": [60643413, 699767044, 75316582, 4172227215, 4172237120, 60643415, 1203034333, 4172237119, 4172227211, 75316585, 4172237118, 4860998379, 60643407, 4860998380, 457323847, 4172237117, 4860998394, 75634351, 4860998395, 699767043, 75316586, 4860998396, 4860998397, 4860998398, 60643411, 75316587, 4860998399, 457323848, 4172227212, 4860998361, 4860998362, 4172227214, 60643413], "tags": {"cycleway:both": "no", "highway": "tertiary", "junction": "roundabout", "lane_markings": "no", "surface": "asphalt"}}, {"type": "way", "id": 55821155, "nodes": [701182854, 4860998435, 4860998434, 701182855, 6342657450, 6342657449, 701182856, 703860202, 703860211, 1772972086, 701182860, 703860213, 703860214, 703860215, 703860217, 703860218, 703860219, 8497143024], "tags": {"highway": "residential", "name": "Am F\u00f6rchensee", "surface": "asphalt"}}, {"type": "way", "id": 56081835, "nodes": [373724083, 529783534], "tags": {"highway": "unclassified", "maxspeed": "100", "name": "Rasthausstra\u00dfe", "sidewalk": "right", "source:maxspeed": "DE:rural", "surface": "asphalt"}}, {"type": "way", "id": 56094867, "nodes": [4172227223, 2922598190, 60905689, 60643415], "tags": {"cycleway:both": "no", "highway": "motorway_link", "lanes": "1", "lit": "no", "oneway": "yes", "surface": "asphalt"}}, {"type": "way", "id": 104252498, "nodes": [60905675, 3333680087, 3333680088, 3333680089, 2342045886, 60905677, 2342045888, 2922598192, 60905678, 2342045887, 60909359], "tags": {"cycleway:both": "no", "destination": "Felden", "highway": "motorway_link", "lanes": "1", "lit": "no", "maxheight": "default", "note:detour": "keine Bedarfsumleitung beschildert", "oneway": "yes", "surface": "asphalt"}}, {"type": "way", "id": 104252499, "nodes": [60905685, 2342045891, 60905686, 2924607771, 2342045890, 60905687, 3333680091, 3333680090, 60905676], "tags": {"cycleway:both": "no", "destination:ref": "A 8", "highway": "motorway_link", "lanes": "1", "lit": "no", "oneway": "yes", "surface": "asphalt"}}, {"type": "way", "id": 127574136, "nodes": [17291588, 181658876, 4860998478, 2006514, 4860998477, 17291591], "tags": {"bdouble": "yes", "cycleway:both": "no", "highway": "motorway", "int_ref": "E 52;E 60", "lanes": "2", "lit": "no", "maxspeed": "100", "oneway": "yes", "ref": "A 8", "source:maxspeed": "sign", "surface": "asphalt", "tmc": "DE:12588/12589"}}, {"type": "way", "id": 127574137, "nodes": [60905676, 2922598191, 2922598189], "tags": {"bdouble": "yes", "cycleway:both": "no", "highway": "motorway", "int_ref": "E 52;E 60", "lanes": "3", "lit": "no", "maxheight": "default", "maxspeed": "120", "oneway": "yes", "placement": "right_of:1", "ref": "A 8", "surface": "asphalt", "tmc": "DE:12588/12589", "turn:lanes": "none|none|merge_to_left"}}, {"type": "way", "id": 131994797, "nodes": [60905675, 2922598194, 17291442], "tags": {"bdouble": "yes", "cycleway:both": "no", "highway": "motorway", "int_ref": "E 52;E 60", "lanes": "2", "lit": "no", "maxheight": "default", "maxspeed": "none", "oneway": "yes", "ref": "A 8", "source:maxspeed": "DE:motorway", "surface": "asphalt", "tmc": "DE:12589"}}, {"type": "way", "id": 131994799, "nodes": [292229950, 292229945, 60643439, 60643441, 60643443, 60643445, 60643447], "tags": {"cycleway:left": "no", "cycleway:right": "lane", "cycleway:right:lane": "exclusive", "highway": "unclassified", "lane_markings": "no", "maxspeed": "30", "name": "Rasthausstra\u00dfe", "sidewalk": "no", "source:maxspeed": "DE:zone:30", "surface": "asphalt"}}, {"type": "way", "id": 138296323, "nodes": [17291592, 17291437, 277646060], "tags": {"bdouble": "yes", "cycleway:both": "no", "highway": "motorway", "int_ref": "E 52;E 60", "lanes": "2", "lit": "no", "maxspeed": "none", "oneway": "yes", "ref": "A 8", "source:maxspeed": "DE:motorway", "surface": "asphalt", "tmc": "DE:12588/12589"}}, {"type": "way", "id": 146641269, "nodes": [17291595, 4172604518, 17291436, 4860998480, 4860998481, 4172604519, 4860998479, 17291592], "tags": {"bdouble": "yes", "cycleway:both": "no", "highway": "motorway", "int_ref": "E 52;E 60", "lanes": "2", "lit": "no", "maxspeed": "100", "oneway": "yes", "overtaking:hgv": "no", "ref": "A 8", "source:maxspeed": "sign", "surface": "asphalt", "tmc": "DE:12588/12589"}}, {"type": "way", "id": 149737233, "nodes": [268141932, 60905676], "tags": {"bdouble": "yes", "cycleway:both": "no", "highway": "motorway", "int_ref": "E 52;E 60", "lanes": "2", "lit": "no", "maxspeed": "120", "maxspeed:variable": "no", "oneway": "yes", "ref": "A 8", "surface": "asphalt", "tmc": "DE:12589"}}, {"type": "way", "id": 161209675, "nodes": [529783534, 373724087], "tags": {"highway": "unclassified", "maxheight": "2.4", "maxspeed": "50", "name": "Rasthausstra\u00dfe", "sidewalk": "right", "source:maxspeed": "DE:urban", "surface": "asphalt", "traffic_sign": "DE:265:2.4"}}, {"type": "way", "id": 161209745, "nodes": [703899876, 1731998833, 1731998832, 1731998831, 1731998828, 457323849], "tags": {"highway": "unclassified", "maxspeed": "30", "name": "Rasthausstra\u00dfe", "sidewalk": "no", "source:maxspeed": "DE:zone:30", "surface": "asphalt"}}, {"type": "way", "id": 162969861, "nodes": [60909359, 2922598193, 60905681, 2922598195, 2342045889, 60905682, 2922598196, 3333680096, 3333680099, 17291442], "tags": {"cycleway:both": "no", "destination": "Salzburg", "destination:ref": "A 8", "highway": "motorway_link", "lanes": "1", "lit": "no", "oneway": "yes", "surface": "asphalt"}}, {"type": "way", "id": 228127895, "nodes": [75175370, 9502337168, 60902781, 4860998360, 462190331, 8453999512, 4172240347, 4172240348, 4172240349, 60902790, 4860998464, 703942955, 4172227193], "tags": {"highway": "tertiary", "lanes": "2", "lanes:backward": "1", "maxspeed": "50", "name": "Chiemseestra\u00dfe", "ref": "RO 14", "surface": "asphalt"}}, {"type": "way", "id": 237129120, "nodes": [373724083, 527665341, 704363794, 527665343, 2924616065, 527665345, 527665347, 4170418796, 527665348, 527665351, 4860998414, 527665353, 4860998413, 527665355, 4860998412, 2569545319, 4860998411, 4860998410, 527665356, 4860998409, 527665358, 4860998408, 527665361, 9170423601, 527665363, 4860998407, 4860998406, 4860998403, 527665364, 4860998405, 4860998404, 527665366, 4860998400, 4172227220], "tags": {"hgv": "destination", "highway": "unclassified", "lanes": "2", "lanes:backward": "1", "maxspeed": "30", "name": "Neum\u00fchlstra\u00dfe", "sidewalk": "no", "surface": "asphalt"}}, {"type": "way", "id": 237566818, "nodes": [701182854, 60643460, 4860998440, 4860998439, 4860998436, 60643462, 60902788, 10059435501, 60902787, 1772756587, 1772756585, 10061998429, 1772756582, 704332123, 60902783, 1772756570, 1376213749], "tags": {"access:conditional": "destination @ (weight>7.5)", "hgv": "destination", "highway": "residential", "lit": "yes", "maxspeed": "50", "name": "Hochfellnstra\u00dfe", "surface": "asphalt"}}, {"type": "way", "id": 278563487, "nodes": [2006555, 2829133319], "tags": {"bdouble": "yes", "bridge": "yes", "bridge:ref": "BW 133", "cycleway:both": "no", "highway": "motorway", "int_ref": "E 52;E 60", "lanes": "2", "layer": "1", "lit": "no", "maxspeed": "none", "oneway": "yes", "ref": "A 8", "surface": "asphalt", "tmc": "DE:12589/12590"}}, {"type": "way", "id": 278563495, "nodes": [2829133318, 17291446], "tags": {"bdouble": "yes", "bridge": "yes", "bridge:ref": "BW 133", "cycleway:both": "no", "highway": "motorway", "int_ref": "E 52;E 60", "lanes": "2", "layer": "1", "lit": "no", "maxspeed": "none", "oneway": "yes", "ref": "A 8", "surface": "asphalt", "tmc": "DE:12589/12590"}}, {"type": "way", "id": 278563551, "nodes": [2006568, 2922599030, 17291573, 2922599025, 17291570, 17291575, 2922599020, 2006564, 2922599007, 17291578, 2922599005, 359723779, 2922599003, 2006555], "tags": {"bdouble": "yes", "cycleway:both": "no", "highway": "motorway", "int_ref": "E 52;E 60", "lanes": "2", "lit": "no", "maxspeed": "none", "oneway": "yes", "ref": "A 8", "surface": "asphalt", "tmc": "DE:12589/12590"}}, {"type": "way", "id": 278563553, "nodes": [2829133319, 359723781, 17291581, 2006546, 17291583, 2006536], "tags": {"bdouble": "yes", "cycleway:both": "no", "highway": "motorway", "int_ref": "E 52;E 60", "lanes": "2", "lit": "no", "maxspeed": "none", "oneway": "yes", "ref": "A 8", "surface": "asphalt", "tmc": "DE:12589/12590"}}, {"type": "way", "id": 278563554, "nodes": [17291446, 2922599002, 359723780, 2922599004, 17291580, 2922599006, 17291447, 2922599017, 17291576, 17291572, 2922599024, 17291574, 2922599026, 17291449], "tags": {"bdouble": "yes", "cycleway:both": "no", "highway": "motorway", "int_ref": "E 52;E 60", "lanes": "2", "lit": "no", "maxspeed": "none", "oneway": "yes", "ref": "A 8", "surface": "asphalt", "tmc": "DE:12589/12590"}}, {"type": "way", "id": 288707078, "nodes": [2922598188, 8591891364, 60905675], "tags": {"bdouble": "yes", "cycleway:both": "no", "destination:lanes": "\u00dcbersee|\u00dcbersee|Felden", "highway": "motorway", "int_ref": "E 52;E 60", "lanes": "3", "lit": "no", "maxspeed": "none", "oneway": "yes", "placement": "right_of:1", "ref": "A 8", "source:maxspeed": "DE:motorway", "surface": "asphalt", "tmc": "DE:12588/12589", "turn:lanes": "none|none|slight_right"}}, {"type": "way", "id": 288707079, "nodes": [2922598189, 17291588], "tags": {"bdouble": "yes", "cycleway:both": "no", "highway": "motorway", "int_ref": "E 52;E 60", "lanes": "2", "lit": "no", "maxspeed": "120", "oneway": "yes", "ref": "A 8", "surface": "asphalt", "tmc": "DE:12588/12589"}}, {"type": "way", "id": 288707081, "nodes": [2006536, 2922599001, 359723784, 268141932], "tags": {"bdouble": "yes", "cycleway:both": "no", "destination:lanes": "Bernau|Bernau|Felden", "highway": "motorway", "int_ref": "E 52;E 60", "lanes": "3", "lit": "no", "maxspeed": "none", "oneway": "yes", "placement": "right_of:1", "ref": "A 8", "surface": "asphalt", "tmc": "DE:12589/12590", "turn:lanes": "none|none|slight_right"}}, {"type": "way", "id": 288707082, "nodes": [17291442, 17291443, 2922598200, 359723783], "tags": {"bdouble": "yes", "cycleway:both": "no", "highway": "motorway", "int_ref": "E 52;E 60", "lanes": "3", "lit": "no", "maxspeed": "none", "oneway": "yes", "placement": "right_of:1", "ref": "A 8", "source:maxspeed": "DE:motorway", "surface": "asphalt", "tmc": "DE:12589/12590", "turn:lanes": "none|none|merge_to_left"}}, {"type": "way", "id": 288707084, "nodes": [359723783, 17291585, 17291445, 17291582, 359723782, 2829133318], "tags": {"bdouble": "yes", "cycleway:both": "no", "highway": "motorway", "int_ref": "E 52;E 60", "lanes": "2", "lit": "no", "maxspeed": "none", "oneway": "yes", "ref": "A 8", "surface": "asphalt", "tmc": "DE:12589/12590"}}, {"type": "way", "id": 326695095, "nodes": [60909356, 60905688], "tags": {"destination:backward": "M\u00fcnchen|", "highway": "tertiary", "lanes": "3", "lanes:backward": "2", "maxspeed": "100", "ref": "RO 14", "sidewalk": "no", "source:maxspeed": "DE:rural", "surface": "asphalt", "turn:lanes:backward": "left|through"}}, {"type": "way", "id": 326695098, "nodes": [703899812, 60643428, 370894556], "tags": {"highway": "unclassified", "lanes": "2", "lanes:backward": "1", "lanes:forward": "1", "lit": "yes", "maxspeed": "30", "name": "Rasthausstra\u00dfe", "sidewalk": "no", "source:maxspeed": "DE:zone:30", "surface": "asphalt", "zone:maxspeed": "DE:30"}}, {"type": "way", "id": 326695101, "nodes": [3333680093, 3333680094, 3333680095, 60905685], "tags": {"cycleway:both": "no", "destination:ref": "A 8", "highway": "motorway_link", "lanes": "1", "lit": "no", "oneway": "yes", "surface": "asphalt"}}, {"type": "way", "id": 329013813, "nodes": [703899876, 3358307677, 3358307678, 60643447], "tags": {"highway": "unclassified", "maxspeed": "30", "name": "Rasthausstra\u00dfe", "sidewalk": "no", "source:maxspeed": "DE:zone:30", "surface": "asphalt"}}, {"type": "way", "id": 416479633, "nodes": [4172227193, 4172227197, 4172217010, 4860998382, 75634351], "tags": {"highway": "tertiary", "lanes": "1", "lit": "yes", "maxspeed": "50", "name": "Chiemseestra\u00dfe", "oneway": "yes", "ref": "RO 14", "surface": "asphalt"}}, {"type": "way", "id": 416479634, "nodes": [457323847, 4860998381, 4172227205, 4172227204, 4172227201, 4172227193], "tags": {"cycleway:right": "no", "highway": "tertiary", "lanes": "1", "lit": "yes", "maxspeed": "50", "name": "Chiemseestra\u00dfe", "oneway": "yes", "ref": "RO 14", "sidewalk:left": "no", "sidewalk:right": "separate", "surface": "asphalt"}}, {"type": "way", "id": 416479635, "nodes": [60643454, 4860998391, 4860998390, 4860998389, 4860998388, 4860998387, 60643411], "tags": {"cycleway:both": "no", "highway": "residential", "lanes": "1", "lit": "no", "maxspeed": "100", "name": "Hochfellnstra\u00dfe", "oneway": "yes", "sidewalk": "no", "surface": "asphalt"}}, {"type": "way", "id": 416479636, "nodes": [75316586, 4860998383, 4860998384, 4172227203, 4860998385, 4860998386, 60643454], "tags": {"cycleway:both": "no", "highway": "residential", "lanes": "1", "lit": "no", "mapillary": "471111424150446", "maxspeed": "100", "name": "Hochfellnstra\u00dfe", "oneway": "yes", "sidewalk:left": "no", "sidewalk:right": "separate", "surface": "asphalt"}}, {"type": "way", "id": 416479637, "nodes": [4172227220, 527665367, 4860998402, 60643413], "tags": {"highway": "unclassified", "lanes": "1", "maxspeed": "30", "name": "Neum\u00fchlstra\u00dfe", "oneway": "yes", "surface": "asphalt"}}, {"type": "way", "id": 416479638, "nodes": [4172227212, 4172227216, 4172227218, 4860998401, 4172227220], "tags": {"highway": "unclassified", "lanes": "1", "maxspeed": "30", "name": "Neum\u00fchlstra\u00dfe", "oneway": "yes", "surface": "asphalt"}}, {"type": "way", "id": 416479639, "nodes": [4172227206, 457321167, 4860998376, 60643417], "tags": {"highway": "tertiary", "lanes": "2", "lanes:backward": "1", "ref": "RO 14", "surface": "asphalt"}}, {"type": "way", "id": 416479640, "nodes": [4172227211, 4172227210, 4172227209, 4172227208, 4172227207, 4172227206], "tags": {"cycleway:right": "no", "highway": "tertiary", "lanes": "1", "oneway": "yes", "ref": "RO 14", "surface": "asphalt"}}, {"type": "way", "id": 416479641, "nodes": [60909359, 4172227223], "tags": {"cycleway:both": "no", "destination:backward": "Salzburg", "highway": "motorway_link", "lanes": "2", "lanes:backward": "1", "lanes:forward": "1", "lit": "no", "oneway": "no", "surface": "asphalt"}}, {"type": "way", "id": 416479642, "nodes": [4172227215, 4172227217, 4172227219, 4172227221, 4172227222, 4172227223], "tags": {"cycleway:both": "no", "destination": "Salzburg", "highway": "motorway_link", "lanes": "1", "lit": "no", "oneway": "yes", "surface": "asphalt"}}, {"type": "way", "id": 430031729, "nodes": [4292889902, 268511739], "tags": {"cycleway": "both", "highway": "tertiary", "lanes": "3", "lanes:backward": "1", "lanes:forward": "2", "maxspeed": "50", "name": "Chiemseestra\u00dfe", "ref": "RO 14", "sidewalk": "both", "surface": "asphalt", "turn:lanes:forward": "left|through"}}, {"type": "way", "id": 430031731, "nodes": [268511739, 60902780, 75175366], "tags": {"cycleway:both": "track", "cycleway:both:segregated": "no", "highway": "tertiary", "lanes": "2", "lit": "yes", "maxspeed": "50", "name": "Chiemseestra\u00dfe", "ref": "RO 14", "sidewalk": "both", "surface": "asphalt"}}, {"type": "way", "id": 460608030, "nodes": [373724087, 703899876], "tags": {"highway": "unclassified", "maxspeed": "30", "name": "Rasthausstra\u00dfe", "sidewalk": "right", "source:maxspeed": "DE:zone:30", "surface": "asphalt"}}, {"type": "way", "id": 460612618, "nodes": [60643447, 3464794043, 60643449, 3464794042, 3464794041, 2450744055, 457323849], "tags": {"highway": "unclassified", "maxspeed": "30", "name": "Rasthausstra\u00dfe", "sidewalk": "no", "source:maxspeed": "DE:zone:30", "surface": "asphalt"}}, {"type": "way", "id": 630331098, "nodes": [1376213749, 60902782, 1376213747, 1772756555, 60643466], "tags": {"highway": "residential", "lane_markings": "no", "lit": "yes", "maxspeed": "50", "name": "Hochfellnstra\u00dfe", "surface": "asphalt"}}, {"type": "way", "id": 630331099, "nodes": [703860237, 4242544500, 1579617810, 4242544508, 703899895, 4242544502, 703899890, 373724078, 4242543278, 703899892, 703899886, 1772972454, 1772972442, 703899888, 373724083], "tags": {"highway": "unclassified", "maxspeed": "30", "name": "Neum\u00fchlstra\u00dfe", "sidewalk": "no", "smoothness": "excellent", "surface": "asphalt"}}, {"type": "way", "id": 630331100, "nodes": [1772010624, 4860998456, 60643458, 701182854], "tags": {"access:conditional": "destination @ (weight>7.5)", "cycleway:both": "no", "hgv": "destination", "highway": "residential", "lane_markings": "no", "lit": "yes", "maxspeed": "50", "name": "Hochfellnstra\u00dfe", "sidewalk": "right", "surface": "asphalt"}}, {"type": "way", "id": 914719642, "nodes": [8497143024, 8497143025], "tags": {"highway": "residential", "name": "Am F\u00f6rchensee", "surface": "asphalt"}}, {"type": "way", "id": 914719643, "nodes": [8497143025, 703860220], "tags": {"highway": "residential", "name": "Am F\u00f6rchensee", "surface": "asphalt"}}, {"type": "way", "id": 1056516256, "nodes": [370894556, 60643430, 703899853, 60643432], "tags": {"highway": "unclassified", "maxspeed": "30", "name": "Rasthausstra\u00dfe", "sidewalk": "no", "source:maxspeed": "DE:zone:30", "surface": "asphalt"}}, {"type": "way", "id": 1098340284, "nodes": [60902812, 60902860, 10054628618, 3304796932, 60902808], "tags": {"cycleway:both": "no", "highway": "residential", "lane_markings": "no", "lit": "yes", "maxspeed": "50", "name": "Klausenstra\u00dfe", "sidewalk": "none", "surface": "asphalt"}}]}